Workbook

Sheet RABONA PAYMENTS
N2: =290.79-123 -> 167.79 | AD2: REIMBURSE FROM / PRORATE TO
N3: REPORT | O3: JANUARY 2026 | AG3: REIMBURSEMENT OF EXPENSES TO EMPLOYEES | AH3: PERSONAL EXPENSES PAID BY COMPANY
C4: 26/1/
Z5: SHARE HOLDER | AA5: REIMBURSE | AD5: REIMBURSE | AE5: REIMBURSE | AG5: CASH | AH5: SHARE HOLDER
B6: REF. NO: MONTH RECEIVED | C6: REF. NO. MONTH PAID | D6: REF. NO: MONTH PAID | E6: ACCOUNT PAID FROM | F6: INWARDS/ OUTWARDS | G6: EXPENSE OF | H6: REF. NO: Travel exp. | I6: REF. NO: Exp. Reimb. | J6: REF. NO: Salaries | K6: INWARDS TRANSFER REFERENCE | L6: INVOICE DATE | M6: MONTH ISSUED | N6: COMPANY | O6: ITEM | P6: SUBCATEGORY | Q6: CATEGORY | R6: TOTAL AMOUNT foreign currency | S6: TOTAL AMOUNT (EURO) | T6: AMOUNT PAID | U6: AMOUNT RECEIVED | V6: DATE PAID / DATE RECEIVED …. | W6: MONTH PAYED | X6: TOTAL PAID (EURO) | Y6: BALANCE (EURO) | Z6: PAYMENT TYPE …. | AA6: EXPENSE OF …. | AB6: STATUS | AC6: COMMENTS …. | AD6: REIMBURSE FROM/ PRORATE TO | AE6: TOTAL AMOUNT (EURO) | AF6: INVOICE NUMBER | AG6: TOTAL AMOUNT Incl. VAT (EURO) | AH6: AMOUNT | AI6: EXPENSES PAID IN CASH BY
B7: 25/7/3 | E7: CURRENT A/C | F7: OUT | G7: RABONA | J7: S7/3 | L7: 45839 | M7: =L7 -> 45839 | N7: SOCIAL INSURANCE | O7: JUNE 2025 | P7: SOCIAL INSURANCE | Q7: COST OF LABOR | S7: 671.25 | U7: 0 | W7: =V7 -> 0 | X7: =T7+U7 -> 0 | Y7: =S7-X7 -> 671.25 | Z7: BT | AA7: RABONA | AB7: =IF(Y7>0,"PENDING EXECUTION","COMPLETED") -> PENDING EXECUTION | AE7: =IF(AA7=$AD$5,S7,0) -> 0 | AG7: =IF(Z7=$AG$5,X7,0) -> 0 | AH7: =IF(AA7=$AH$5,X7,0) -> 0
B8: 25/8/3 | E8: CURRENT A/C | F8: OUT | G8: RABONA | J8: S8/3 | L8: 45870 | M8: =L8 -> 45870 | N8: SOCIAL INSURANCE | O8: JULY 2025 | P8: SOCIAL INSURANCE | Q8: COST OF LABOR | S8: 671.25 | U8: 0 | W8: =V8 -> 0 | X8: =T8+U8 -> 0 | Y8: =S8-X8 -> 671.25 | Z8: BT | AA8: =G8 -> RABONA | AB8: =IF(Y8>0,"PENDING EXECUTION","COMPLETED") -> PENDING EXECUTION | AE8: =IF(AA8=$AD$5,S8,0) -> 0 | AG8: =IF(Z8=$AG$5,X8,0) -> 0 | AH8: =IF(AA8=$AH$5,X8,0) -> 0
B9: 25/9/3 | E9: CURRENT A/C | F9: OUT | G9: RABONA | J9: S9/3 | L9: 45901 | M9: =L9 -> 45901 | N9: SOCIAL INSURANCE | O9: AUGUST 2025 | P9: SOCIAL INSURANCE | Q9: COST OF LABOR | S9: 671.25 | U9: 0 | W9: =V9 -> 0 | X9: =T9+U9 -> 0 | Y9: =S9-X9 -> 671.25 | Z9: BT | AA9: =G9 -> RABONA | AB9: =IF(Y9>0,"PENDING EXECUTION","COMPLETED") -> PENDING EXECUTION | AE9: =IF(AA9=$AD$5,S9,0) -> 0 | AG9: =IF(Z9=$AG$5,X9,0) -> 0 | AH9: =IF(AA9=$AH$5,X9,0) -> 0
B10: 25/10/3 | E10: CURRENT A/C | F10: OUT | G10: RABONA | J10: S10/3 | L10: 45931 | M10: =L10 -> 45931 | N10: SOCIAL INSURANCE | O10: SEPTEMBER 2025 | P10: SOCIAL INSURANCE | Q10: COST OF LABOR | S10: 671.25 | U10: 0 | W10: =V10 -> 0 | X10: =T10+U10 -> 0 | Y10: =S10-X10 -> 671.25 | Z10: BT | AA10: =G10 -> RABONA | AB10: =IF(Y10>0,"PENDING EXECUTION","COMPLETED") -> PENDING EXECUTION | AE10: =IF(AA10=$AD$5,S10,0) -> 0 | AG10: =IF(Z10=$AG$5,X10,0) -> 0 | AH10: =IF(AA10=$AH$5,X10,0) -> 0
B11: 25/11/1 | E11: CURRENT A/C | F11: OUT | G11: RABONA | J11: S11/1 | L11: 45962 | M11: =L11 -> 45962 | N11: BETIJA KEDEM | O11: B.KEDEM SALARY NOVEMBER 2025 | P11: SALARY BK | Q11: COST OF LABOR | S11: 2142.75 | T11: 2142.75 | U11: 0 | V11: 46030 | W11: =V11 -> 46030 | X11: =T11+U11 -> 2142.75 | Y11: =S11-X11 -> 0 | Z11: BT | AA11: =G11 -> RABONA | AB11: =IF(Y11>0,"PENDING EXECUTION","COMPLETED") -> COMPLETED | AE11: =IF(AA11=$AD$5,S11,0) -> 0 | AG11: =IF(Z11=$AG$5,X11,0) -> 0 | AH11: =IF(AA11=$AH$5,X11,0) -> 0
B12: 25/11/3 | E12: CURRENT A/C | F12: OUT | G12: RABONA | J12: S11/3 | L12: 45962 | M12: =L12 -> 45962 | N12: SOCIAL INSURANCE | O12: OCTOBER 2025 | P12: SOCIAL INSURANCE | Q12: COST OF LABOR | S12: 671.25 | U12: 0 | W12: =V12 -> 0 | X12: =T12+U12 -> 0 | Y12: =S12-X12 -> 671.25 | Z12: BT | AA12: =G12 -> RABONA | AB12: =IF(Y12>0,"PENDING EXECUTION","COMPLETED") -> PENDING EXECUTION | AE12: =IF(AA12=$AD$5,S12,0) -> 0 | AG12: =IF(Z12=$AG$5,X12,0) -> 0 | AH12: =IF(AA12=$AH$5,X12,0) -> 0
B13: 25/12/1 | E13: CURRENT A/C | F13: OUT | G13: RABONA | J13: S12/1 | L13: 45992 | M13: =L13 -> 45992 | N13: BETIJA KEDEM | O13: B.KEDEM SALARY DECEMBER 2025 | P13: SALARY BK | Q13: COST OF LABOR | S13: 2142.75 | U13: 0 | W13: =V13 -> 0 | X13: =T13+U13 -> 0 | Y13: =S13-X13 -> 2142.75 | Z13: BT | AA13: =G13 -> RABONA | AB13: =IF(Y13>0,"PENDING EXECUTION","COMPLETED") -> PENDING EXECUTION | AE13: =IF(AA13=$AD$5,S13,0) -> 0 | AG13: =IF(Z13=$AG$5,X13,0) -> 0 | AH13: =IF(AA13=$AH$5,X13,0) -> 0
B14: 25/12/2 | E14: CURRENT A/C | F14: OUT | G14: RABONA | J14: S12/2 | L14: 45992 | M14: =L14 -> 45992 | N14: PAYE | O14: NOVEMBER 2025 | P14: PAYE | Q14: COST OF LABOR | S14: 71 | U14: 0 | W14: =V14 -> 0 | X14: =T14+U14 -> 0 | Y14: =S14-X14 -> 71 | Z14: BT | AA14: =G14 -> RABONA | AB14: =IF(Y14>0,"PENDING EXECUTION","COMPLETED") -> PENDING EXECUTION | AE14: =IF(AA14=$AD$5,S14,0) -> 0 | AG14: =IF(Z14=$AG$5,X14,0) -> 0 | AH14: =IF(AA14=$AH$5,X14,0) -> 0
B15: 25/12/3 | E15: CURRENT A/C | F15: OUT | G15: RABONA | J15: S12/3 | L15: 45992 | M15: =L15 -> 45992 | N15: SOCIAL INSURANCE | O15: NOVEMBER 2025 | P15: SOCIAL INSURANCE | Q15: COST OF LABOR | S15: 671.25 | U15: 0 | W15: =V15 -> 0 | X15: =T15+U15 -> 0 | Y15: =S15-X15 -> 671.25 | Z15: BT | AA15: =G15 -> RABONA | AB15: =IF(Y15>0,"PENDING EXECUTION","COMPLETED") -> PENDING EXECUTION | AE15: =IF(AA15=$AD$5,S15,0) -> 0 | AG15: =IF(Z15=$AG$5,X15,0) -> 0 | AH15: =IF(AA15=$AH$5,X15,0) -> 0
C16: =IF(A7=0,$C$4,"-") -> 26/1/ | D16: 1 | E16: CURRENT A/C | F16: OUT | G16: RABONA | J16: S1/1 | L16: 46023 | M16: =L16 -> 46023 | N16: BETIJA KEDEM | O16: B.KEDEM SALARY JANUARY 2026 | P16: SALARY BK | Q16: COST OF LABOR | S16: 2142.75 | U16: 0 | W16: =V16 -> 0 | X16: =T16+U16 -> 0 | Y16: =S16-X16 -> 2142.75 | Z16: BT | AA16: =G16 -> RABONA | AB16: =IF(Y16>0,"PENDING EXECUTION","COMPLETED") -> PENDING EXECUTION | AE16: =IF(AA16=$AD$5,S16,0) -> 0 | AG16: =IF(Z16=$AG$5,X16,0) -> 0 | AH16: =IF(AA16=$AH$5,X16,0) -> 0
C17: =IF(A8=0,$C$4,"-") -> 26/1/ | D17: 2 | E17: CURRENT A/C | F17: OUT | G17: RABONA | J17: S1/2 | L17: 46023 | M17: =L17 -> 46023 | N17: PAYE | O17: DECEMBER 2025 | P17: PAYE | Q17: COST OF LABOR | S17: 71 | U17: 0 | W17: =V17 -> 0 | X17: =T17+U17 -> 0 | Y17: =S17-X17 -> 71 | Z17: BT | AA17: =G17 -> RABONA | AB17: =IF(Y17>0,"PENDING EXECUTION","COMPLETED") -> PENDING EXECUTION | AE17: =IF(AA17=$AD$5,S17,0) -> 0 | AG17: =IF(Z17=$AG$5,X17,0) -> 0 | AH17: =IF(AA17=$AH$5,X17,0) -> 0
C18: =IF(A9=0,$C$4,"-") -> 26/1/ | D18: 3 | E18: CURRENT A/C | F18: OUT | G18: RABONA | J18: S1/3 | L18: 46023 | M18: =L18 -> 46023 | N18: SOCIAL INSURANCE | O18: DECEMBER 2025 | P18: SOCIAL INSURANCE | Q18: COST OF LABOR | S18: 671.25 | U18: 0 | W18: =V18 -> 0 | X18: =T18+U18 -> 0 | Y18: =S18-X18 -> 671.25 | Z18: BT | AA18: =G18 -> RABONA | AB18: =IF(Y18>0,"PENDING EXECUTION","COMPLETED") -> PENDING EXECUTION | AE18: =IF(AA18=$AD$5,S18,0) -> 0 | AG18: =IF(Z18=$AG$5,X18,0) -> 0 | AH18: =IF(AA18=$AH$5,X18,0) -> 0
C19: =IF(A8=0,$C$4,"-") -> 26/1/ | D19: 4 | E19: CURRENT A/C | F19: IN | G19: RABONA | K19: A | L19: 46020 | M19: =L19 -> 46020 | N19: INWARDS TRANSFER FROM SUNDAY LIFESTILE SLU INV NO 2025/12/004 | O19: CONSULTING SERVICES for project KYPSELI DECEBER FEE 2025 | P19: CONSULTING SERVICES | Q19: REVENUE | S19: 6000 | U19: =S19 -> 6000 | V19: 46029 | W19: =V19 -> 46029 | X19: =T19+U19 -> 6000 | Y19: =S19-X19 -> 0 | Z19: BT | AA19: =G19 -> RABONA | AB19: =IF(Y19>0,"PENDING EXECUTION","COMPLETED") -> COMPLETED | AC19: INWARDS TRANSFER | AE19: =IF(AA19=$AD$5,S19,0) -> 0 | AG19: =IF(Z19=$AG$5,X19,0) -> 0 | AH19: =IF(AA19=$AH$5,X19,0) -> 0
C20: =IF(A19=0,$C$4,"-") -> 26/1/ | D20: 5 | E20: CURRENT A/C | F20: IN | G20: RABONA | K20: B | L20: 46020 | M20: =L20 -> 46020 | N20: INWARDS TRANSFER FROM OZ SHLOMI SINGLE MEMBER S.A.INV. NO: 2025/12/005 | O20: CONSULTING SERVICES for project GREEN FIELD HOTEL DECEMBER FEE 2025 | P20: CONSULTING SERVICES | Q20: REVENUE | S20: 3500 | U20: =S20 -> 3500 | V20: 46041 | W20: =V20 -> 46041 | X20: =T20+U20 -> 3500 | Y20: =S20-X20 -> 0 | Z20: BT | AA20: =G20 -> RABONA | AB20: =IF(Y20>0,"PENDING EXECUTION","COMPLETED") -> COMPLETED | AC20: INWARDS TRANSFER | AE20: =IF(AA20=$AD$5,S20,0) -> 0 | AG20: =IF(Z20=$AG$5,X20,0) -> 0 | AH20: =IF(AA20=$AH$5,X20,0) -> 0
C21: =IF(A20=0,$C$4,"-") -> 26/1/ | D21: 6 | E21: CURRENT A/C | F21: IN | G21: RABONA | K21: C | L21: 46029 | M21: =L21 -> 46029 | N21: YORAM KEDEM | O21: INVESTMENT FROM SHARE HOLDER | P21: BANK TRANSFERS/CASH DEPOSITS (YK) | Q21: INVESTMENT (SHARE HOLDER'S ACCOUNT) | S21: 8100 | U21: =S21 -> 8100 | V21: 46029 | W21: =V21 -> 46029 | X21: =T21+U21 -> 8100 | Y21: =S21-X21 -> 0 | Z21: CASH | AA21: =G21 -> RABONA | AB21: =IF(Y21>0,"PENDING EXECUTION","COMPLETED") -> COMPLETED | AC21: INWARDS TRANSFER | AE21: =IF(AA21=$AD$5,S21,0) -> 0 | AG21: =IF(Z21=$AG$5,X21,0) -> 8100 | AH21: =IF(AA21=$AH$5,X21,0) -> 0 | AI21: EXPENSES PAID CASH YK
C22: =IF(A21=0,$C$4,"-") -> 26/1/ | D22: 7 | E22: CURRENT A/C | F22: IN | G22: RABONA | K22: D | L22: 46048 | M22: =L22 -> 46048 | N22: INWARDS TRANSFER FROM BTS REAL ESTATE INV. NO: 2026/01/002 | O22: project BLUE LAGOON FIXED EXPENSES JANUARY FIXED EXPENSES 2026 | P22: REIMBURSMENT OF PROCURE AND RUNNING EXPENSES | Q22: REVENUE | S22: 1200 | U22: =S22 -> 1200 | V22: 46052 | W22: =V22 -> 46052 | X22: =T22+U22 -> 1200 | Y22: =S22-X22 -> 0 | Z22: BT | AA22: =G22 -> RABONA | AB22: =IF(Y22>0,"PENDING EXECUTION","COMPLETED") -> COMPLETED | AC22: INWARDS TRANSFER | AE22: =IF(AA22=$AD$5,S22,0) -> 0 | AG22: =IF(Z22=$AG$5,X22,0) -> 0 | AH22: =IF(AA22=$AH$5,X22,0) -> 0
C23: =IF(A22=0,$C$4,"-") -> 26/1/ | D23: 8 | E23: CURRENT A/C | F23: IN | G23: RABONA | K23: E | L23: 46048 | M23: =L23 -> 46048 | N23: INWARDS TRANSFER FROM BTS REAL ESTATE INV. NO: 2026/01/001 | O23: CONSULTING SERVICES for project BLUE LAGOON JANUARY FEES 2026 | P23: CONSULTING SERVICES | Q23: REVENUE | S23: 5000 | U23: =S23 -> 5000 | V23: 46052 | W23: =V23 -> 46052 | X23: =T23+U23 -> 5000 | Y23: =S23-X23 -> 0 | Z23: BT | AA23: =G23 -> RABONA | AB23: =IF(Y23>0,"PENDING EXECUTION","COMPLETED") -> COMPLETED | AC23: INWARDS TRANSFER | AE23: =IF(AA23=$AD$5,S23,0) -> 0 | AG23: =IF(Z23=$AG$5,X23,0) -> 0 | AH23: =IF(AA23=$AH$5,X23,0) -> 0
C24: =IF(A23=0,$C$4,"-") -> 26/1/ | D24: 9 | E24: CURRENT A/C | F24: IN | G24: RABONA | K24: F | L24: 46048 | M24: =L24 -> 46048 | N24: INWARDS TRANSFER FROM EVIMER LTD INV. NO: 2026/01/003 | O24: CONSULTING SERVICES for project URBAN CITY JANUARY 2026 | P24: CONSULTING SERVICES | Q24: REVENUE | S24: 11900 | U24: =S24 -> 11900 | V24: 46052 | W24: =V24 -> 46052 | X24: =T24+U24 -> 11900 | Y24: =S24-X24 -> 0 | Z24: BT | AA24: =G24 -> RABONA | AB24: =IF(Y24>0,"PENDING EXECUTION","COMPLETED") -> COMPLETED | AC24: INWARDS TRANSFER | AE24: =IF(AA24=$AD$5,S24,0) -> 0 | AG24: =IF(Z24=$AG$5,X24,0) -> 0 | AH24: =IF(AA24=$AH$5,X24,0) -> 0
C25: =IF(A24=0,$C$4,"-") -> 26/1/ | D25: 10 | E25: CURRENT A/C | F25: IN | G25: RABONA | K25: G | L25: 46048 | M25: =L25 -> 46048 | N25: INWARDS TRANSFER FROM EVIMER LTD INV. NO: 2026/01/006 | O25: REIMBURSMENTS OF EXPENSES project URBAN CITY NOVEMBER 2025 | P25: REIMBURSMENT OF PROCURE AND RUNNING EXPENSES | Q25: REVENUE | S25: 729 | U25: =S25 -> 729 | V25: 46052 | W25: =V25 -> 46052 | X25: =T25+U25 -> 729 | Y25: =S25-X25 -> 0 | Z25: BT | AA25: =G25 -> RABONA | AB25: =IF(Y25>0,"PENDING EXECUTION","COMPLETED") -> COMPLETED | AC25: INWARDS TRANSFER | AE25: =IF(AA25=$AD$5,S25,0) -> 0 | AG25: =IF(Z25=$AG$5,X25,0) -> 0 | AH25: =IF(AA25=$AH$5,X25,0) -> 0
C26: =IF(A25=0,$C$4,"-") -> 26/1/ | D26: 11 | E26: CURRENT A/C | F26: IN | G26: RABONA | K26: H | L26: 46048 | M26: =L26 -> 46048 | N26: INWARDS TRANSFER FROM OZ SHLOMI SINGLE MEMBER S.A.INV. NO: 2026/01/005 | O26: CONSULTING SERVICES for project GREEN FIELD HOTEL JANUARY FEE 2026 | P26: CONSULTING SERVICES | Q26: REVENUE | S26: 3500 | U26: =S26 -> 3500 | V26: 46052 | W26: =V26 -> 46052 | X26: =T26+U26 -> 3500 | Y26: =S26-X26 -> 0 | Z26: BT | AA26: =G26 -> RABONA | AB26: =IF(Y26>0,"PENDING EXECUTION","COMPLETED") -> COMPLETED | AC26: INWARDS TRANSFER | AE26: =IF(AA26=$AD$5,S26,0) -> 0 | AG26: =IF(Z26=$AG$5,X26,0) -> 0 | AH26: =IF(AA26=$AH$5,X26,0) -> 0
C27: =IF(A26=0,$C$4,"-") -> 26/1/ | D27: 12 | E27: MASTER CARD A/C | F27: IN | G27: RABONA | K27: I | L27: 46052 | M27: =L27 -> 46052 | N27: RABONA | O27: TRANSFER FROM RABONA CURRENT A/S TO RABONA MASTER CARD A/C | P27: MOVEMENT FROM CURRENT A/C TO MASTER CARD A/C | Q27: MOVEMENT FROM CURRENT A/C TO MASTER CARD A/C | S27: 1500 | U27: 0 | V27: 46052 | W27: =V27 -> 46052 | X27: =T27+U27 -> 0 | Y27: =S27-X27 -> 1500 | Z27: BT | AA27: =G27 -> RABONA | AB27: =IF(Y27>0,"PENDING EXECUTION","COMPLETED") -> PENDING EXECUTION | AC27: MOVEMENT BETWEEN A/C | AE27: =IF(AA27=$AD$5,S27,0) -> 0 | AG27: =IF(Z27=$AG$5,X27,0) -> 0 | AH27: =IF(AA27=$AH$5,X27,0) -> 0
C28: =IF(A27=0,$C$4,"-") -> 26/1/ | D28: 13 | E28: MASTER CARD A/C | F28: IN | G28: RABONA | K28: J | L28: 46052 | M28: =L28 -> 46052 | N28: RABONA | O28: TRANSFER FROM RABONA CURRENT A/S TO RABONA MASTER CARD A/C | P28: MOVEMENT FROM CURRENT A/C TO MASTER CARD A/C | Q28: MOVEMENT FROM CURRENT A/C TO MASTER CARD A/C | S28: 1000 | U28: 0 | V28: 46052 | W28: =V28 -> 46052 | X28: =T28+U28 -> 0 | Y28: =S28-X28 -> 1000 | Z28: BT | AA28: =G28 -> RABONA | AB28: =IF(Y28>0,"PENDING EXECUTION","COMPLETED") -> PENDING EXECUTION | AC28: MOVEMENT BETWEEN A/C | AE28: =IF(AA28=$AD$5,S28,0) -> 0 | AG28: =IF(Z28=$AG$5,X28,0) -> 0 | AH28: =IF(AA28=$AH$5,X28,0) -> 0
C29: =IF(A28=0,$C$4,"-") -> 26/1/ | D29: 14 | E29: MASTER CARD A/C | F29: IN | G29: RABONA | K29: K | L29: 46023 | M29: =L29 -> 46023 | N29: RABONA | O29: TRANSFER FROM RABONA CURRENT A/S TO RABONA MASTER CARD A/C | P29: MOVEMENT FROM CURRENT A/C TO MASTER CARD A/C | Q29: MOVEMENT FROM CURRENT A/C TO MASTER CARD A/C | S29: 1000 | U29: 0 | V29: 46052 | W29: =V29 -> 46052 | X29: =T29+U29 -> 0 | Y29: =S29-X29 -> 1000 | Z29: BT | AA29: =G29 -> RABONA | AB29: =IF(Y29>0,"PENDING EXECUTION","COMPLETED") -> PENDING EXECUTION | AC29: MOVEMENT BETWEEN A/C | AE29: =IF(AA29=$AD$5,S29,0) -> 0 | AG29: =IF(Z29=$AG$5,X29,0) -> 0 | AH29: =IF(AA29=$AH$5,X29,0) -> 0
C30: =IF(A29=0,$C$4,"-") -> 26/1/ | D30: 15 | E30: MASTER CARD A/C | F30: IN | G30: RABONA | K30: L | L30: 46026 | M30: =L30 -> 46026 | N30: RABONA | O30: TRANSFER FROM RABONA CURRENT A/S TO RABONA MASTER CARD A/C | P30: MOVEMENT FROM CURRENT A/C TO MASTER CARD A/C | Q30: MOVEMENT FROM CURRENT A/C TO MASTER CARD A/C | S30: 1000 | U30: 0 | V30: 46052 | W30: =V30 -> 46052 | X30: =T30+U30 -> 0 | Y30: =S30-X30 -> 1000 | Z30: BT | AA30: =G30 -> RABONA | AB30: =IF(Y30>0,"PENDING EXECUTION","COMPLETED") -> PENDING EXECUTION | AC30: MOVEMENT BETWEEN A/C | AE30: =IF(AA30=$AD$5,S30,0) -> 0 | AG30: =IF(Z30=$AG$5,X30,0) -> 0 | AH30: =IF(AA30=$AH$5,X30,0) -> 0
C31: =IF(A30=0,$C$4,"-") -> 26/1/ | D31: 16 | E31: CURRENT A/C | F31: IN | G31: RABONA | K31: M | L31: 46035 | M31: =L31 -> 46035 | N31: INWARDS TRANSFER FROM SHA (YORAM KEDEM) | O31: INVESTMENT FROM SHARE HOLDER | P31: BANK TRANSFERS/CASH DEPOSITS (YK) | Q31: INVESTMENT (SHARE HOLDER'S ACCOUNT) | S31: 150 | U31: =S31 -> 150 | V31: =L31 -> 46035 | W31: =V31 -> 46035 | X31: =T31+U31 -> 150 | Y31: =S31-X31 -> 0 | Z31: CASH | AA31: =G31 -> RABONA | AB31: =IF(Y31>0,"PENDING EXECUTION","COMPLETED") -> COMPLETED | AC31: INWARDS TRANSFER | AE31: =IF(AA31=$AD$5,S31,0) -> 0 | AG31: =IF(Z31=$AG$5,X31,0) -> 150 | AH31: =IF(AA31=$AH$5,X31,0) -> 0 | AI31: EXPENSES PAID CASH YK
C32: =IF(A31=0,$C$4,"-") -> 26/1/ | D32: 17 | E32: CURRENT A/C | F32: IN | G32: RABONA | K32: N | L32: 46035 | M32: =L32 -> 46035 | N32: INWARDS TRANSFER FROM SHA (YORAM KEDEM) | O32: INVESTMENT FROM SHARE HOLDER | P32: BANK TRANSFERS/CASH DEPOSITS (YK) | Q32: INVESTMENT (SHARE HOLDER'S ACCOUNT) | S32: 200 | U32: =S32 -> 200 | V32: =L32 -> 46035 | W32: =V32 -> 46035 | X32: =T32+U32 -> 200 | Y32: =S32-X32 -> 0 | Z32: CASH | AA32: =G32 -> RABONA | AB32: =IF(Y32>0,"PENDING EXECUTION","COMPLETED") -> COMPLETED | AC32: INWARDS TRANSFER | AE32: =IF(AA32=$AD$5,S32,0) -> 0 | AG32: =IF(Z32=$AG$5,X32,0) -> 200 | AH32: =IF(AA32=$AH$5,X32,0) -> 0 | AI32: EXPENSES PAID CASH YK
C33: =IF(A32=0,$C$4,"-") -> 26/1/ | D33: 18 | E33: MASTER CARD A/C | F33: IN | G33: RABONA | K33: O | L33: 46030 | M33: =L33 -> 46030 | N33: RABONA | O33: TRANSFER FROM RABONA CURRENT A/S TO RABONA MASTER CARD A/C | P33: MOVEMENT FROM CURRENT A/C TO MASTER CARD A/C | Q33: MOVEMENT FROM CURRENT A/C TO MASTER CARD A/C | S33: 2000 | U33: 0 | V33: 46030 | W33: =V33 -> 46030 | X33: =T33+U33 -> 0 | Y33: =S33-X33 -> 2000 | Z33: BT | AA33: =G33 -> RABONA | AB33: =IF(Y33>0,"PENDING EXECUTION","COMPLETED") -> PENDING EXECUTION | AC33: MOVEMENT BETWEEN A/C | AE33: =IF(AA33=$AD$5,S33,0) -> 0 | AG33: =IF(Z33=$AG$5,X33,0) -> 0 | AH33: =IF(AA33=$AH$5,X33,0) -> 0
C34: =IF(A33=0,$C$4,"-") -> 26/1/ | D34: 19 | E34: CURRENT A/C | F34: IN | G34: RABONA | K34: P | L34: 46041 | M34: =L34 -> 46041 | N34: YORAM KEDEM | O34: INVESTMENT FROM SHARE HOLDER | P34: BANK TRANSFERS/CASH DEPOSITS (YK) | Q34: INVESTMENT (SHARE HOLDER'S ACCOUNT) | S34: 500 | U34: =S34 -> 500 | V34: 46041 | W34: =V34 -> 46041 | X34: =T34+U34 -> 500 | Y34: =S34-X34 -> 0 | Z34: CASH | AA34: =G34 -> RABONA | AB34: =IF(Y34>0,"PENDING EXECUTION","COMPLETED") -> COMPLETED | AC34: INWARDS TRANSFER | AE34: =IF(AA34=$AD$5,S34,0) -> 0 | AG34: =IF(Z34=$AG$5,X34,0) -> 500 | AH34: =IF(AA34=$AH$5,X34,0) -> 0 | AI34: EXPENSES PAID CASH YK
C35: =IF(A34=0,$C$4,"-") -> 26/1/ | D35: 20 | E35: MASTER CARD A/C | F35: IN | G35: RABONA | K35: R | L35: 46040 | M35: =L35 -> 46040 | N35: RABONA | O35: TRANSFER FROM RABONA CURRENT A/S TO RABONA MASTER CARD A/C | P35: MOVEMENT FROM CURRENT A/C TO MASTER CARD A/C | Q35: MOVEMENT FROM CURRENT A/C TO MASTER CARD A/C | S35: 60 | U35: 0 | V35: =L35 -> 46040 | W35: =V35 -> 46040 | X35: =T35+U35 -> 0 | Y35: =S35-X35 -> 60 | Z35: BT | AA35: =G35 -> RABONA | AB35: =IF(Y35>0,"PENDING EXECUTION","COMPLETED") -> PENDING EXECUTION | AC35: MOVEMENT BETWEEN A/C | AE35: =IF(AA35=$AD$5,S35,0) -> 0 | AG35: =IF(Z35=$AG$5,X35,0) -> 0 | AH35: =IF(AA35=$AH$5,X35,0) -> 0
C36: =IF(A35=0,$C$4,"-") -> 26/1/ | D36: 21 | E36: MASTER CARD A/C | F36: IN | G36: RABONA | K36: S | L36: 46041 | M36: =L36 -> 46041 | N36: RABONA | O36: TRANSFER FROM RABONA CURRENT A/S TO RABONA MASTER CARD A/C | P36: MOVEMENT FROM CURRENT A/C TO MASTER CARD A/C | Q36: MOVEMENT FROM CURRENT A/C TO MASTER CARD A/C | S36: 1500 | U36: 0 | V36: =L36 -> 46041 | W36: =V36 -> 46041 | X36: =T36+U36 -> 0 | Y36: =S36-X36 -> 1500 | Z36: BT | AA36: =G36 -> RABONA | AB36: =IF(Y36>0,"PENDING EXECUTION","COMPLETED") -> PENDING EXECUTION | AC36: MOVEMENT BETWEEN A/C | AE36: =IF(AA36=$AD$5,S36,0) -> 0 | AG36: =IF(Z36=$AG$5,X36,0) -> 0 | AH36: =IF(AA36=$AH$5,X36,0) -> 0
C37: =IF(A36=0,$C$4,"-") -> 26/1/ | D37: 22 | E37: CURRENT A/C | F37: IN | G37: RABONA | K37: T | L37: 46029 | M37: =L37 -> 46029 | N37: LUFTHANSA | O37: REFUND RECEIVED (96AAOM) | P37: OTHER (VAT RETURNS)(REFUNDS) | Q37: OTHER (VAT RETURNS)(REFUNDS) | S37: 114.32 | U37: =S37 -> 114.32 | V37: =L37 -> 46029 | W37: =V37 -> 46029 | X37: =T37+U37 -> 114.32 | Y37: =S37-X37 -> 0 | Z37: RCC | AA37: =G37 -> RABONA | AB37: =IF(Y37>0,"PENDING EXECUTION","COMPLETED") -> COMPLETED | AC37: REFUND RECEIVED | AE37: =IF(AA37=$AD$5,S37,0) -> 0 | AG37: =IF(Z37=$AG$5,X37,0) -> 0 | AH37: =IF(AA37=$AH$5,X37,0) -> 0
C38: =IF(A37=0,$C$4,"-") -> 26/1/ | D38: 23 | E38: MASTER CARD A/C | F38: IN | G38: RABONA | K38: U | L38: 46049 | M38: =L38 -> 46049 | N38: INWARDS TRANSFER FROM SHA (YORAM KEDEM) | O38: INVESTMENT FROM SHARE HOLDER | P38: BANK TRANSFERS/CASH DEPOSITS (YK) | Q38: INVESTMENT (SHARE HOLDER'S ACCOUNT) | S38: 50 | U38: =S38 -> 50 | V38: =L38 -> 46049 | W38: =V38 -> 46049 | X38: =T38+U38 -> 50 | Y38: =S38-X38 -> 0 | Z38: CASH | AA38: =G38 -> RABONA | AB38: =IF(Y38>0,"PENDING EXECUTION","COMPLETED") -> COMPLETED | AC38: INWARDS TRANSFER | AE38: =IF(AA38=$AD$5,S38,0) -> 0 | AG38: =IF(Z38=$AG$5,X38,0) -> 50 | AH38: =IF(AA38=$AH$5,X38,0) -> 0 | AI38: EXPENSES PAID CASH YK
C39: =IF(A38=0,$C$4,"-") -> 26/1/ | D39: 24 | E39: MASTER CARD A/C | F39: IN | G39: RABONA | K39: V | L39: 46052 | M39: =L39 -> 46052 | N39: INWARDS TRANSFER FROM SHA (YORAM KEDEM) | O39: INVESTMENT FROM SHARE HOLDER | P39: BANK TRANSFERS/CASH DEPOSITS (YK) | Q39: INVESTMENT (SHARE HOLDER'S ACCOUNT) | S39: 500 | U39: =S39 -> 500 | V39: =L39 -> 46052 | W39: =V39 -> 46052 | X39: =T39+U39 -> 500 | Y39: =S39-X39 -> 0 | Z39: CASH | AA39: =G39 -> RABONA | AB39: =IF(Y39>0,"PENDING EXECUTION","COMPLETED") -> COMPLETED | AC39: INWARDS TRANSFER | AE39: =IF(AA39=$AD$5,S39,0) -> 0 | AG39: =IF(Z39=$AG$5,X39,0) -> 500 | AH39: =IF(AA39=$AH$5,X39,0) -> 0 | AI39: EXPENSES PAID CASH YK
C40: =IF(A39=0,$C$4,"-") -> 26/1/ | D40: 25 | E40: MASTER CARD A/C | F40: IN | G40: RABONA | K40: W | L40: 46034 | M40: =L40 -> 46034 | N40: AEGEAN | O40: REFUND RECEIVED | P40: OTHER (VAT RETURNS)(REFUNDS) | Q40: OTHER (VAT RETURNS)(REFUNDS) | S40: 8.91 | U40: =S40 -> 8.91 | V40: =L40 -> 46034 | W40: =V40 -> 46034 | X40: =T40+U40 -> 8.91 | Y40: =S40-X40 -> 0 | Z40: RMC | AA40: =G40 -> RABONA | AB40: =IF(Y40>0,"PENDING EXECUTION","COMPLETED") -> COMPLETED | AC40: REFUND RECEIVED/MISSING SUP DOC | AE40: =IF(AA40=$AD$5,S40,0) -> 0 | AG40: =IF(Z40=$AG$5,X40,0) -> 0 | AH40: =IF(AA40=$AH$5,X40,0) -> 0
C41: =IF(A40=0,$C$4,"-") -> 26/1/ | D41: 26 | E41: MASTER CARD A/C | F41: IN | G41: RABONA | K41: Z | L41: 46034 | M41: =L41 -> 46034 | N41: AEGEAN | O41: REFUND RECEIVED | P41: OTHER (VAT RETURNS)(REFUNDS) | Q41: OTHER (VAT RETURNS)(REFUNDS) | S41: 4.79 | U41: =S41 -> 4.79 | V41: =L41 -> 46034 | W41: =V41 -> 46034 | X41: =T41+U41 -> 4.79 | Y41: =S41-X41 -> 0 | Z41: RMC | AA41: =G41 -> RABONA | AB41: =IF(Y41>0,"PENDING EXECUTION","COMPLETED") -> COMPLETED | AC41: REFUND RECEIVED/MISSING SUP DOC | AE41: =IF(AA41=$AD$5,S41,0) -> 0 | AG41: =IF(Z41=$AG$5,X41,0) -> 0 | AH41: =IF(AA41=$AH$5,X41,0) -> 0
C42: =IF(A41=0,$C$4,"-") -> 26/1/ | D42: 27 | E42: CURRENT A/C | F42: OUT | G42: RABONA | L42: 46052 | M42: =L42 -> 46052 | N42: ESPARGOS | O42: TRANSFER FROM RABONA CURRENT A/S TO ESPARGOS CURRENT A/C | P42: TRANSFERS TO CONNECTED ACCOUNTS (ESPARGOS) | Q42: TRANSFERS TO CONNECTED ACCOUNTS (ESPARGOS) | S42: 1000 | T42: =S42 -> 1000 | V42: =L42 -> 46052 | W42: =V42 -> 46052 | X42: =T42+U42 -> 1000 | Y42: =S42-X42 -> 0 | Z42: BT | AA42: =G42 -> RABONA | AB42: =IF(Y42>0,"PENDING EXECUTION","COMPLETED") -> COMPLETED | AC42: TRANSFER TO CONNECTED ACCOUNT (IN ESPARGOS RECORDED WITH REF NO 26/1/1E) | AE42: =IF(AA42=$AD$5,S42,0) -> 0 | AG42: =IF(Z42=$AG$5,X42,0) -> 0 | AH42: =IF(AA42=$AH$5,X42,0) -> 0
C43: =IF(A42=0,$C$4,"-") -> 26/1/ | D43: 28 | E43: CURRENT A/C | F43: OUT | G43: SHARE HOLDER | L43: 46052 | M43: =L43 -> 46052 | N43: YORAM KEDEM | O43: TRANSFER TO SHA | P43: TRANSFERS TO SH A/C AND CASH WITHDRAWAL (YK) | Q43: PERSONAL EXPENSES OF SHARE HOLDER | S43: 2500 | T43: =S43 -> 2500 | V43: =L43 -> 46052 | W43: =V43 -> 46052 | X43: =T43+U43 -> 2500 | Y43: =S43-X43 -> 0 | Z43: BT | AA43: =G43 -> SHARE HOLDER | AB43: =IF(Y43>0,"PENDING EXECUTION","COMPLETED") -> COMPLETED | AE43: =IF(AA43=$AD$5,S43,0) -> 0 | AG43: =IF(Z43=$AG$5,X43,0) -> 0 | AH43: =IF(AA43=$AH$5,X43,0) -> 2500 | AI43: YORAM KEDEM
C44: =IF(A43=0,$C$4,"-") -> 26/1/ | D44: 29 | E44: CURRENT A/C | F44: OUT | G44: SHARE HOLDER | L44: 46031 | M44: =L44 -> 46031 | N44: YORAM KEDEM | O44: TRANSFER TO SHA | P44: TRANSFERS TO SH A/C AND CASH WITHDRAWAL (YK) | Q44: PERSONAL EXPENSES OF SHARE HOLDER | S44: 1000 | T44: =S44 -> 1000 | V44: =L44 -> 46031 | W44: =V44 -> 46031 | X44: =T44+U44 -> 1000 | Y44: =S44-X44 -> 0 | Z44: BT | AA44: =G44 -> SHARE HOLDER | AB44: =IF(Y44>0,"PENDING EXECUTION","COMPLETED") -> COMPLETED | AE44: =IF(AA44=$AD$5,S44,0) -> 0 | AG44: =IF(Z44=$AG$5,X44,0) -> 0 | AH44: =IF(AA44=$AH$5,X44,0) -> 1000 | AI44: YORAM KEDEM
C45: =IF(A44=0,$C$4,"-") -> 26/1/ | D45: 30 | E45: CURRENT A/C | F45: OUT | G45: RABONA | L45: 46030 | M45: =L45 -> 46030 | N45: ESPARGOS | O45: TRANSFER FROM RABONA CURRENT A/S TO ESPARGOS CURRENT A/C | P45: TRANSFERS TO CONNECTED ACCOUNTS (ESPARGOS) | Q45: TRANSFERS TO CONNECTED ACCOUNTS (ESPARGOS) | S45: 720 | T45: =S45 -> 720 | V45: 46030 | W45: =V45 -> 46030 | X45: =T45+U45 -> 720 | Y45: =S45-X45 -> 0 | Z45: BT | AA45: =G45 -> RABONA | AB45: =IF(Y45>0,"PENDING EXECUTION","COMPLETED") -> COMPLETED | AC45: TRANSFER TO CONNECTED ACCOUNT (IN ESPARGOS RECORDED WITH REF NO 26/1/2E) | AE45: =IF(AA45=$AD$5,S45,0) -> 0 | AG45: =IF(Z45=$AG$5,X45,0) -> 0 | AH45: =IF(AA45=$AH$5,X45,0) -> 0
C46: =IF(A45=0,$C$4,"-") -> 26/1/ | D46: 31 | E46: CURRENT A/C | F46: OUT | G46: SHARE HOLDER | L46: 46041 | M46: =L46 -> 46041 | N46: YORAM KEDEM | O46: TRANSFER TO SHA | P46: TRANSFERS TO SH A/C AND CASH WITHDRAWAL (YK) | Q46: PERSONAL EXPENSES OF SHARE HOLDER | S46: 1000 | T46: =S46 -> 1000 | V46: 46041 | W46: =V46 -> 46041 | X46: =T46+U46 -> 1000 | Y46: =S46-X46 -> 0 | Z46: BT | AA46: =G46 -> SHARE HOLDER | AB46: =IF(Y46>0,"PENDING EXECUTION","COMPLETED") -> COMPLETED | AE46: =IF(AA46=$AD$5,S46,0) -> 0 | AG46: =IF(Z46=$AG$5,X46,0) -> 0 | AH46: =IF(AA46=$AH$5,X46,0) -> 1000 | AI46: YORAM KEDEM
C47: =IF(A46=0,$C$4,"-") -> 26/1/ | D47: 32 | E47: CURRENT A/C | F47: OUT | G47: SHARE HOLDER | L47: 46048 | M47: =L47 -> 46048 | N47: BETIJA KEDEM | O47: TRANSFER TO SHA | P47: TRANSFERS TO SH A/C AND CASH WITHDRAWAL (BK) | Q47: PERSONAL EXPENSES OF SHARE HOLDER | S47: 10 | T47: =S47 -> 10 | V47: 46048 | W47: =V47 -> 46048 | X47: =T47+U47 -> 10 | Y47: =S47-X47 -> 0 | Z47: BT | AA47: =G47 -> SHARE HOLDER | AB47: =IF(Y47>0,"PENDING EXECUTION","COMPLETED") -> COMPLETED | AE47: =IF(AA47=$AD$5,S47,0) -> 0 | AG47: =IF(Z47=$AG$5,X47,0) -> 0 | AH47: =IF(AA47=$AH$5,X47,0) -> 10 | AI47: BETIJA KEDEM
C48: =IF(A47=0,$C$4,"-") -> 26/1/ | D48: 33 | E48: CURRENT A/C | F48: OUT | G48: SHARE HOLDER | L48: 46023 | M48: =L48 -> 46023 | N48: YORAM KEDEM | O48: TRANSFER TO SHA | P48: TRANSFERS TO SH A/C AND CASH WITHDRAWAL (YK) | Q48: PERSONAL EXPENSES OF SHARE HOLDER | S48: 320 | T48: =S48 -> 320 | V48: 46023 | W48: =V48 -> 46023 | X48: =T48+U48 -> 320 | Y48: =S48-X48 -> 0 | Z48: BT | AA48: =G48 -> SHARE HOLDER | AB48: =IF(Y48>0,"PENDING EXECUTION","COMPLETED") -> COMPLETED | AE48: =IF(AA48=$AD$5,S48,0) -> 0 | AG48: =IF(Z48=$AG$5,X48,0) -> 0 | AH48: =IF(AA48=$AH$5,X48,0) -> 320 | AI48: YORAM KEDEM
C49: =IF(A48=0,$C$4,"-") -> 26/1/ | D49: 34 | E49: CURRENT A/C | F49: OUT | G49: SHARE HOLDER | L49: 46024 | M49: =L49 -> 46024 | N49: YORAM KEDEM | O49: TRANSFER TO SHA | P49: TRANSFERS TO SH A/C AND CASH WITHDRAWAL (YK) | Q49: PERSONAL EXPENSES OF SHARE HOLDER | S49: 8000 | T49: =S49 -> 8000 | V49: 46024 | W49: =V49 -> 46024 | X49: =T49+U49 -> 8000 | Y49: =S49-X49 -> 0 | Z49: BT | AA49: =G49 -> SHARE HOLDER | AB49: =IF(Y49>0,"PENDING EXECUTION","COMPLETED") -> COMPLETED | AE49: =IF(AA49=$AD$5,S49,0) -> 0 | AG49: =IF(Z49=$AG$5,X49,0) -> 0 | AH49: =IF(AA49=$AH$5,X49,0) -> 8000 | AI49: YORAM KEDEM
C50: =IF(A49=0,$C$4,"-") -> 26/1/ | D50: 35 | E50: CURRENT A/C | F50: OUT | G50: SHARE HOLDER | L50: 46026 | M50: =L50 -> 46026 | N50: YORAM KEDEM | O50: TRANSFER TO SHA | P50: TRANSFERS TO SH A/C AND CASH WITHDRAWAL (YK) | Q50: PERSONAL EXPENSES OF SHARE HOLDER | S50: 1000 | T50: =S50 -> 1000 | V50: 46026 | W50: =V50 -> 46026 | X50: =T50+U50 -> 1000 | Y50: =S50-X50 -> 0 | Z50: BT | AA50: =G50 -> SHARE HOLDER | AB50: =IF(Y50>0,"PENDING EXECUTION","COMPLETED") -> COMPLETED | AE50: =IF(AA50=$AD$5,S50,0) -> 0 | AG50: =IF(Z50=$AG$5,X50,0) -> 0 | AH50: =IF(AA50=$AH$5,X50,0) -> 1000 | AI50: YORAM KEDEM
C51: =IF(A50=0,$C$4,"-") -> 26/1/ | D51: 36 | E51: CURRENT A/C | F51: OUT | G51: SHARE HOLDER | L51: 46024 | M51: =L51 -> 46024 | N51: BNA MASKOT IL | O51: PERSONAL EXPENSE OF SH (YK) | P51: PAYMENTS MADE ON BEHALF OF SH (YK) | Q51: PERSONAL EXPENSES OF SHARE HOLDER | R51: 5921 | S51: 673.71 | T51: =S51 -> 673.71 | V51: 46024 | W51: =V51 -> 46024 | X51: =T51+U51 -> 673.71 | Y51: =S51-X51 -> 0 | Z51: RCC | AA51: =G51 -> SHARE HOLDER | AB51: =IF(Y51>0,"PENDING EXECUTION","COMPLETED") -> COMPLETED | AE51: =IF(AA51=$AD$5,S51,0) -> 0 | AG51: =IF(Z51=$AG$5,X51,0) -> 0 | AH51: =IF(AA51=$AH$5,X51,0) -> 673.71 | AI51: YORAM KEDEM
C52: =IF(A51=0,$C$4,"-") -> 26/1/ | D52: 37 | E52: CURRENT A/C | F52: OUT | G52: RABONA | L52: 46024 | M52: =L52 -> 46024 | N52: BOC | O52: CARD TRANSACTION ADM FEE | P52: BANK CHARGES AND INTEREST | Q52: BANK CHARGES AND INTEREST | S52: 20.21 | T52: =S52 -> 20.21 | V52: 46024 | W52: =V52 -> 46024 | X52: =T52+U52 -> 20.21 | Y52: =S52-X52 -> 0 | Z52: DD | AA52: =G52 -> RABONA | AB52: =IF(Y52>0,"PENDING EXECUTION","COMPLETED") -> COMPLETED | AE52: =IF(AA52=$AD$5,S52,0) -> 0 | AG52: =IF(Z52=$AG$5,X52,0) -> 0 | AH52: =IF(AA52=$AH$5,X52,0) -> 0
C53: =IF(A52=0,$C$4,"-") -> 26/1/ | D53: 38 | E53: CURRENT A/C | F53: OUT | G53: RABONA | H53: T1/22 | L53: 46031 | M53: =L53 -> 46031 | N53: BLUEGROUND | O53: FLAT IN ATHENS | P53: ACCOMODATION | Q53: TRAVEL EXPENSES | S53: 1136.23 | T53: =S53 -> 1136.23 | V53: 46031 | W53: =V53 -> 46031 | X53: =T53+U53 -> 1136.23 | Y53: =S53-X53 -> 0 | Z53: BT | AA53: =G53 -> RABONA | AB53: =IF(Y53>0,"PENDING EXECUTION","COMPLETED") -> COMPLETED | AE53: =IF(AA53=$AD$5,S53,0) -> 0 | AG53: =IF(Z53=$AG$5,X53,0) -> 0 | AH53: =IF(AA53=$AH$5,X53,0) -> 0
C54: =IF(A53=0,$C$4,"-") -> 26/1/ | D54: 39 | E54: CURRENT A/C | F54: OUT | G54: RABONA | L54: 45982 | M54: =L54 -> 45982 | N54: TAX DEPARTMENT | O54: TAX PAYMENT | P54: VAT | Q54: TAXES | S54: 5000 | T54: =S54 -> 5000 | V54: 45985 | W54: =V54 -> 45985 | X54: =T54+U54 -> 5000 | Y54: =S54-X54 -> 0 | Z54: BT | AA54: =G54 -> RABONA | AB54: =IF(Y54>0,"PENDING EXECUTION","COMPLETED") -> COMPLETED | AE54: =IF(AA54=$AD$5,S54,0) -> 0 | AG54: =IF(Z54=$AG$5,X54,0) -> 0 | AH54: =IF(AA54=$AH$5,X54,0) -> 0
C55: =IF(A54=0,$C$4,"-") -> 26/1/ | D55: 40 | E55: CURRENT A/C | F55: OUT | G55: RABONA | L55: 46035 | M55: =L55 -> 46035 | N55: NIADORN TRAIDING LTD | O55: CORPORATE DINNER RESERVATION | P55: ENTERTAINMENT | Q55: OFFICE / GENERAL ADMINISTRATIVE | S55: 500 | T55: =S55 -> 500 | V55: 46035 | W55: =V55 -> 46035 | X55: =T55+U55 -> 500 | Y55: =S55-X55 -> 0 | Z55: BT | AA55: =G55 -> RABONA | AB55: =IF(Y55>0,"PENDING EXECUTION","COMPLETED") -> COMPLETED | AE55: =IF(AA55=$AD$5,S55,0) -> 0 | AG55: =IF(Z55=$AG$5,X55,0) -> 0 | AH55: =IF(AA55=$AH$5,X55,0) -> 0
C56: =IF(A55=0,$C$4,"-") -> 26/1/ | D56: 41 | E56: CURRENT A/C | F56: OUT | G56: RABONA | L56: 46046 | M56: =L56 -> 46046 | N56: NIADORN TRAIDING LTD | O56: CORPORATE DINNER RESERVATION | P56: ENTERTAINMENT | Q56: OFFICE / GENERAL ADMINISTRATIVE | S56: 1000 | T56: =S56 -> 1000 | V56: 46041 | W56: =V56 -> 46041 | X56: =T56+U56 -> 1000 | Y56: =S56-X56 -> 0 | Z56: BT | AA56: =G56 -> RABONA | AB56: =IF(Y56>0,"PENDING EXECUTION","COMPLETED") -> COMPLETED | AE56: =IF(AA56=$AD$5,S56,0) -> 0 | AG56: =IF(Z56=$AG$5,X56,0) -> 0 | AH56: =IF(AA56=$AH$5,X56,0) -> 0
C57: =IF(A56=0,$C$4,"-") -> 26/1/ | D57: 42 | E57: CURRENT A/C | F57: OUT | G57: RABONA | L57: 46046 | M57: =L57 -> 46046 | N57: NIADORN TRAIDING LTD | O57: CORPORATE DINNER RESERVATION | P57: ENTERTAINMENT | Q57: OFFICE / GENERAL ADMINISTRATIVE | S57: 500 | T57: =S57 -> 500 | V57: 46041 | W57: =V57 -> 46041 | X57: =T57+U57 -> 500 | Y57: =S57-X57 -> 0 | Z57: BT | AA57: =G57 -> RABONA | AB57: =IF(Y57>0,"PENDING EXECUTION","COMPLETED") -> COMPLETED | AE57: =IF(AA57=$AD$5,S57,0) -> 0 | AG57: =IF(Z57=$AG$5,X57,0) -> 0 | AH57: =IF(AA57=$AH$5,X57,0) -> 0
C58: =C57 -> 26/1/ | D58: 43 | E58: CURRENT A/C | F58: OUT | G58: RABONA | L58: 46051 | M58: =L58 -> 46051 | N58: STELVIO BUSINESS SERVICES LTD | O58: AUDIT 2023 | P58: ACCOUNTING, AUDIT, COMPANY SECRITARY SERVICES | Q58: PROFESIONAL SERVICES | S58: 1844.5 | T58: =S58 -> 1844.5 | V58: 46030 | W58: =V58 -> 46030 | X58: =T58+U58 -> 1844.5 | Y58: =S58-X58 -> 0 | Z58: BT | AA58: =G58 -> RABONA | AB58: =IF(Y58>0,"PENDING EXECUTION","COMPLETED") -> COMPLETED | AE58: =IF(AA58=$AD$5,S58,0) -> 0 | AG58: =IF(Z58=$AG$5,X58,0) -> 0 | AH58: =IF(AA58=$AH$5,X58,0) -> 0
C59: =C58 -> 26/1/ | D59: 44 | E59: CURRENT A/C | F59: OUT | G59: RABONA | L59: 46052 | M59: =L59 -> 46052 | N59: AUTHOTECHNICA LTD | O59: BALANCE ON CAR LEASE (CONTRACT ENDED) | P59: INLAND TRANSPORTATION | Q59: TRANSPORTATION EXPENSES | S59: 866.59 | T59: =S59 -> 866.59 | V59: 46052 | W59: =V59 -> 46052 | X59: =T59+U59 -> 866.59 | Y59: =S59-X59 -> 0 | Z59: BT | AA59: =G59 -> RABONA | AB59: =IF(Y59>0,"PENDING EXECUTION","COMPLETED") -> COMPLETED | AE59: =IF(AA59=$AD$5,S59,0) -> 0 | AG59: =IF(Z59=$AG$5,X59,0) -> 0 | AH59: =IF(AA59=$AH$5,X59,0) -> 0
C60: =IF(A59=0,$C$4,"-") -> 26/1/ | D60: 45 | E60: CURRENT A/C | F60: OUT | G60: RABONA | L60: 46052 | M60: =L60 -> 46052 | N60: TAX DEPARTMENT | O60: TAX PAYMENT | P60: VAT | Q60: TAXES | S60: 3811.59 | T60: =S60 -> 3811.59 | V60: =L60 -> 46052 | W60: =V60 -> 46052 | X60: =T60+U60 -> 3811.59 | Y60: =S60-X60 -> 0 | Z60: BT | AA60: =G60 -> RABONA | AB60: =IF(Y60>0,"PENDING EXECUTION","COMPLETED") -> COMPLETED | AE60: =IF(AA60=$AD$5,S60,0) -> 0 | AG60: =IF(Z60=$AG$5,X60,0) -> 0 | AH60: =IF(AA60=$AH$5,X60,0) -> 0
C61: =IF(A60=0,$C$4,"-") -> 26/1/ | D61: 46 | E61: CURRENT A/C | F61: OUT | G61: RABONA | H61: T1/23 | L61: 46036 | M61: =L61 -> 46036 | N61: AEGEAN | O61: SEAT CHANGE (FLIGHT ATH-TLV (YKEDEM) | P61: TRANSPORTATION | Q61: TRAVEL EXPENSES | S61: 7 | T61: =S61 -> 7 | V61: 46038 | W61: =V61 -> 46038 | X61: =T61+U61 -> 7 | Y61: =S61-X61 -> 0 | Z61: RCC | AA61: =G61 -> RABONA | AB61: =IF(Y61>0,"PENDING EXECUTION","COMPLETED") -> COMPLETED | AE61: =IF(AA61=$AD$5,S61,0) -> 0 | AG61: =IF(Z61=$AG$5,X61,0) -> 0 | AH61: =IF(AA61=$AH$5,X61,0) -> 0
C62: =IF(A61=0,$C$4,"-") -> 26/1/ | D62: 47 | E62: CURRENT A/C | F62: OUT | G62: RABONA | H62: T1/24 | L62: 46036 | M62: =L62 -> 46036 | N62: CUBE REALESTATE | O62: MAINTANCE SERVICES (ATHENS FLAT) | P62: ACCOMODATION | Q62: TRAVEL EXPENSES | S62: 149.64 | T62: =S62 -> 149.64 | V62: 46038 | W62: =V62 -> 46038 | X62: =T62+U62 -> 149.64 | Y62: =S62-X62 -> 0 | Z62: RCC | AA62: =G62 -> RABONA | AB62: =IF(Y62>0,"PENDING EXECUTION","COMPLETED") -> COMPLETED | AE62: =IF(AA62=$AD$5,S62,0) -> 0 | AG62: =IF(Z62=$AG$5,X62,0) -> 0 | AH62: =IF(AA62=$AH$5,X62,0) -> 0
C63: =IF(A62=0,$C$4,"-") -> 26/1/ | D63: 48 | E63: MASTER CARD A/C | F63: OUT | G63: RABONA | H63: T1/25 | L63: 46023 | M63: =L63 -> 46023 | N63: CAFÉ CAFÉ BERSHEVA | O63: ALLOWANCES | P63: ALLOWANCES | Q63: TRAVEL EXPENSES | R63: 33 | S63: 8.91 | T63: =S63 -> 8.91 | V63: 46027 | W63: =V63 -> 46027 | X63: =T63+U63 -> 8.91 | Y63: =S63-X63 -> 0 | Z63: RMC | AA63: =G63 -> RABONA | AB63: =IF(Y63>0,"PENDING EXECUTION","COMPLETED") -> COMPLETED | AE63: =IF(AA63=$AD$5,S63,0) -> 0 | AG63: =IF(Z63=$AG$5,X63,0) -> 0 | AH63: =IF(AA63=$AH$5,X63,0) -> 0
C64: =IF(A63=0,$C$4,"-") -> 26/1/ | D64: 49 | E64: MASTER CARD A/C | F64: OUT | G64: RABONA | L64: 46027 | M64: =L64 -> 46027 | N64: BOC | O64: CARD TRANSACTION ADM FEE | P64: BANK CHARGES AND INTEREST | Q64: BANK CHARGES AND INTEREST | S64: 0.27 | T64: =S64 -> 0.27 | V64: 46027 | W64: =V64 -> 46027 | X64: =T64+U64 -> 0.27 | Y64: =S64-X64 -> 0 | Z64: DD | AA64: =G64 -> RABONA | AB64: =IF(Y64>0,"PENDING EXECUTION","COMPLETED") -> COMPLETED | AE64: =IF(AA64=$AD$5,S64,0) -> 0 | AG64: =IF(Z64=$AG$5,X64,0) -> 0 | AH64: =IF(AA64=$AH$5,X64,0) -> 0
C65: =IF(A64=0,$C$4,"-") -> 26/1/ | D65: 50 | E65: MASTER CARD A/C | F65: OUT | G65: RABONA | H65: T1/26 | L65: 46025 | M65: =L65 -> 46025 | N65: ZE LTD ASHDOD | O65: ALLOWANCES | P65: ALLOWANCES | Q65: TRAVEL EXPENSES | R65: 1201 | S65: 324.14 | T65: =S65 -> 324.14 | V65: 46029 | W65: =V65 -> 46029 | X65: =T65+U65 -> 324.14 | Y65: =S65-X65 -> 0 | Z65: RMC | AA65: =G65 -> RABONA | AB65: =IF(Y65>0,"PENDING EXECUTION","COMPLETED") -> COMPLETED | AE65: =IF(AA65=$AD$5,S65,0) -> 0 | AG65: =IF(Z65=$AG$5,X65,0) -> 0 | AH65: =IF(AA65=$AH$5,X65,0) -> 0
C66: =IF(A65=0,$C$4,"-") -> 26/1/ | D66: 51 | E66: MASTER CARD A/C | F66: OUT | G66: RABONA | L66: 46029 | M66: =L66 -> 46029 | N66: BOC | O66: CARD TRANSACTION ADM FEE | P66: BANK CHARGES AND INTEREST | Q66: BANK CHARGES AND INTEREST | S66: 9.72 | T66: =S66 -> 9.72 | V66: 46029 | W66: =V66 -> 46029 | X66: =T66+U66 -> 9.72 | Y66: =S66-X66 -> 0 | Z66: DD | AA66: =G66 -> RABONA | AB66: =IF(Y66>0,"PENDING EXECUTION","COMPLETED") -> COMPLETED | AE66: =IF(AA66=$AD$5,S66,0) -> 0 | AG66: =IF(Z66=$AG$5,X66,0) -> 0 | AH66: =IF(AA66=$AH$5,X66,0) -> 0
C67: =IF(A66=0,$C$4,"-") -> 26/1/ | D67: 52 | E67: MASTER CARD A/C | F67: OUT | G67: RABONA | H67: T1/27 | L67: 46028 | M67: =L67 -> 46028 | N67: WOLT GR BLINKY'S | O67: ALLOWANCES | P67: ALLOWANCES | Q67: TRAVEL EXPENSES | S67: 101.34 | T67: =S67 -> 101.34 | V67: 46030 | W67: =V67 -> 46030 | X67: =T67+U67 -> 101.34 | Y67: =S67-X67 -> 0 | Z67: RMC | AA67: =G67 -> RABONA | AB67: =IF(Y67>0,"PENDING EXECUTION","COMPLETED") -> COMPLETED | AE67: =IF(AA67=$AD$5,S67,0) -> 0 | AG67: =IF(Z67=$AG$5,X67,0) -> 0 | AH67: =IF(AA67=$AH$5,X67,0) -> 0
C68: =IF(A67=0,$C$4,"-") -> 26/1/ | D68: 53 | E68: MASTER CARD A/C | F68: OUT | G68: RABONA | H68: T1/8 | L68: 46024 | M68: =L68 -> 46024 | N68: AEGEAN | O68: FLIGHT TLV-LCA (9TBSOD 4/1/2026) EXTRA LAGGAGE BK | P68: TRANSPORTATION | Q68: TRAVEL EXPENSES | S68: 66 | T68: =S68 -> 66 | V68: 46027 | W68: =V68 -> 46027 | X68: =T68+U68 -> 66 | Y68: =S68-X68 -> 0 | Z68: RMC | AA68: =G68 -> RABONA | AB68: =IF(Y68>0,"PENDING EXECUTION","COMPLETED") -> COMPLETED | AE68: =IF(AA68=$AD$5,S68,0) -> 0 | AG68: =IF(Z68=$AG$5,X68,0) -> 0 | AH68: =IF(AA68=$AH$5,X68,0) -> 0
C69: =IF(A68=0,$C$4,"-") -> 26/1/ | D69: 54 | E69: MASTER CARD A/C | F69: OUT | G69: RABONA | H69: T1/9 | L69: 46025 | M69: =L69 -> 46025 | N69: AEGEAN | O69: FLIGHT ATH-TLV (73PLJ7 8/1/26) REISSU CHARGES YK | P69: TRANSPORTATION | Q69: TRAVEL EXPENSES | S69: 27.76 | T69: =S69 -> 27.76 | V69: 46027 | W69: =V69 -> 46027 | X69: =T69+U69 -> 27.76 | Y69: =S69-X69 -> 0 | Z69: RMC | AA69: =G69 -> RABONA | AB69: =IF(Y69>0,"PENDING EXECUTION","COMPLETED") -> COMPLETED | AE69: =IF(AA69=$AD$5,S69,0) -> 0 | AG69: =IF(Z69=$AG$5,X69,0) -> 0 | AH69: =IF(AA69=$AH$5,X69,0) -> 0
C70: =IF(A69=0,$C$4,"-") -> 26/1/ | D70: 55 | E70: MASTER CARD A/C | F70: OUT | G70: RABONA | H70: T1/10 | L70: 46031 | M70: =L70 -> 46031 | N70: AEGEAN | O70: FLIGHT LCA-ATH-LCA (YTNUB 12/1/2026) REISSUE CHARGES YK | P70: TRANSPORTATION | Q70: TRAVEL EXPENSES | S70: 38 | T70: =S70 -> 38 | V70: 46034 | W70: =V70 -> 46034 | X70: =T70+U70 -> 38 | Y70: =S70-X70 -> 0 | Z70: RMC | AA70: =G70 -> RABONA | AB70: =IF(Y70>0,"PENDING EXECUTION","COMPLETED") -> COMPLETED | AE70: =IF(AA70=$AD$5,S70,0) -> 0 | AG70: =IF(Z70=$AG$5,X70,0) -> 0 | AH70: =IF(AA70=$AH$5,X70,0) -> 0
C71: =IF(A70=0,$C$4,"-") -> 26/1/ | D71: 56 | E71: MASTER CARD A/C | F71: OUT | G71: RABONA | H71: T1/11 | L71: 46027 | M71: =L71 -> 46027 | N71: AEGEAN | O71: REISSUANCE FEE | P71: TRANSPORTATION | Q71: TRAVEL EXPENSES | S71: 46 | T71: =S71 -> 46 | V71: 46030 | W71: =V71 -> 46030 | X71: =T71+U71 -> 46 | Y71: =S71-X71 -> 0 | Z71: RMC | AA71: =G71 -> RABONA | AB71: =IF(Y71>0,"PENDING EXECUTION","COMPLETED") -> COMPLETED | AE71: =IF(AA71=$AD$5,S71,0) -> 0 | AG71: =IF(Z71=$AG$5,X71,0) -> 0 | AH71: =IF(AA71=$AH$5,X71,0) -> 0
C72: =IF(A71=0,$C$4,"-") -> 26/1/ | D72: 57 | E72: MASTER CARD A/C | F72: OUT | G72: SHARE HOLDER | L72: 46027 | M72: =L72 -> 46027 | N72: AEGEAN | O72: PAYMENTS MADE ON BEHALF OF SH | P72: PAYMENTS MADE ON BEHALF OF SH (YK) | Q72: PERSONAL EXPENSES OF SHARE HOLDER | S72: 46 | T72: =S72 -> 46 | V72: 46030 | W72: =V72 -> 46030 | X72: =T72+U72 -> 46 | Y72: =S72-X72 -> 0 | Z72: RMC | AA72: =G72 -> SHARE HOLDER | AB72: =IF(Y72>0,"PENDING EXECUTION","COMPLETED") -> COMPLETED | AE72: =IF(AA72=$AD$5,S72,0) -> 0 | AG72: =IF(Z72=$AG$5,X72,0) -> 0 | AH72: =IF(AA72=$AH$5,X72,0) -> 46 | AI72: YORAM KEDEM
C73: =IF(A72=0,$C$4,"-") -> 26/1/ | D73: 58 | E73: MASTER CARD A/C | F73: OUT | G73: SHARE HOLDER | L73: 46027 | M73: =L73 -> 46027 | N73: AEGEAN | O73: PAYMENTS MADE ON BEHALF OF SH | P73: PAYMENTS MADE ON BEHALF OF SH (YK) | Q73: PERSONAL EXPENSES OF SHARE HOLDER | S73: 46 | T73: =S73 -> 46 | V73: 46030 | W73: =V73 -> 46030 | X73: =T73+U73 -> 46 | Y73: =S73-X73 -> 0 | Z73: RMC | AA73: =G73 -> SHARE HOLDER | AB73: =IF(Y73>0,"PENDING EXECUTION","COMPLETED") -> COMPLETED | AE73: =IF(AA73=$AD$5,S73,0) -> 0 | AG73: =IF(Z73=$AG$5,X73,0) -> 0 | AH73: =IF(AA73=$AH$5,X73,0) -> 46 | AI73: YORAM KEDEM
C74: =IF(A73=0,$C$4,"-") -> 26/1/ | D74: 59 | E74: MASTER CARD A/C | F74: OUT | G74: RABONA | H74: T1/12 | L74: 46034 | M74: =L74 -> 46034 | N74: WOLT GR PIKANTIKO | O74: ALLOWANCES | P74: ALLOWANCES | Q74: TRAVEL EXPENSES | S74: 20.53 | T74: =S74 -> 20.53 | V74: 46036 | W74: =V74 -> 46036 | X74: =T74+U74 -> 20.53 | Y74: =S74-X74 -> 0 | Z74: RMC | AA74: =G74 -> RABONA | AB74: =IF(Y74>0,"PENDING EXECUTION","COMPLETED") -> COMPLETED | AE74: =IF(AA74=$AD$5,S74,0) -> 0 | AG74: =IF(Z74=$AG$5,X74,0) -> 0 | AH74: =IF(AA74=$AH$5,X74,0) -> 0
C75: =IF(A74=0,$C$4,"-") -> 26/1/ | D75: 60 | E75: MASTER CARD A/C | F75: OUT | G75: RABONA | H75: T1/13 | L75: 46036 | M75: =L75 -> 46036 | N75: WOLT GR ME KOLONAKI | O75: ALLOWANCES | P75: ALLOWANCES | Q75: TRAVEL EXPENSES | S75: 55.69 | T75: =S75 -> 55.69 | V75: 46038 | W75: =V75 -> 46038 | X75: =T75+U75 -> 55.69 | Y75: =S75-X75 -> 0 | Z75: RMC | AA75: =G75 -> RABONA | AB75: =IF(Y75>0,"PENDING EXECUTION","COMPLETED") -> COMPLETED | AE75: =IF(AA75=$AD$5,S75,0) -> 0 | AG75: =IF(Z75=$AG$5,X75,0) -> 0 | AH75: =IF(AA75=$AH$5,X75,0) -> 0
C76: =IF(A75=0,$C$4,"-") -> 26/1/ | D76: 61 | E76: MASTER CARD A/C | F76: OUT | G76: RABONA | L76: 46037 | M76: =L76 -> 46037 | N76: BOC | O76: TOTAL INTEREST | P76: BANK CHARGES AND INTEREST | Q76: BANK CHARGES AND INTEREST | S76: 0.69 | T76: =S76 -> 0.69 | V76: 46037 | W76: =V76 -> 46037 | X76: =T76+U76 -> 0.69 | Y76: =S76-X76 -> 0 | Z76: DD | AA76: =G76 -> RABONA | AB76: =IF(Y76>0,"PENDING EXECUTION","COMPLETED") -> COMPLETED | AE76: =IF(AA76=$AD$5,S76,0) -> 0 | AG76: =IF(Z76=$AG$5,X76,0) -> 0 | AH76: =IF(AA76=$AH$5,X76,0) -> 0
A77: D | C77: =IF(A76=0,$C$4,"-") -> 26/1/ | D77: 62 | E77: MASTER CARD A/C | F77: OUT | G77: SHARE HOLDER | L77: 46038 | M77: =L77 -> 46038 | N77: INTERSPORT | O77: PAYMENTS MADE ON BEHALF OF SH | P77: PAYMENTS MADE ON BEHALF OF SH (YK) | Q77: PERSONAL EXPENSES OF SHARE HOLDER | S77: 73.99 | T77: =S77 -> 73.99 | V77: 46041 | W77: =V77 -> 46041 | X77: =T77+U77 -> 73.99 | Y77: =S77-X77 -> 0 | Z77: RMC | AA77: =G77 -> SHARE HOLDER | AB77: =IF(Y77>0,"PENDING EXECUTION","COMPLETED") -> COMPLETED | AE77: =IF(AA77=$AD$5,S77,0) -> 0 | AG77: =IF(Z77=$AG$5,X77,0) -> 0 | AH77: =IF(AA77=$AH$5,X77,0) -> 73.99 | AI77: YORAM KEDEM
C78: =C77 -> 26/1/ | D78: 63 | E78: MASTER CARD A/C | F78: OUT | G78: RABONA | L78: 46038 | M78: 45782 | N78: ESSO | O78: CAR WASH | P78: INLAND TRANSPORTATION | Q78: TRANSPORTATION EXPENSES | S78: 30 | T78: =S78 -> 30 | V78: 46038 | W78: =V78 -> 46038 | X78: =T78+U78 -> 30 | Y78: =S78-X78 -> 0 | Z78: RMC | AA78: =G78 -> RABONA | AB78: =IF(Y78>0,"PENDING EXECUTION","COMPLETED") -> COMPLETED | AE78: =IF(AA78=$AD$5,S78,0) -> 0 | AG78: =IF(Z78=$AG$5,X78,0) -> 0 | AH78: =IF(AA78=$AH$5,X78,0) -> 0
C79: =IF(A78=0,$C$4,"-") -> 26/1/ | D79: 64 | E79: MASTER CARD A/C | F79: OUT | G79: RABONA | L79: 46037 | M79: =L79 -> 46037 | N79: PIZZA EXPRESS | O79: MARKETING PURPOSES | P79: ENTERTAINMENT | Q79: OFFICE / GENERAL ADMINISTRATIVE | S79: 156.8 | T79: =S79 -> 156.8 | V79: 46041 | W79: =V79 -> 46041 | X79: =T79+U79 -> 156.8 | Y79: =S79-X79 -> 0 | Z79: RMC | AA79: =G79 -> RABONA | AB79: =IF(Y79>0,"PENDING EXECUTION","COMPLETED") -> COMPLETED | AE79: =IF(AA79=$AD$5,S79,0) -> 0 | AG79: =IF(Z79=$AG$5,X79,0) -> 0 | AH79: =IF(AA79=$AH$5,X79,0) -> 0
C80: =IF(A79=0,$C$4,"-") -> 26/1/ | D80: 65 | E80: MASTER CARD A/C | F80: OUT | G80: RABONA | H80: T1/14 | L80: 46038 | M80: =L80 -> 46038 | N80: AEGEAN | O80: REISSUANCE FEE | P80: TRANSPORTATION | Q80: TRAVEL EXPENSES | S80: 98.85 | T80: =S80 -> 98.85 | V80: 46041 | W80: =V80 -> 46041 | X80: =T80+U80 -> 98.85 | Y80: =S80-X80 -> 0 | Z80: RMC | AA80: =G80 -> RABONA | AB80: =IF(Y80>0,"PENDING EXECUTION","COMPLETED") -> COMPLETED | AE80: =IF(AA80=$AD$5,S80,0) -> 0 | AG80: =IF(Z80=$AG$5,X80,0) -> 0 | AH80: =IF(AA80=$AH$5,X80,0) -> 0
C81: =IF(A80=0,$C$4,"-") -> 26/1/ | D81: 66 | E81: MASTER CARD A/C | F81: OUT | G81: RABONA | H81: T1/15 | L81: 46037 | M81: =L81 -> 46037 | N81: CYPRUS AIRWAYS | O81: FLIGHT LCA-TLV 23/2/2026 BK | P81: TRANSPORTATION | Q81: TRAVEL EXPENSES | S81: 102.06 | T81: =S81 -> 102.06 | V81: 46041 | W81: =V81 -> 46041 | X81: =T81+U81 -> 102.06 | Y81: =S81-X81 -> 0 | Z81: RMC | AA81: =G81 -> RABONA | AB81: =IF(Y81>0,"PENDING EXECUTION","COMPLETED") -> COMPLETED | AE81: =IF(AA81=$AD$5,S81,0) -> 0 | AG81: =IF(Z81=$AG$5,X81,0) -> 0 | AH81: =IF(AA81=$AH$5,X81,0) -> 0
C82: =IF(A81=0,$C$4,"-") -> 26/1/ | D82: 67 | E82: MASTER CARD A/C | F82: OUT | G82: SHARE HOLDER | L82: 46037 | M82: =L82 -> 46037 | N82: CYPRUS AIRWAYS | O82: PAYMENTS MADE ON BEHALF OF SH | P82: PAYMENTS MADE ON BEHALF OF SH (YK) | Q82: PERSONAL EXPENSES OF SHARE HOLDER | S82: 120.06 | T82: =S82 -> 120.06 | V82: 46041 | W82: =V82 -> 46041 | X82: =T82+U82 -> 120.06 | Y82: =S82-X82 -> 0 | Z82: RMC | AA82: =G82 -> SHARE HOLDER | AB82: =IF(Y82>0,"PENDING EXECUTION","COMPLETED") -> COMPLETED | AE82: =IF(AA82=$AD$5,S82,0) -> 0 | AG82: =IF(Z82=$AG$5,X82,0) -> 0 | AH82: =IF(AA82=$AH$5,X82,0) -> 120.06 | AI82: YORAM KEDEM
C83: =IF(A82=0,$C$4,"-") -> 26/1/ | D83: 68 | E83: MASTER CARD A/C | F83: OUT | G83: RABONA | H83: T1/16 | L83: 46042 | M83: =L83 -> 46042 | N83: MOXY MUNCHEN AIRPORT | O83: ALLOWANCES | P83: ALLOWANCES | Q83: TRAVEL EXPENSES | S83: 33 | T83: =S83 -> 33 | V83: 46044 | W83: =V83 -> 46044 | X83: =T83+U83 -> 33 | Y83: =S83-X83 -> 0 | Z83: RMC | AA83: =G83 -> RABONA | AB83: =IF(Y83>0,"PENDING EXECUTION","COMPLETED") -> COMPLETED | AE83: =IF(AA83=$AD$5,S83,0) -> 0 | AG83: =IF(Z83=$AG$5,X83,0) -> 0 | AH83: =IF(AA83=$AH$5,X83,0) -> 0
C84: =IF(A83=0,$C$4,"-") -> 26/1/ | D84: 69 | E84: MASTER CARD A/C | F84: OUT | G84: RABONA | L84: 46046 | M84: =L84 -> 46046 | N84: THE GARDEN | O84: MARKETING PURPOSES | P84: ENTERTAINMENT | Q84: OFFICE / GENERAL ADMINISTRATIVE | S84: 510.26 | T84: =S84 -> 510.26 | V84: 46048 | W84: =V84 -> 46048 | X84: =T84+U84 -> 510.26 | Y84: =S84-X84 -> 0 | Z84: RMC | AA84: =G84 -> RABONA | AB84: =IF(Y84>0,"PENDING EXECUTION","COMPLETED") -> COMPLETED | AE84: =IF(AA84=$AD$5,S84,0) -> 0 | AG84: =IF(Z84=$AG$5,X84,0) -> 0 | AH84: =IF(AA84=$AH$5,X84,0) -> 0
C85: =IF(A84=0,$C$4,"-") -> 26/1/ | D85: 70 | E85: MASTER CARD A/C | F85: OUT | G85: RABONA | L85: 46046 | M85: =L85 -> 46046 | N85: EKO | O85: FUEL | P85: FUEL | Q85: TRANSPORTATION EXPENSES | S85: 92.44 | T85: =S85 -> 92.44 | V85: 46048 | W85: =V85 -> 46048 | X85: =T85+U85 -> 92.44 | Y85: =S85-X85 -> 0 | Z85: RMC | AA85: =G85 -> RABONA | AB85: =IF(Y85>0,"PENDING EXECUTION","COMPLETED") -> COMPLETED | AE85: =IF(AA85=$AD$5,S85,0) -> 0 | AG85: =IF(Z85=$AG$5,X85,0) -> 0 | AH85: =IF(AA85=$AH$5,X85,0) -> 0
C86: =IF(A85=0,$C$4,"-") -> 26/1/ | D86: 71 | E86: MASTER CARD A/C | F86: OUT | G86: SHARE HOLDER | L86: 46048 | M86: =L86 -> 46048 | N86: BOC | O86: CASH WITHDRAWAL | P86: TRANSFERS TO SH A/C AND CASH WITHDRAWAL (YK) | Q86: PERSONAL EXPENSES OF SHARE HOLDER | S86: 300 | T86: =S86 -> 300 | V86: 46048 | W86: =V86 -> 46048 | X86: =T86+U86 -> 300 | Y86: =S86-X86 -> 0 | Z86: RMC | AA86: =G86 -> SHARE HOLDER | AB86: =IF(Y86>0,"PENDING EXECUTION","COMPLETED") -> COMPLETED | AE86: =IF(AA86=$AD$5,S86,0) -> 0 | AG86: =IF(Z86=$AG$5,X86,0) -> 0 | AH86: =IF(AA86=$AH$5,X86,0) -> 300 | AI86: YORAM KEDEM
C87: =IF(A86=0,$C$4,"-") -> 26/1/ | D87: 72 | E87: MASTER CARD A/C | F87: OUT | G87: RABONA | L87: 46048 | M87: =L87 -> 46048 | N87: BOC | O87: CASH ADV/TRANSF FEE | P87: BANK CHARGES AND INTEREST | Q87: BANK CHARGES AND INTEREST | S87: 9.99 | T87: =S87 -> 9.99 | V87: 46048 | W87: =V87 -> 46048 | X87: =T87+U87 -> 9.99 | Y87: =S87-X87 -> 0 | Z87: RMC | AA87: =G87 -> RABONA | AB87: =IF(Y87>0,"PENDING EXECUTION","COMPLETED") -> COMPLETED | AE87: =IF(AA87=$AD$5,S87,0) -> 0 | AG87: =IF(Z87=$AG$5,X87,0) -> 0 | AH87: =IF(AA87=$AH$5,X87,0) -> 0
C88: =IF(A87=0,$C$4,"-") -> 26/1/ | D88: 73 | E88: MASTER CARD A/C | F88: OUT | G88: RABONA | H88: T1/17 | L88: 46043 | M88: =L88 -> 46043 | N88: MOXY MUNCHEN AIRPORT | O88: ACCOMODATION MUNICH | P88: ACCOMODATION | Q88: TRAVEL EXPENSES | S88: 85 | T88: =S88 -> 85 | V88: 46048 | W88: =V88 -> 46048 | X88: =T88+U88 -> 85 | Y88: =S88-X88 -> 0 | Z88: RMC | AA88: =G88 -> RABONA | AB88: =IF(Y88>0,"PENDING EXECUTION","COMPLETED") -> COMPLETED | AE88: =IF(AA88=$AD$5,S88,0) -> 0 | AG88: =IF(Z88=$AG$5,X88,0) -> 0 | AH88: =IF(AA88=$AH$5,X88,0) -> 0
C89: =IF(A88=0,$C$4,"-") -> 26/1/ | D89: 74 | E89: MASTER CARD A/C | F89: OUT | G89: RABONA | H89: T1/18 | L89: 46043 | M89: =L89 -> 46043 | N89: MOXY MUNCHEN AIRPORT | O89: ACCOMODATION MUNICH | P89: ACCOMODATION | Q89: TRAVEL EXPENSES | S89: 81 | T89: =S89 -> 81 | V89: 46048 | W89: =V89 -> 46048 | X89: =T89+U89 -> 81 | Y89: =S89-X89 -> 0 | Z89: RMC | AA89: =G89 -> RABONA | AB89: =IF(Y89>0,"PENDING EXECUTION","COMPLETED") -> COMPLETED | AE89: =IF(AA89=$AD$5,S89,0) -> 0 | AG89: =IF(Z89=$AG$5,X89,0) -> 0 | AH89: =IF(AA89=$AH$5,X89,0) -> 0
C90: =IF(A89=0,$C$4,"-") -> 26/1/ | D90: 75 | E90: MASTER CARD A/C | F90: OUT | G90: RABONA | H90: T1/19 | L90: 46049 | M90: =L90 -> 46049 | N90: GR WOLT DAO VIETNAMESE | O90: ALLOWANCES | P90: ALLOWANCES | Q90: TRAVEL EXPENSES | S90: 55.19 | T90: =S90 -> 55.19 | V90: 46051 | W90: =V90 -> 46051 | X90: =T90+U90 -> 55.19 | Y90: =S90-X90 -> 0 | Z90: RMC | AA90: =G90 -> RABONA | AB90: =IF(Y90>0,"PENDING EXECUTION","COMPLETED") -> COMPLETED | AE90: =IF(AA90=$AD$5,S90,0) -> 0 | AG90: =IF(Z90=$AG$5,X90,0) -> 0 | AH90: =IF(AA90=$AH$5,X90,0) -> 0
C91: =IF(A90=0,$C$4,"-") -> 26/1/ | D91: 76 | E91: MASTER CARD A/C | F91: OUT | G91: RABONA | L91: 46027 | M91: =L91 -> 46027 | N91: STARLINK | O91: INTERNET SUBSCRIPTION | P91: TELEPHONE/INTERNET/MOBILE EXPENSES (CYTA) | Q91: OFFICE / GENERAL ADMINISTRATIVE | S91: 50 | T91: =S91 -> 50 | V91: 45968 | W91: =V91 -> 45968 | X91: =T91+U91 -> 50 | Y91: =S91-X91 -> 0 | Z91: RMC | AA91: =G91 -> RABONA | AB91: =IF(Y91>0,"PENDING EXECUTION","COMPLETED") -> COMPLETED | AE91: =IF(AA91=$AD$5,S91,0) -> 0 | AG91: =IF(Z91=$AG$5,X91,0) -> 0 | AH91: =IF(AA91=$AH$5,X91,0) -> 0
C92: =IF(A91=0,$C$4,"-") -> 26/1/ | D92: 77 | E92: MASTER CARD A/C | F92: OUT | G92: RABONA | L92: 46047 | M92: =L92 -> 46047 | N92: COLUMBIA CONFECTIONARY | O92: MARKETING PURPOSES | P92: ENTERTAINMENT | Q92: OFFICE / GENERAL ADMINISTRATIVE | S92: 72.5 | T92: =S92 -> 72.5 | V92: 46049 | W92: =V92 -> 46049 | X92: =T92+U92 -> 72.5 | Y92: =S92-X92 -> 0 | Z92: RMC | AA92: =G92 -> RABONA | AB92: =IF(Y92>0,"PENDING EXECUTION","COMPLETED") -> COMPLETED | AE92: =IF(AA92=$AD$5,S92,0) -> 0 | AG92: =IF(Z92=$AG$5,X92,0) -> 0 | AH92: =IF(AA92=$AH$5,X92,0) -> 0
C93: =IF(A92=0,$C$4,"-") -> 26/1/ | D93: 78 | E93: MASTER CARD A/C | F93: OUT | G93: RABONA | H93: T1/20 | L93: 46048 | M93: =L93 -> 46048 | N93: WOLT GR MEAT N ROSES | O93: ALLOWANCES | P93: ALLOWANCES | Q93: TRAVEL EXPENSES | S93: 22.3 | T93: =S93 -> 22.3 | V93: 28.1 | W93: =V93 -> 28.1 | X93: =T93+U93 -> 22.3 | Y93: =S93-X93 -> 0 | Z93: RMC | AA93: =G93 -> RABONA | AB93: =IF(Y93>0,"PENDING EXECUTION","COMPLETED") -> COMPLETED | AE93: =IF(AA93=$AD$5,S93,0) -> 0 | AG93: =IF(Z93=$AG$5,X93,0) -> 0 | AH93: =IF(AA93=$AH$5,X93,0) -> 0
C94: =IF(A93=0,$C$4,"-") -> 26/1/ | D94: 79 | E94: MASTER CARD A/C | F94: OUT | G94: RABONA | H94: T1/21 | L94: 46049 | M94: =L94 -> 46049 | N94: WOLT GR ME KOLONAKI | O94: ALLOWANCES | P94: ALLOWANCES | Q94: TRAVEL EXPENSES | S94: 49.54 | T94: =S94 -> 49.54 | V94: 46051 | W94: =V94 -> 46051 | X94: =T94+U94 -> 49.54 | Y94: =S94-X94 -> 0 | Z94: RMC | AA94: =G94 -> RABONA | AB94: =IF(Y94>0,"PENDING EXECUTION","COMPLETED") -> COMPLETED | AE94: =IF(AA94=$AD$5,S94,0) -> 0 | AG94: =IF(Z94=$AG$5,X94,0) -> 0 | AH94: =IF(AA94=$AH$5,X94,0) -> 0
C95: =IF(A94=0,$C$4,"-") -> 26/1/ | D95: 80 | E95: MASTER CARD A/C | F95: OUT | G95: SHARE HOLDER | L95: 46050 | M95: =L95 -> 46050 | N95: YORAM KEDEM (REVOLUT) | O95: TRANSFER TO SHA | P95: TRANSFERS TO SH A/C AND CASH WITHDRAWAL (YK) | Q95: PERSONAL EXPENSES OF SHARE HOLDER | S95: 207 | T95: =S95 -> 207 | V95: 46050 | W95: =V95 -> 46050 | X95: =T95+U95 -> 207 | Y95: =S95-X95 -> 0 | Z95: RMC | AA95: =G95 -> SHARE HOLDER | AB95: =IF(Y95>0,"+Q41:AB41PENDING EXECUTION","COMPLETED") -> COMPLETED | AE95: =IF(AA95=$AD$5,S95,0) -> 0 | AG95: =IF(Z95=$AG$5,X95,0) -> 0 | AH95: =IF(AA95=$AH$5,X95,0) -> 207 | AI95: YORAM KEDEM
C96: =IF(A95=0,$C$4,"-") -> 26/1/ | D96: 81 | E96: MASTER CARD A/C | F96: OUT | G96: RABONA | L96: 46051 | M96: =L96 -> 46051 | N96: BOC | O96: CARD MEMBERSHIP FEE | P96: BANK CHARGES AND INTEREST | Q96: BANK CHARGES AND INTEREST | S96: 8 | T96: =S96 -> 8 | V96: 46051 | W96: =V96 -> 46051 | X96: =T96+U96 -> 8 | Y96: =S96-X96 -> 0 | Z96: DD | AA96: =G96 -> RABONA | AB96: =IF(Y96>0,"PENDING EXECUTION","COMPLETED") -> COMPLETED | AE96: =IF(AA96=$AD$5,S96,0) -> 0 | AG96: =IF(Z96=$AG$5,X96,0) -> 0 | AH96: =IF(AA96=$AH$5,X96,0) -> 0
C97: =IF(A96=0,$C$4,"-") -> 26/1/ | D97: 82 | E97: MASTER CARD A/C | F97: OUT | G97: SHARE HOLDER | L97: 46052 | M97: =L97 -> 46052 | N97: BOC | O97: CASH WITHDRAWAL | P97: TRANSFERS TO SH A/C AND CASH WITHDRAWAL (YK) | Q97: PERSONAL EXPENSES OF SHARE HOLDER | S97: 1000 | T97: =S97 -> 1000 | V97: 46052 | W97: =V97 -> 46052 | X97: =T97+U97 -> 1000 | Y97: =S97-X97 -> 0 | Z97: RMC | AA97: =G97 -> SHARE HOLDER | AB97: =IF(Y97>0,"PENDING EXECUTION","COMPLETED") -> COMPLETED | AE97: =IF(AA97=$AD$5,S97,0) -> 0 | AG97: =IF(Z97=$AG$5,X97,0) -> 0 | AH97: =IF(AA97=$AH$5,X97,0) -> 1000 | AI97: YORAM KEDEM
C98: =IF(A97=0,$C$4,"-") -> 26/1/ | D98: 83 | E98: MASTER CARD A/C | F98: OUT | G98: RABONA | L98: 46052 | M98: =L98 -> 46052 | N98: BOC | O98: CASH ADV/TRANSF FEE | P98: BANK CHARGES AND INTEREST | Q98: BANK CHARGES AND INTEREST | S98: 33.3 | T98: =S98 -> 33.3 | V98: 46052 | W98: =V98 -> 46052 | X98: =T98+U98 -> 33.3 | Y98: =S98-X98 -> 0 | Z98: RMC | AA98: =G98 -> RABONA | AB98: =IF(Y98>0,"PENDING EXECUTION","COMPLETED") -> COMPLETED | AE98: =IF(AA98=$AD$5,S98,0) -> 0 | AG98: =IF(Z98=$AG$5,X98,0) -> 0 | AH98: =IF(AA98=$AH$5,X98,0) -> 0
C99: =IF(A98=0,$C$4,"-") -> 26/1/ | D99: 84 | E99: MASTER CARD A/C | F99: OUT | G99: RABONA | H99: T1/28 | L99: 46386 | M99: =L99 -> 46386 | N99: LUFTHANSA | O99: FLIGHT LCA-MUC-ATH (7Z7JFX) YK 18-21 JAN | P99: TRANSPORTATION | Q99: TRAVEL EXPENSES | S99: 200 | T99: =S99 -> 200 | V99: 46029 | W99: =V99 -> 46029 | X99: =T99+U99 -> 200 | Y99: =S99-X99 -> 0 | Z99: RMC | AA99: =G99 -> RABONA | AB99: =IF(Y99>0,"PENDING EXECUTION","COMPLETED") -> COMPLETED | AE99: =IF(AA99=$AD$5,S99,0) -> 0 | AG99: =IF(Z99=$AG$5,X99,0) -> 0 | AH99: =IF(AA99=$AH$5,X99,0) -> 0
C100: =IF(A99=0,$C$4,"-") -> 26/1/ | D100: 85 | E100: MASTER CARD A/C | F100: OUT | G100: RABONA | L100: 46028 | M100: =L100 -> 46028 | N100: FAT BULL CO | O100: MARKETING PURPOSES | P100: ENTERTAINMENT | Q100: OFFICE / GENERAL ADMINISTRATIVE | S100: 47.34 | T100: =S100 -> 47.34 | V100: 46030 | W100: =V100 -> 46030 | X100: =T100+U100 -> 47.34 | Y100: =S100-X100 -> 0 | Z100: RMC | AA100: =G100 -> RABONA | AB100: =IF(Y100>0,"PENDING EXECUTION","COMPLETED") -> COMPLETED | AE100: =IF(AA100=$AD$5,S100,0) -> 0 | AG100: =IF(Z100=$AG$5,X100,0) -> 0 | AH100: =IF(AA100=$AH$5,X100,0) -> 0
C101: =IF(A100=0,$C$4,"-") -> 26/1/ | D101: 86 | E101: MASTER CARD A/C | F101: OUT | G101: RABONA | L101: 46032 | M101: =L101 -> 46032 | N101: MIXTILES | O101: PRINTED MARKETING MATERIALS | P101: MARKETING | Q101: OFFICE / GENERAL ADMINISTRATIVE | S101: 101.25 | T101: =S101 -> 101.25 | V101: 46034 | W101: =V101 -> 46034 | X101: =T101+U101 -> 101.25 | Y101: =S101-X101 -> 0 | Z101: RMC | AA101: =G101 -> RABONA | AB101: =IF(Y101>0,"PENDING EXECUTION","COMPLETED") -> COMPLETED | AE101: =IF(AA101=$AD$5,S101,0) -> 0 | AG101: =IF(Z101=$AG$5,X101,0) -> 0 | AH101: =IF(AA101=$AH$5,X101,0) -> 0
...

Sheet EXPENSES Mothly Totals
B2: RABONA HOLDINGS LTD. | D2: JANUARY 2026
B3: MONTHLY ACTUALS
B6: REVENUE | D6: =SUM(D7:D8) -> 31829
B7: CONSULTING SERVICES | D7: =SUMIF('RABONA PAYMENTS'!$P$7:$P$206,B7,'RABONA PAYMENTS'!$X$7:$X$206) -> 29900
B8: REIMBURSMENT OF PROCURE AND RUNNING EXPENSES | D8: =SUMIF('RABONA PAYMENTS'!$P$7:$P$206,B8,'RABONA PAYMENTS'!$X$7:$X$206) -> 1929
B11: INVESTMENT (SHARE HOLDER'S ACCOUNT) | D11: =D12+D15 -> 20102.627
B12: YK | D12: =D14+D13 -> 20005.197
B13: BANK TRANSFERS/CASH DEPOSITS (YK) | D13: =SUMIF('RABONA PAYMENTS'!P7:P205,B13,'RABONA PAYMENTS'!S7:S205) -> 9500
B14: EXPENSES PAID IN CASH BY S/H (YK) | D14: =H38 -> 10505.197
B15: BK | D15: =D17+D16 -> 97.43
B16: BANK TRANSFERS/CASH DEPOSITS (BK) | D16: =SUMIF('RABONA PAYMENTS'!P7:P205,B16,'RABONA PAYMENTS'!S7:S205) -> 0
B17: EXPENSES PAID IN CASH BY S/H (BK) | D17: =H37 -> 97.43
B19: INVESTMENT (ESPARGOS) | D19: =SUMIF('RABONA PAYMENTS'!$Q$7:$Q$205,B19,'RABONA PAYMENTS'!$S$7:$S$205) -> 0
B21: OTHER (VAT RETURNS)(REFUNDS) | D21: =SUMIF('RABONA PAYMENTS'!$Q$7:$Q$205,B21,'RABONA PAYMENTS'!$S$7:$S$205) -> 128.02
B24: TOTAL REVENUE | D24: =D6+D11+D19+D21 -> 52059.647
B27: EXPENSES | D27: 44986 | F27: CHECK LIST
B29: COST OF LABOR | D29: =SUM(D30:D34) -> 2142.75 | F29: =SUMIF('RABONA PAYMENTS'!Q7:Q205,B29,'RABONA PAYMENTS'!X7:X205) -> 2142.75
B30: SALARY BK | D30: =SUMIF('RABONA PAYMENTS'!$P$7:$P$206,B30,'RABONA PAYMENTS'!$X$7:$X$206) -> 2142.75
B31: SALARY YK | D31: =SUMIF('RABONA PAYMENTS'!$P$7:$P$206,B31,'RABONA PAYMENTS'!$X$7:$X$206) -> 0
B32: Social Insurance | D32: =SUMIF('RABONA PAYMENTS'!$P$7:$P$206,B32,'RABONA PAYMENTS'!$X$7:$X$206) -> 0
B33: PAYE | D33: =SUMIF('RABONA PAYMENTS'!$P$7:$P$206,B33,'RABONA PAYMENTS'!$X$7:$X$206) -> 0
B34: INSURANCE (DAVID SHIELD) | D34: =SUMIF('RABONA PAYMENTS'!$P$7:$P$206,B34,'RABONA PAYMENTS'!$X$7:$X$206) -> 0
B36: EXPENSE REIMBURSMENT TO EMPLOYEES | D36: =SUM(D37:D38) -> 0 | F36: =SUMIF('RABONA PAYMENTS'!Q7:Q205,B36,'RABONA PAYMENTS'!X7:X205) -> 0 | H36: ='RABONA PAYMENTS'!AG206 -> 10602.627 | I36: (EXPENSES PAID IN CASH TO REFUND)
B37: EXPENSES PAID CASH BK | D37: =SUMIF('RABONA PAYMENTS'!$P$7:$P$206,B37,'RABONA PAYMENTS'!$X$7:$X$206) -> 0 | H37: =SUMIF('RABONA PAYMENTS'!$AI$7:$AI$205,B37,'RABONA PAYMENTS'!$AG$7:$AG$205) -> 97.43 | I37: INVESTMENT (BK SHARE HOLDER'S A/C)
B38: EXPENSES PAID CASH YK | D38: =SUMIF('RABONA PAYMENTS'!$P$7:$P$206,B38,'RABONA PAYMENTS'!$X$7:$X$206) -> 0 | H38: =SUMIF('RABONA PAYMENTS'!$AI$7:$AI$205,B38,'RABONA PAYMENTS'!$AG$7:$AG$205) -> 10505.197 | I38: INVESTMENT (YK SHARE HOLDER'S A/C)
B40: TAXES | D40: =SUM(D41:D46) -> 8811.59 | F40: =SUMIF('RABONA PAYMENTS'!$Q$7:$Q$205,B40,'RABONA PAYMENTS'!$X$7:$X$205) -> 8811.59
B41: GESI ON DIVIDENDS | D41: =SUMIF('RABONA PAYMENTS'!$P$7:$P$206,B41,'RABONA PAYMENTS'!$X$7:$X$206) -> 0
B42: INCOME TAX | D42: =SUMIF('RABONA PAYMENTS'!$P$7:$P$206,B42,'RABONA PAYMENTS'!$X$7:$X$206) -> 0
B43: PROVISIONAL TAX | D43: =SUMIF('RABONA PAYMENTS'!$P$7:$P$206,B43,'RABONA PAYMENTS'!$X$7:$X$206) -> 0
B44: VAT | D44: =SUMIF('RABONA PAYMENTS'!$P$7:$P$206,B44,'RABONA PAYMENTS'!$X$7:$X$206) -> 8811.59
B45: ANNUAL LEVY TO THE ROCK | D45: =SUMIF('RABONA PAYMENTS'!$P$7:$P$206,B45,'RABONA PAYMENTS'!$X$7:$X$206) -> 0
D46: =SUMIF('RABONA PAYMENTS'!$P$7:$P$206,B46,'RABONA PAYMENTS'!$X$7:$X$206) -> 0
B48: TRAVEL EXPENSES | D48: =D50+D59 -> 3506.477 | F48: =SUMIF('RABONA PAYMENTS'!$Q$7:$Q$205,B48,'RABONA PAYMENTS'!$X$7:$X$205) -> 3506.477
B50: TRAVELING ABROAD EXPENSES | D50: =SUM(D51:D57) -> 2871.137
B51: TRANSPORTATION | D51: =SUMIF('RABONA PAYMENTS'!$P$7:$P$205,B51,'RABONA PAYMENTS'!$X$7:$X$205)-D60 -> 673.27291
B52: ACCOMODATION | D52: =SUMIF('RABONA PAYMENTS'!$P$7:$P$205,B52,'RABONA PAYMENTS'!$X$7:$X$205)-D61 -> 1451.87
B53: ALLOWANCES | D53: =SUMIF('RABONA PAYMENTS'!$P$7:$P$205,B53,'RABONA PAYMENTS'!$X$7:$X$205) -> 690.74
B54: OTHER (COVID TESTS AND SPECIAL PERMITS) | D54: =SUMIF('RABONA PAYMENTS'!$P$7:$P$205,B54,'RABONA PAYMENTS'!$X$7:$X$205) -> 0
B55: MARKETING PURPOSES (HOSTING VISITS) | D55: =SUMIF('RABONA PAYMENTS'!$P$7:$P$205,B55,'RABONA PAYMENTS'!$X$7:$X$205) -> 0
B56: OTHER TRAVEL EXPENSES | D56: =SUMIF('RABONA PAYMENTS'!$P$7:$P$205,B56,'RABONA PAYMENTS'!$X$7:$X$205) -> 55.254126
B59: TRAVELING ABROAD EXPENSES TO BE REIMBURSED | D59: =SUM(D60:D66) -> 635.34
B60: TRANSPORTATION | D60: =SUMIF('RABONA PAYMENTS'!$P$7:$P$205,B60,'RABONA PAYMENTS'!$AE$7:$AE$205) -> 362.34
B61: ACCOMODATION | D61: =SUMIF('RABONA PAYMENTS'!$P$7:$P$205,B61,'RABONA PAYMENTS'!$AE$7:$AE$205) -> 237
B62: REPRESENTATION ON VISITS | D62: =SUMIF('RABONA PAYMENTS'!$P$7:$P$205,B62,'RABONA PAYMENTS'!$AE$7:$AE$205) -> 0
B63: OTHER (COVID TESTS AND SPECIAL PERMITS) | D63: =SUMIF('RABONA PAYMENTS'!$P$7:$P$205,B63,'RABONA PAYMENTS'!$AE$7:$AE$205) -> 0
B64: CAR PARK AIRPORT | D64: =SUMIF('RABONA PAYMENTS'!$P$7:$P$205,B64,'RABONA PAYMENTS'!$AE$7:$AE$205) -> 36
B68: PROFESIONAL SERVICES | D68: =D81+D70 -> 1844.5 | F68: =SUMIF('RABONA PAYMENTS'!$Q$7:$Q$205,B68,'RABONA PAYMENTS'!$X$7:$X$205) -> 1844.5
B70: PROFESIONAL SERVICES | D70: =SUM(D71:D79) -> 1844.5
B71: ACCOUNTING, AUDIT, COMPANY SECRITARY SERVICES | D71: =SUMIF('RABONA PAYMENTS'!$P$7:$P$205,B71,'RABONA PAYMENTS'!$X$7:$X$205)-D82 -> 1844.5
B72: SERVICES ON FF&E | D72: =SUMIF('RABONA PAYMENTS'!$P$7:$P$205,B72,'RABONA PAYMENTS'!$X$7:$X$205)-D83 -> 0
B73: IT SERVICES | D73: =SUMIF('RABONA PAYMENTS'!$P$7:$P$205,B73,'RABONA PAYMENTS'!$X$7:$X$205)-D84 -> 0
B74: LEGAL | D74: =SUMIF('RABONA PAYMENTS'!$P$7:$P$205,B74,'RABONA PAYMENTS'!$X$7:$X$205)-D85 -> 0
B75: PRINTING | D75: =SUMIF('RABONA PAYMENTS'!$P$7:$P$205,B75,'RABONA PAYMENTS'!$X$7:$X$205)-D86 -> 0
B76: OTHER | D76: =SUMIF('RABONA PAYMENTS'!$P$7:$P$205,B76,'RABONA PAYMENTS'!$X$7:$X$205)-D87 -> 0
D77: =SUMIF('RABONA PAYMENTS'!$P$7:$P$205,B77,'RABONA PAYMENTS'!$X$7:$X$205)-D88 -> 0
D78: =SUMIF('RABONA PAYMENTS'!$P$7:$P$205,B78,'RABONA PAYMENTS'!$X$7:$X$205)-D89 -> 0
D79: =SUMIF('RABONA PAYMENTS'!$P$7:$P$205,B79,'RABONA PAYMENTS'!$X$7:$X$205)-D90 -> 0
B81: PROFESIONAL SERVICES TO BE REIMBURSED | D81: =SUM(D82:D90) -> 0
B82: ACCOUNTING, AUDIT, COMPANY SECRITARY SERVICES | D82: =SUMIF('RABONA PAYMENTS'!$P$7:$P$205,B82,'RABONA PAYMENTS'!$AE$7:$AE$205) -> 0
B83: SEVICES ON FF&E | D83: =SUMIF('RABONA PAYMENTS'!$P$7:$P$205,B83,'RABONA PAYMENTS'!$AE$7:$AE$205) -> 0
B84: IT SERVICES | D84: =SUMIF('RABONA PAYMENTS'!$P$7:$P$205,B84,'RABONA PAYMENTS'!$AE$7:$AE$205) -> 0
B85: LEGAL | D85: =SUMIF('RABONA PAYMENTS'!$P$7:$P$205,B85,'RABONA PAYMENTS'!$AE$7:$AE$205) -> 0
B86: PRINTING | D86: =SUMIF('RABONA PAYMENTS'!$P$7:$P$205,B86,'RABONA PAYMENTS'!$AE$7:$AE$205) -> 0
B87: OTHER | D87: =SUMIF('RABONA PAYMENTS'!$P$7:$P$205,B87,'RABONA PAYMENTS'!$AE$7:$AE$205) -> 0
B92: FURNITURE AND EQUIPMENT | D92: =D94+D102 -> 0 | F92: =SUMIF('RABONA PAYMENTS'!$Q$7:$Q$205,B92,'RABONA PAYMENTS'!$X$7:$X$205) -> 0
B94: FURNITURE & EQUIPMENT | D94: =SUM(D95:D100) -> 0
B95: FURNITURE &FITTINGS OFFICE | D95: =SUMIF('RABONA PAYMENTS'!$P$7:$P$205,B95,'RABONA PAYMENTS'!$X$7:$X$205)-D103 -> 0
B96: COMPUTERS AND TELEPHONES | D96: =SUMIF('RABONA PAYMENTS'!$P$7:$P$205,B96,'RABONA PAYMENTS'!$X$7:$X$205)-D104 -> 0
B97: FURNITURE &FITTINGS (MOCK UP) | D97: =SUMIF('RABONA PAYMENTS'!$P$7:$P$205,B97,'RABONA PAYMENTS'!$X$7:$X$205)-D105 -> 0
B98: COPUTER SOFTWARE/ WEBPAGE SUBSCRIPTIONS | D98: =SUMIF('RABONA PAYMENTS'!$P$7:$P$205,B98,'RABONA PAYMENTS'!$X$7:$X$205)-D106 -> 0
B102: FURNITURE & EQUIPMENT TO BE REIMBURSED | D102: =SUM(D103:D108) -> 0
B103: FURNITURE &FITTINGS OFFICE | D103: =SUMIF('RABONA PAYMENTS'!$P$7:$P$205,B103,'RABONA PAYMENTS'!$AE$7:$AE$205) -> 0
B104: COMPUTERS AND TELEPHONES | D104: =SUMIF('RABONA PAYMENTS'!$P$7:$P$205,B104,'RABONA PAYMENTS'!$AE$7:$AE$205) -> 0
B105: FURNITURE &FITTINGS (MOCK UP) | D105: =SUMIF('RABONA PAYMENTS'!$P$7:$P$205,B105,'RABONA PAYMENTS'!$AE$7:$AE$205) -> 0
B106: COPUTER SOFTWARE/ WEBPAGE SUBSCRIPTIONS | D106: =SUMIF('RABONA PAYMENTS'!$P$7:$P$205,B106,'RABONA PAYMENTS'!$AE$7:$AE$205) -> 0
B110: OFFICE / GENERAL ADMINISTRATIVE | D110: =D112+D127 -> 3597.22 | F110: =SUMIF('RABONA PAYMENTS'!$Q$7:$Q$205,B110,'RABONA PAYMENTS'!$X$7:$X$205) -> 3597.22 | H110: =D110-F110 -> 0
B112: GENERAL ADMINISTRATIVE | D112: =SUM(D113:D125) -> 3597.22
B113: OFFICE STATIONARY | D113: =SUMIF('RABONA PAYMENTS'!$P$7:$P$205,B113,'RABONA PAYMENTS'!$X$7:$X$205)-D128 -> 134.18
B114: OFFICE SUPPLIES AND SUNDRIES | D114: =SUMIF('RABONA PAYMENTS'!$P$7:$P$205,B114,'RABONA PAYMENTS'!$X$7:$X$205)-D129 -> 68
B115: COURIER AND POSTAL SERVICES | D115: =SUMIF('RABONA PAYMENTS'!$P$7:$P$205,B115,'RABONA PAYMENTS'!$X$7:$X$205)-D130 -> 0
B116: TELEPHONE/INTERNET/MOBILE EXPENSES (CYTA) | D116: =SUMIF('RABONA PAYMENTS'!$P$7:$P$205,B116,'RABONA PAYMENTS'!$X$7:$X$205)-D131 -> 50
B117: PENALTIES | D117: =SUMIF('RABONA PAYMENTS'!$P$7:$P$205,B117,'RABONA PAYMENTS'!$X$7:$X$205)-D132 -> 0
B118: MAINTENANCE | D118: =SUMIF('RABONA PAYMENTS'!$P$7:$P$205,B118,'RABONA PAYMENTS'!$X$7:$X$205)-D133 -> 0
B119: ENTERTAINMENT | D119: =SUMIF('RABONA PAYMENTS'!$P$7:$P$205,B119,'RABONA PAYMENTS'!$X$7:$X$205)-D134 -> 3123.79
B120: REPRESENTATION/GIFTS | D120: =SUMIF('RABONA PAYMENTS'!$P$7:$P$205,B120,'RABONA PAYMENTS'!$X$7:$X$205)-D135 -> 120
B121: MARKETING | D121: =SUMIF('RABONA PAYMENTS'!$P$7:$P$205,B121,'RABONA PAYMENTS'!$X$7:$X$205)-D136 -> 101.25
B122: MSCL. | D122: =SUMIF('RABONA PAYMENTS'!$P$7:$P$205,B122,'RABONA PAYMENTS'!$X$7:$X$205)-D137 -> 0
D123: =SUMIF('RABONA PAYMENTS'!$P$7:$P$205,B123,'RABONA PAYMENTS'!$X$7:$X$205)-D138 -> 0
D124: =SUMIF('RABONA PAYMENTS'!$P$7:$P$205,B124,'RABONA PAYMENTS'!$X$7:$X$205)-D139 -> 0
D125: =SUMIF('RABONA PAYMENTS'!$P$7:$P$205,B125,'RABONA PAYMENTS'!$X$7:$X$205)-D140 -> 0
B127: GENERAL ADMINISTRATIVE TO BE REIMBURSED | D127: =SUM(D128:D140) -> 0
B128: OFFICE STATIONARY | D128: =SUMIF('RABONA PAYMENTS'!$P$7:$P$205,B128,'RABONA PAYMENTS'!$AE$7:$AE$205) -> 0
B129: OFFICE SUPPLIES AND SUNDRIES | D129: =SUMIF('RABONA PAYMENTS'!$P$7:$P$205,B129,'RABONA PAYMENTS'!$AE$7:$AE$205) -> 0
B130: COURIER AND POSTAL SERVICES | D130: =SUMIF('RABONA PAYMENTS'!$P$7:$P$205,B130,'RABONA PAYMENTS'!$AE$7:$AE$205) -> 0
B131: TELEPHONE/INTERNET/MOBILE EXPENSES (CYTA) | D131: =SUMIF('RABONA PAYMENTS'!$P$7:$P$205,B131,'RABONA PAYMENTS'!$AE$7:$AE$205) -> 0
B132: PENALTIES | D132: =SUMIF('RABONA PAYMENTS'!$P$7:$P$205,B132,'RABONA PAYMENTS'!$AE$7:$AE$205) -> 0
B133: MAINTENANCE | D133: =SUMIF('RABONA PAYMENTS'!$P$7:$P$205,B133,'RABONA PAYMENTS'!$AE$7:$AE$205) -> 0
B134: ENTERTAINMENT | D134: =SUMIF('RABONA PAYMENTS'!$P$7:$P$205,B134,'RABONA PAYMENTS'!$AE$7:$AE$205) -> 0
B135: GIFTS | D135: =SUMIF('RABONA PAYMENTS'!$P$7:$P$205,B135,'RABONA PAYMENTS'!$AE$7:$AE$205) -> 0
B136: MARKETING | D136: =SUMIF('RABONA PAYMENTS'!$P$7:$P$205,B136,'RABONA PAYMENTS'!$AE$7:$AE$205) -> 0
...

Sheet EXP paid on behalf of Client
N1: CHECK 1 | O1: CHECK 2
N2: ='RABONA PAYMENTS'!AE206 -> 635.34 | O2: =AE28+AE56+AE113 -> 635.34 | P2: =N2-O2 -> 0
N4: REPORT MARCH 31ST 2023
B5: Ref.No. | H5: Accounting for Travel expenses | I5: Accounting for expense reimbursment | J5: salaries | L5: DATE ISSUED | N5: COMPANY | O5: ITEM | P5: SUBCATEGORY | Q5: CATEGORY | R5: TOTAL AMOUNT incl. VAT | S5: Total Amount paid (EURO) incl. VAT | V5: Date payed | W5: MONTH PAYED | X5: Total Payed incl. VAT (EURO) | Y5: Balance (EURO) | Z5: Payed buy | AA5: EXPENSE OF | AC5: Comments | AD5: REIMBURSE FROM / PRORATE TO | AE5: TOTAL AMOUNT to Prorate/Reimburse (EURO) | AF5: Invoice No. of REIMBURMENT | AG5: TOTAL AMOUNT Incl. VAT (EURO) | AI5: EXPENSES OF | AJ5: Comments
AG11: 40.04 | AH11: 0
AG12: 40.19 | AH12: 0
AG13: 110.04 | AH13: 0
AG14: 0 | AH14: 0
AG15: 0 | AH15: 0
AG16: 0 | AH16: 0
AG17: 22 | AH17: 0 | AI17: YORAM KEDEM
AG18: =IF(Z18=$AG$4,X18,0) -> 0 | AH18: =IF(AA18=$AH$4,X18,0) -> 0
AG19: =IF(Z19=$AG$4,X19,0) -> 0 | AH19: =IF(AA19=$AH$4,X19,0) -> 0
AG20: =IF(Z20=$AG$4,X20,0) -> 0 | AH20: =IF(AA20=$AH$4,X20,0) -> 0
AG21: =IF(Z21=$AG$4,X21,0) -> 0 | AH21: =IF(AA21=$AH$4,X21,0) -> 0
AG22: =IF(Z22=$AG$4,X22,0) -> 0 | AH22: =IF(AA22=$AH$4,X22,0) -> 0
AG23: =IF(Z23=$AG$4,X23,0) -> 0 | AH23: =IF(AA23=$AH$4,X23,0) -> 0
AG24: =IF(Z24=$AG$4,X24,0) -> 0 | AH24: =IF(AA24=$AH$4,X24,0) -> 0
AG25: =IF(Z25=$AG$4,X25,0) -> 0 | AH25: =IF(AA25=$AH$4,X25,0) -> 0
AG26: =IF(Z26=$AG$4,X26,0) -> 0 | AH26: =IF(AA26=$AH$4,X26,0) -> 0
AG27: =IF(Z27=$AG$4,X27,0) -> 0 | AH27: =IF(AA27=$AH$4,X27,0) -> 0 | AI27: YORAM KEDEM
O28: Inv. No: 2023/04/001 | S28: WHG | AE28: =SUM(AE6:AE9) -> 0 | AF28: Inv. No: 2021/04/016
N30: REPORT JANUARY 31ST 2025 | O30: URBAN CITY
B32: REF. NO: MONTH RECEIVED | C32: REF. NO. | E32: ACCOUNT PAID FROM | F32: INWARDS/ OUTWARDS | G32: EXPENSE OF | H32: Accounting for Travel expenses | I32: Accounting for expense reimbursment | J32: salaries | L32: DATE ISSUED | N32: COMPANY | O32: ITEM | Q32: CATEGORY | R32: TOTAL AMOUNT (foreign curancy) Incl.VAT | S32: Total Amount paid (EURO) incl. VAT | T32: AMOUNT PAID | U32: AMOUNT RECEIVED | V32: DATE PAID | W32: MONTH | X32: Total Payed incl. VAT (EURO) | Y32: Balance (EURO) | Z32: Payed buy | AA32: EXPENSE OF | AC32: Comments | AD32: REIMBURSE FROM / PRORATE TO | AE32: TOTAL AMOUNT to Reimburse (EURO) | AF32: Invoice No. of REIMBURMENT | AG32: TOTAL AMOUNT Incl. VAT (EURO) | AI32: EXPENSES OF | AJ32: Comments | AK32: EXPENSE OF RABONA
C33: 26/1/ | D33: 38 | E33: MASTER CARD A/C | F33: OUT | G33: REIMBURSE | H33: T1/8 | I33: R1/8 | L33: 46037 | M33: 46037 | N33: LARNACA INTERNATIONAL AIRPORT | O33: CAR PARKING AIRPORT | P33: TRANSPORTATION | Q33: TRAVEL EXPENSES | S33: 36 | T33: 36 | U33: 0 | V33: 46041 | W33: 46041 | X33: 36 | Y33: 0 | Z33: RMC | AA33: REIMBURSE | AB33: COMPLETED | AD33: URBAN CITY | AE33: 36 | AG33: 0 | AH33: 0
C34: 26/1/ | D34: 90 | E34: CASH | F34: OUT | G34: REIMBURSE | H34: T1/3 | I34: R1/3 | L34: 46044 | M34: 46044 | N34: POUKAKIS NICOLAS | O34: TAXI ATHENS | P34: TRANSPORTATION | Q34: TRAVEL EXPENSES | S34: 46.14 | T34: 46.14 | U34: 0 | V34: 46044 | W34: 46044 | X34: 46.14 | Y34: 0 | Z34: CASH | AA34: REIMBURSE | AB34: COMPLETED | AD34: URBAN CITY | AE34: 46.14 | AG34: 46.14 | AH34: 0 | AI34: EXPENSES PAID CASH BK
C35: 26/1/ | D35: 91 | E35: CASH | F35: OUT | G35: REIMBURSE | H35: T1/4 | I35: R1/4 | L35: 46044 | M35: 46044 | N35: POUKAKIS NICOLAS | O35: TAXI ATHENS | P35: TRANSPORTATION | Q35: TRAVEL EXPENSES | S35: 51.29 | T35: 51.29 | U35: 0 | V35: 46044 | W35: 46044 | X35: 51.29 | Y35: 0 | Z35: CASH | AA35: REIMBURSE | AB35: COMPLETED | AD35: URBAN CITY | AE35: 51.29 | AG35: 51.29 | AH35: 0 | AI35: EXPENSES PAID CASH BK
C36: 26/1/ | D36: 92 | E36: CASH | F36: OUT | G36: REIMBURSE | H36: T1/5 | I36: R1/5 | L36: 46034 | M36: 46034 | N36: POUKAKIS NICOLAS | O36: TAXI ATHENS | P36: TRANSPORTATION | Q36: TRAVEL EXPENSES | S36: 50.5 | T36: 50.5 | U36: 0 | V36: 46034 | W36: 46034 | X36: 50.5 | Y36: 0 | Z36: CASH | AA36: REIMBURSE | AB36: COMPLETED | AD36: URBAN CITY | AE36: 50.5 | AG36: 50.5 | AH36: 0 | AI36: EXPENSES PAID CASH YK
C37: 26/1/ | D37: 93 | E37: CASH | F37: OUT | G37: REIMBURSE | H37: T1/6 | I37: R1/6 | L37: 46051 | M37: 46051 | N37: POUKAKIS NICOLAS | O37: TAXI ATHENS | P37: TRANSPORTATION | Q37: TRAVEL EXPENSES | S37: 50.06 | T37: 50.06 | U37: 0 | V37: 46051 | W37: 46051 | X37: 50.06 | Y37: 0 | Z37: CASH | AA37: REIMBURSE | AB37: COMPLETED | AD37: URBAN CITY | AE37: 50.06 | AG37: 50.06 | AH37: 0 | AI37: EXPENSES PAID CASH YK
C38: 26/1/ | D38: 94 | E38: CASH | F38: OUT | G38: REIMBURSE | H38: T1/7 | I38: R1/7 | L38: 46048 | M38: 46048 | N38: POUKAKIS NICOLAS | O38: TAXI ATHENS | P38: TRANSPORTATION | Q38: TRAVEL EXPENSES | S38: 50.25 | T38: 50.25 | U38: 0 | V38: 46048 | W38: 46048 | X38: 50.25 | Y38: 0 | Z38: CASH | AA38: REIMBURSE | AB38: COMPLETED | AD38: URBAN CITY | AE38: 50.25 | AG38: 50.25 | AH38: 0 | AI38: EXPENSES PAID CASH YK
A49: T9/
C54: TOTAL TO REIMBURSE | AE54: =SUM(AE33:AE53) -> 284.24
C56: GRAND TOTAL | AE56: =SUM(AE33:AE53) -> 284.24 | AF56: Inv. No: 2021/04/017
O59: * Only 50% of the amount is to be reimburesed for flights to and from Israel
O60: ** Flights that are paid in current month but take place in fallowing month will be reimbured after the flight took place
AE62: Invoice Number | AK62: Date issued
O63: EXPENSES TO BE REIBURSED | T63: =AE54 -> 284.24
O64: MARCH EXPENSES TO BE REIBURSED IN MAY | T64: =AE55 -> 0
O65: GRAND TOTAL | T65: =SUM(T63:T64) -> 284.24
N70: REPORT JANUARY 31ST 2025 | O70: BAD Steffenstein
B72: Ref.No. | C72: REF. NO. | E72: ACCOUNT PAID FROM | F72: INWARDS/ OUTWARDS | G72: EXPENSE OF | H72: Accounting for Travel expenses | I72: Accounting for expense reimbursment | J72: salaries | L72: DATE ISSUED | N72: COMPANY | O72: ITEM | Q72: CATEGORY | R72: TOTAL AMOUNT (foreign curancy) Incl.VAT | S72: Total Amount paid (EURO) incl. VAT | T72: AMOUNT PAID | U72: AMOUNT RECEIVED | V72: DATE PAID | W72: MONTH | X72: Total Payed incl. VAT (EURO) | Y72: Balance (EURO) | Z72: Payed buy | AA72: EXPENSE OF | AC72: Comments | AD72: REIMBURSE FROM / PRORATE TO | AE72: TOTAL AMOUNT to Reimburse (EURO) | AF72: Invoice No. of REIMBURMENT | AG72: TOTAL AMOUNT Incl. VAT (EURO) | AI72: EXPENSES OF | AJ72: Comments | AK72: EXPENSE OF RABONA
C73: 26/1/ | D73: 88 | E73: MASTER CARD A/C | F73: OUT | G73: REIMBURSE | H73: T1/1 | I73: R1/1 | L73: 46043 | M73: 46043 | N73: TAXIQUITTUNG | O73: TAXI GERMANY | P73: TRANSPORTATION | Q73: TRAVEL EXPENSES | S73: 114.1 | T73: 114.1 | U73: 0 | V73: 46043 | W73: 46043 | X73: 114.1 | Y73: 0 | Z73: RMC | AA73: REIMBURSE | AB73: COMPLETED | AD73: BAD STEFFENSTAIN | AE73: 114.1 | AG73: 0 | AH73: 0
C74: 26/1/ | D74: 89 | E74: CASH | F74: OUT | G74: REIMBURSE | H74: T1/2 | I74: R1/2 | L74: 46040 | M74: 46040 | N74: PLATZL HOTEL | O74: ACCOMODATION GERMANY | P74: ACCOMMODATION | Q74: TRAVEL EXPENSES | S74: 237 | T74: 237 | U74: 0 | V74: 46040 | W74: 46040 | X74: 237 | Y74: 0 | Z74: CASH | AA74: REIMBURSE | AB74: COMPLETED | AD74: BAD STEFFENSTAIN | AE74: 237 | AG74: 237 | AH74: 0 | AI74: EXPENSES PAID CASH YK
C113: GRAND TOTAL | AE113: =SUM(AE73:AE112) -> 351.1 | AF113: Inv. No: 2021/04/
AE114: Invoice Number | AK114: Date issued
O115: NOVEMBER EXPENSES TO BE REIBURSED IN DECEMBER | T115: =AE113 -> 351.1
N117: REPORT FEBRUARY 29TH 2024
B119: Ref.No. | H119: Accounting for Travel expenses | I119: Accounting for expense reimbursment | J119: salaries | L119: DATE ISSUED | N119: COMPANY | O119: ITEM | Q119: CATEGORY | R119: TOTAL AMOUNT incl. VAT | S119: Total Amount paid (EURO) incl. VAT | V119: Date payed | W119: MONTH PAYED | X119: Total Payed incl. VAT (EURO) | Y119: Balance (EURO) | Z119: Payed buy | AA119: EXPENSE OF | AC119: Comments | AD119: REIMBURSE FROM / PRORATE TO | AE119: TOTAL AMOUNT to Prorate/Reimburse (EURO) | AF119: Invoice No. of REIMBURMENT | AG119: TOTAL AMOUNT Incl. VAT (EURO) | AI119: EXPENSES OF | AJ119: Comments
S163: … | AE163: =SUM(AE120:AE162) -> 0

Sheet EXP to refund to employees
B2: EXPENSE REPORT MAY 31ST, 2024
B4: REF. NO: MONTH RECEIVED | C4: REF. NO: | E4: ACCOUNT PAID FROM | F4: INWARDS/ OUTWARDS | G4: EXPENSE OF | H4: Ref.No: Travel exp. | I4: Ref.No: Expense reimb. | J4: REF. NO: Salaries …. | K4: Ref.No: Inwards Transf. | L4: Document / Transfer date | M4: MONTH ISSUED | N4: COMPANY | O4: ITEM | P4: SUBCATEGORY | Q4: CATEGORY | R4: TOTAL AMOUNT (foreign curancy) Incl.VAT | S4: TOTAL AMOUNT (EURO) Incl.VAT | T4: AMOUNT PAID | U4: AMOUNT RECEIVED | V4: DATE PAID / DATE RECEIVED …. | W4: MONTH PAYED | X4: TOTAL PAID (EURO) | Y4: BALANCE (EURO) | Z4: PAYMENT TYPE …. | AA4: EXPENSE OF …. | AB4: STATUS | AC4: COMMENTS | AD4: REIMBURSE FROM/ PRORATE TO | AE4: TOTAL AMOUNT (EURO) | AF4: INVOICE NUMBER | AG4: TOTAL AMOUNT Incl. VAT (EURO) | AH4: AMOUNT | AI4: EXPENSES PAID IN CASH BY
C5: 24/5/ | D5: 32 | E5: CURRENT A/C | F5: OUT | G5: SHARE HOLDER | L5: 45422 | M5: 45422 | N5: YORAM KEDEM | O5: TRANSFER TO SHA | P5: TRANSFERS TO SH A/C AND CASH WITHDRAWAL | Q5: PERSONAL EXPENSES OF SHARE HOLDER | S5: 2000 | T5: 2000 | U5: 0 | V5: 45422 | W5: 45422 | X5: 2000 | Y5: 0 | Z5: BT | AA5: SHARE HOLDER | AB5: COMPLETED | AE5: 0 | AG5: 0 | AH5: 2000 | AI5: YORAM KEDEM
C6: 24/5/ | D6: 33 | E6: CURRENT A/C | F6: OUT | G6: SHARE HOLDER | L6: 45422 | M6: 45422 | N6: YORAM KEDEM | O6: TRANSFER TO SHA | P6: TRANSFERS TO SH A/C AND CASH WITHDRAWAL | Q6: PERSONAL EXPENSES OF SHARE HOLDER | S6: 1000 | T6: 1000 | U6: 0 | V6: 45422 | W6: 45422 | X6: 1000 | Y6: 0 | Z6: BT | AA6: SHARE HOLDER | AB6: COMPLETED | AE6: 0 | AG6: 0 | AH6: 1000 | AI6: YORAM KEDEM
C7: 24/5/ | D7: 34 | E7: CURRENT A/C | F7: OUT | G7: SHARE HOLDER | L7: 45426 | M7: 45426 | N7: YORAM KEDEM | O7: TRANSFER TO SHA | P7: TRANSFERS TO SH A/C AND CASH WITHDRAWAL | Q7: PERSONAL EXPENSES OF SHARE HOLDER | S7: 100 | T7: 100 | U7: 0 | V7: 45426 | W7: 45426 | X7: 100 | Y7: 0 | Z7: BT | AA7: SHARE HOLDER | AB7: COMPLETED | AE7: 0 | AG7: 0 | AH7: 100 | AI7: YORAM KEDEM
C8: 24/5/ | D8: 38 | E8: CURRENT A/C | F8: OUT | G8: SHARE HOLDER | L8: 45437 | M8: 45437 | N8: YORAM KEDEM | O8: TRANSFER TO SHA | P8: TRANSFERS TO SH A/C AND CASH WITHDRAWAL | Q8: PERSONAL EXPENSES OF SHARE HOLDER | S8: 100 | T8: 100 | U8: 0 | V8: 45439 | W8: 45439 | X8: 100 | Y8: 0 | Z8: BT | AA8: SHARE HOLDER | AB8: COMPLETED | AE8: 0 | AG8: 0 | AH8: 100 | AI8: YORAM KEDEM
C9: 24/5/ | D9: 39 | E9: CURRENT A/C | F9: OUT | G9: SHARE HOLDER | L9: 45441 | M9: 45441 | N9: YORAM KEDEM | O9: TRANSFER TO SHA | P9: TRANSFERS TO SH A/C AND CASH WITHDRAWAL | Q9: PERSONAL EXPENSES OF SHARE HOLDER | S9: 2000 | T9: 2000 | U9: 0 | V9: 45441 | W9: 45441 | X9: 2000 | Y9: 0 | Z9: BT | AA9: SHARE HOLDER | AB9: COMPLETED | AE9: 0 | AG9: 0 | AH9: 2000 | AI9: YORAM KEDEM
C10: 24/5/ | D10: 40 | E10: CURRENT A/C | F10: OUT | G10: SHARE HOLDER | L10: 45441 | M10: 45441 | N10: YORAM KEDEM | O10: TRANSFER TO SHA | P10: TRANSFERS TO SH A/C AND CASH WITHDRAWAL | Q10: PERSONAL EXPENSES OF SHARE HOLDER | S10: 2000 | T10: 2000 | U10: 0 | V10: 45441 | W10: 45441 | X10: 2000 | Y10: 0 | Z10: BT | AA10: SHARE HOLDER | AB10: COMPLETED | AE10: 0 | AG10: 0 | AH10: 2000 | AI10: YORAM KEDEM
C11: 24/5/ | D11: 45 | E11: MASTER CARD A/C | F11: OUT | G11: SHARE HOLDER | L11: 45439 | M11: 45439 | N11: CELLSAN | O11: PERSONAL EXPENSE OF SH | P11: PAYMENTS MADE ON BEHALF OF SH | Q11: PERSONAL EXPENSES OF SHARE HOLDER | S11: 40 | T11: 40 | U11: 0 | V11: 45439 | W11: 45439 | X11: 40 | Y11: 0 | Z11: RMC | AA11: SHARE HOLDER | AB11: COMPLETED | AE11: 0 | AG11: 0 | AH11: 40 | AI11: YORAM KEDEM
C12: 24/5/ | D12: 48 | E12: MASTER CARD A/C | F12: OUT | G12: SHARE HOLDER | L12: 45436 | M12: 45046 | N12: GINZA | O12: PERSONAL EXPENSE OF SH | P12: PAYMENTS MADE ON BEHALF OF SH | Q12: PERSONAL EXPENSES OF SHARE HOLDER | R12: 87361 | S12: 525.55 | T12: 525.55 | U12: 0 | V12: 45425 | W12: 45425 | X12: 525.55 | Y12: 0 | Z12: RMC | AA12: SHARE HOLDER | AB12: COMPLETED | AE12: 0 | AG12: 0 | AH12: 525.55 | AI12: YORAM KEDEM
C13: 24/5/ | D13: 50 | E13: MASTER CARD A/C | F13: OUT | G13: SHARE HOLDER | L13: 45425 | M13: 45425 | N13: BOLT ALION | O13: PERSONAL EXPENSE OF SH | P13: PAYMENTS MADE ON BEHALF OF SH | Q13: PERSONAL EXPENSES OF SHARE HOLDER | S13: 110.32 | T13: 110.32 | U13: 0 | V13: 45427 | W13: 45427 | X13: 110.32 | Y13: 0 | Z13: RMC | AA13: SHARE HOLDER | AB13: COMPLETED | AE13: 0 | AG13: 0 | AH13: 110.32 | AI13: YORAM KEDEM
C14: 24/5/ | D14: 51 | E14: MASTER CARD A/C | F14: OUT | G14: SHARE HOLDER | L14: 45425 | M14: 45425 | N14: BOLT TOY CONFECTIONARY | O14: PERSONAL EXPENSE OF SH | P14: PAYMENTS MADE ON BEHALF OF SH | Q14: PERSONAL EXPENSES OF SHARE HOLDER | S14: 61.19 | T14: 61.19 | U14: 0 | V14: 45427 | W14: 45427 | X14: 61.19 | Y14: 0 | Z14: RMC | AA14: SHARE HOLDER | AB14: COMPLETED | AE14: 0 | AG14: 0 | AH14: 61.19 | AI14: YORAM KEDEM
C15: 24/5/ | D15: 56 | E15: MASTER CARD A/C | F15: OUT | G15: SHARE HOLDER | L15: 45429 | M15: 45429 | N15: ALPHA MEGA | O15: PERSONAL EXPENSE OF SH | P15: PAYMENTS MADE ON BEHALF OF SH | Q15: PERSONAL EXPENSES OF SHARE HOLDER | S15: 220.13 | T15: 220.13 | U15: 0 | V15: 45429 | W15: 45429 | X15: 220.13 | Y15: 0 | Z15: RMC | AA15: SHARE HOLDER | AB15: COMPLETED | AE15: 0 | AG15: 0 | AH15: 220.13 | AI15: YORAM KEDEM
C16: 24/5/ | D16: 64 | E16: MASTER CARD A/C | F16: OUT | G16: SHARE HOLDER | L16: 45432 | M16: 45432 | N16: STIRNU BUKS | O16: PERSONAL EXPENSE OF SH | P16: PAYMENTS MADE ON BEHALF OF SH | Q16: PERSONAL EXPENSES OF SHARE HOLDER | S16: 60 | T16: 60 | U16: 0 | V16: 45432 | W16: 45432 | X16: 60 | Y16: 0 | Z16: RMC | AA16: SHARE HOLDER | AB16: COMPLETED | AE16: 0 | AG16: 0 | AH16: 60 | AI16: YORAM KEDEM
C17: 24/5/ | D17: 65 | E17: MASTER CARD A/C | F17: OUT | G17: SHARE HOLDER | L17: 45432 | M17: 45432 | N17: DUTY FREE | O17: PERSONAL EXPENSE OF SH | P17: PAYMENTS MADE ON BEHALF OF SH | Q17: PERSONAL EXPENSES OF SHARE HOLDER | S17: 46 | T17: 46 | U17: 0 | V17: 45432 | W17: 45432 | X17: 46 | Y17: 0 | Z17: RMC | AA17: SHARE HOLDER | AB17: COMPLETED | AE17: 0 | AG17: 0 | AH17: 46 | AI17: YORAM KEDEM
C18: 24/5/ | D18: 120 | E18: MASTER CARD A/C | F18: OUT | G18: SHARE HOLDER | L18: 45425 | M18: 45425 | N18: YORAM KEDEM | O18: TRANSFER TO SHA | P18: TRANSFERS TO SH A/C AND CASH WITHDRAWAL | Q18: PERSONAL EXPENSES OF SHARE HOLDER | S18: 85 | T18: 85 | U18: 0 | V18: 45425 | W18: 45425 | X18: 85 | Y18: 0 | Z18: RMC | AA18: SHARE HOLDER | AB18: COMPLETED | AE18: 0 | AG18: 0 | AH18: 85 | AI18: YORAM KEDEM
C19: 24/5/ | D19: 121 | E19: MASTER CARD A/C | F19: OUT | G19: SHARE HOLDER | L19: 45413 | M19: 45413 | N19: NIKE GINZA | O19: PERSONAL EXPENSE OF SH | P19: PAYMENTS MADE ON BEHALF OF SH | Q19: PERSONAL EXPENSES OF SHARE HOLDER | S19: 669.64 | T19: 669.64 | U19: 0 | V19: 45413 | W19: 45413 | X19: 669.64 | Y19: 0 | Z19: RMC | AA19: SHARE HOLDER | AB19: COMPLETED | AE19: 0 | AG19: 0 | AH19: 669.64 | AI19: YORAM KEDEM
C20: 24/5/ | D20: 122 | E20: MASTER CARD A/C | F20: OUT | G20: SHARE HOLDER | L20: 45415 | M20: 45415 | N20: LAWSON | O20: PERSONAL EXPENSE OF SH | P20: PAYMENTS MADE ON BEHALF OF SH | Q20: PERSONAL EXPENSES OF SHARE HOLDER | S20: 105.26 | T20: 105.26 | U20: 0 | V20: 45415 | W20: 45415 | X20: 105.26 | Y20: 0 | Z20: RMC | AA20: SHARE HOLDER | AB20: COMPLETED | AE20: 0 | AG20: 0 | AH20: 105.26 | AI20: YORAM KEDEM
C21: 24/5/ | D21: 123 | E21: MASTER CARD A/C | F21: OUT | G21: SHARE HOLDER | L21: 45425 | M21: 45425 | N21: LE CROBAG FFM | O21: PERSONAL EXPENSE OF SH | P21: PAYMENTS MADE ON BEHALF OF SH | Q21: PERSONAL EXPENSES OF SHARE HOLDER | S21: 14.4 | T21: 14.4 | U21: 0 | V21: 45425 | W21: 45425 | X21: 14.4 | Y21: 0 | Z21: RMC | AA21: SHARE HOLDER | AB21: COMPLETED | AE21: 0 | AG21: 0 | AH21: 14.4 | AI21: YORAM KEDEM
C22: 24/5/ | D22: 129 | E22: MASTER CARD A/C | F22: OUT | G22: SHARE HOLDER | L22: 45416 | M22: 45416 | N22: ORYOURI MASITA | O22: PERSONAL EXPENSE OF SH | P22: PAYMENTS MADE ON BEHALF OF SH | Q22: PERSONAL EXPENSES OF SHARE HOLDER | R22: 142.05 | S22: 866.16 | T22: 866.16 | U22: 0 | V22: 45420 | W22: 45420 | X22: 866.16 | Y22: 0 | Z22: RMC | AA22: SHARE HOLDER | AB22: COMPLETED | AE22: 0 | AG22: 0 | AH22: 866.16 | AI22: YORAM KEDEM
C23: 24/5/ | D23: 130 | E23: MASTER CARD A/C | F23: OUT | G23: SHARE HOLDER | L23: 45414 | M23: 45414 | N23: VIATORI IT | O23: PERSONAL EXPENSE OF SH | P23: PAYMENTS MADE ON BEHALF OF SH | Q23: PERSONAL EXPENSES OF SHARE HOLDER | R23: 930.26 | S23: 873.65 | T23: 873.65 | U23: 0 | V23: 45420 | W23: 45420 | X23: 873.65 | Y23: 0 | Z23: RMC | AA23: SHARE HOLDER | AB23: COMPLETED | AE23: 0 | AG23: 0 | AH23: 873.65 | AI23: YORAM KEDEM
C24: 24/5/ | D24: 131 | E24: MASTER CARD A/C | F24: OUT | G24: SHARE HOLDER | L24: 45417 | M24: 45417 | N24: VIATORI IT | O24: PERSONAL EXPENSE OF SH | P24: PAYMENTS MADE ON BEHALF OF SH | Q24: PERSONAL EXPENSES OF SHARE HOLDER | S24: 590.62 | T24: 590.62 | U24: 0 | V24: 45420 | W24: 45420 | X24: 590.62 | Y24: 0 | Z24: RMC | AA24: SHARE HOLDER | AB24: COMPLETED | AE24: 0 | AG24: 0 | AH24: 590.62 | AI24: YORAM KEDEM
C25: 24/5/ | D25: 140 | E25: MASTER CARD A/C | F25: OUT | G25: SHARE HOLDER | L25: 45443 | M25: 45443 | N25: MANTA RAY GRC | O25: PERSONAL EXPENSE OF SH | P25: PAYMENTS MADE ON BEHALF OF SH | Q25: PERSONAL EXPENSES OF SHARE HOLDER | S25: 80 | T25: 80 | U25: 0 | V25: 45443 | W25: 45443 | X25: 80 | Y25: 0 | Z25: RMC | AA25: SHARE HOLDER | AB25: COMPLETED | AE25: 0 | AG25: 0 | AH25: 80 | AI25: YORAM KEDEM
C26: 24/5/ | D26: 142 | E26: MASTER CARD A/C | F26: OUT | G26: SHARE HOLDER | L26: 45442 | M26: 45442 | N26: COLUMBIA BEACH | O26: PERSONAL EXPENSE OF SH | P26: PAYMENTS MADE ON BEHALF OF SH | Q26: PERSONAL EXPENSES OF SHARE HOLDER | S26: 129.6 | T26: 129.6 | U26: 0 | V26: 45442 | W26: 45442 | X26: 129.6 | Y26: 0 | Z26: RMC | AA26: SHARE HOLDER | AB26: COMPLETED | AC26: MISSING INVOICE/RECEIPT | AE26: 0 | AG26: 0 | AH26: 129.6 | AI26: YORAM KEDEM
B27: 23/3/66 | C27: TOTAL paid on behalf of Share Holder / transferred to Share Holders a/c (Yoram Kedem) | S27: =SUM(S5:S26) -> 11677.52
C28: 24/5/ | D28: 77 | E28: CASH PAYMENTS | F28: OUT | G28: RABONA | H28: T5/15 | L28: 45419 | M28: 45419 | N28: KAITEN SUSHI | O28: ALLOWANCES | P28: ALLOWANCES | Q28: TRAVEL EXPENSES | R28: 25030 | S28: 150.18 | T28: 150.18 | U28: 0 | V28: 45421 | W28: 45421 | X28: 150.18 | Y28: 0 | Z28: CASH | AA28: RABONA | AB28: COMPLETED | AE28: 0 | AG28: 150.18 | AH28: 0 | AI28: EXPENSES PAID CASH YK
C29: 24/5/ | D29: 78 | E29: CASH PAYMENTS | F29: OUT | G29: RABONA | H29: T5/16 | L29: 45425 | M29: 45425 | N29: ITOYA | O29: SYMBOLIC GIFT ON SIGNING | P29: MARKETING PURPOSES (HOSTING VISITS) | Q29: TRAVEL EXPENSES | R29: 47190 | S29: 278.421 | T29: 278.421 | U29: 0 | V29: 45436 | W29: 45436 | X29: 278.421 | Y29: 0 | Z29: CASH | AA29: RABONA | AB29: COMPLETED | AE29: 0 | AG29: 278.421 | AH29: 0 | AI29: EXPENSES PAID CASH YK
C30: 24/5/ | D30: 79 | E30: CASH PAYMENTS | F30: OUT | G30: RABONA | H30: T5/17 | L30: 45422 | M30: 45422 | N30: HULIC | O30: REPRESENTATION ON VISITS | P30: MARKETING PURPOSES (HOSTING VISITS) | Q30: TRAVEL EXPENSES | R30: 82280 | S30: 493.68 | T30: 493.68 | U30: 0 | V30: 45424 | W30: 45424 | X30: 493.68 | Y30: 0 | Z30: CASH | AA30: RABONA | AB30: COMPLETED | AE30: 0 | AG30: 493.68 | AH30: 0 | AI30: EXPENSES PAID CASH YK
C31: 24/5/ | D31: 80 | E31: CASH PAYMENTS | F31: OUT | G31: RABONA | H31: T5/18 | L31: 45420 | M31: 45420 | N31: LA PANZA | O31: REPRESENTATION ON VISITS | P31: MARKETING PURPOSES (HOSTING VISITS) | Q31: TRAVEL EXPENSES | R31: 52360 | S31: 308.924 | T31: 308.924 | U31: 0 | V31: 45422 | W31: 45422 | X31: 308.924 | Y31: 0 | Z31: CASH | AA31: RABONA | AB31: COMPLETED | AE31: 0 | AG31: 308.924 | AH31: 0 | AI31: EXPENSES PAID CASH YK
C32: 24/5/ | D32: 81 | E32: CASH PAYMENTS | F32: OUT | G32: RABONA | H32: T5/19 | L32: 45421 | M32: 45421 | N32: EMIT FISHBAR | O32: ALLOWANCES | P32: ALLOWANCES | Q32: TRAVEL EXPENSES | R32: 4136 | S32: 24.4024 | T32: 24.4024 | U32: 0 | V32: 45422 | W32: 45422 | X32: 24.4024 | Y32: 0 | Z32: CASH | AA32: RABONA | AB32: COMPLETED | AE32: 0 | AG32: 24.4024 | AH32: 0 | AI32: EXPENSES PAID CASH YK
C33: 24/5/ | D33: 82 | E33: CASH PAYMENTS | F33: OUT | G33: RABONA | H33: T5/20 | L33: 45421 | M33: 45421 | N33: HANAMARU NEMURO | O33: ALLOWANCES | P33: ALLOWANCES | Q33: TRAVEL EXPENSES | R33: 14421 | S33: 85.0839 | T33: 85.0839 | U33: 0 | V33: 45423 | W33: 45423 | X33: 85.0839 | Y33: 0 | Z33: CASH | AA33: RABONA | AB33: COMPLETED | AE33: 0 | AG33: 85.0839 | AH33: 0 | AI33: EXPENSES PAID CASH YK
C34: 24/5/ | D34: 83 | E34: CASH PAYMENTS | F34: OUT | G34: RABONA | H34: T5/21 | L34: 45417 | M34: 45417 | N34: DINING BAR W | O34: ALLOWANCES | P34: ALLOWANCES | Q34: TRAVEL EXPENSES | R34: 8873 | S34: 53.238 | T34: 53.238 | U34: 0 | V34: 45420 | W34: 45420 | X34: 53.238 | Y34: 0 | Z34: CASH | AA34: RABONA | AB34: COMPLETED | AE34: 0 | AG34: 53.238 | AH34: 0 | AI34: EXPENSES PAID CASH YK
C35: 24/5/ | D35: 84 | E35: CASH PAYMENTS | F35: OUT | G35: RABONA | H35: T5/22 | L35: 45419 | M35: 45419 | N35: STARBACKS | O35: ALLOWANCES | P35: ALLOWANCES | Q35: TRAVEL EXPENSES | R35: 4706 | S35: 28.236 | T35: 28.236 | U35: 0 | V35: 45419 | W35: 45419 | X35: 28.236 | Y35: 0 | Z35: CASH | AA35: RABONA | AB35: COMPLETED | AE35: 0 | AG35: 28.236 | AH35: 0 | AI35: EXPENSES PAID CASH YK
C36: 24/5/ | D36: 85 | E36: CASH PAYMENTS | F36: OUT | G36: RABONA | H36: T5/23 | L36: 45415 | M36: 45415 | N36: CUCINA ITALIANA | O36: REPRESENTATION ON VISITS | P36: MARKETING PURPOSES (HOSTING VISITS) | Q36: TRAVEL EXPENSES | R36: 67100 | S36: 409.31 | T36: 409.31 | U36: 0 | V36: 45415 | W36: 45415 | X36: 409.31 | Y36: 0 | Z36: CASH | AA36: RABONA | AB36: COMPLETED | AE36: 0 | AG36: 409.31 | AH36: 0 | AI36: EXPENSES PAID CASH YK
C37: 24/5/ | D37: 86 | E37: CASH PAYMENTS | F37: OUT | G37: RABONA | H37: T5/24 | L37: 45417 | M37: 45417 | N37: KANI GORAKU | O37: REPRESENTATION ON VISITS | P37: MARKETING PURPOSES (HOSTING VISITS) | Q37: TRAVEL EXPENSES | R37: 71412 | S37: 428.472 | T37: 428.472 | U37: 0 | V37: 45417 | W37: 45417 | X37: 428.472 | Y37: 0 | Z37: CASH | AA37: RABONA | AB37: COMPLETED | AE37: 0 | AG37: 428.472 | AH37: 0 | AI37: EXPENSES PAID CASH YK
C38: 24/5/ | D38: 87 | E38: CASH PAYMENTS | F38: OUT | G38: RABONA | H38: T5/25 | L38: 45418 | M38: 45418 | N38: NEW JAPAN TOURIST CO. LTD | O38: TAXI JAPAN | P38: TRANSPORTATION | Q38: TRAVEL EXPENSES | R38: 5380 | S38: 32.28 | T38: 32.28 | U38: 0 | V38: 45418 | W38: 45418 | X38: 32.28 | Y38: 0 | Z38: CASH | AA38: RABONA | AB38: COMPLETED | AE38: 0 | AG38: 32.28 | AH38: 0 | AI38: EXPENSES PAID CASH YK
C39: 24/5/ | D39: 88 | E39: CASH PAYMENTS | F39: OUT | G39: RABONA | H39: T5/26 | L39: 45419 | M39: 45419 | N39: GYUKATSUMOTOMURA | O39: ALLOWANCES | P39: ALLOWANCES | Q39: TRAVEL EXPENSES | R39: 10890 | S39: 65.34 | T39: 65.34 | U39: 0 | V39: 45419 | W39: 45419 | X39: 65.34 | Y39: 0 | Z39: CASH | AA39: RABONA | AB39: COMPLETED | AE39: 0 | AG39: 65.34 | AH39: 0 | AI39: EXPENSES PAID CASH YK
... C50: 24/5/ | D50: 99 | E50: CASH PAYMENTS | F50: OUT | G50: RABONA | H50: T5/37 | L50: 45417 | M50: 45417 | N50: UBER | O50: TAXI JAPAN | P50: TRANSPORTATION | Q50: TRAVEL EXPENSES | R50: 6217 | S50: 37.302 | T50: 37.302 | U50: 0 | V50: 45417 | W50: 45417 | X50: 37.302 | Y50: 0 | Z50: CASH | AA50: RABONA | AB50: COMPLETED | AE50: 0 | AG50: 37.302 | AH50: 0 | AI50: EXPENSES PAID CASH YK
C51: 24/5/ | D51: 100 | E51: CASH PAYMENTS | F51: OUT | G51: RABONA | H51: T5/1 | L51: 45399 | M51: 45399 | N51: ELDAN | O51: CAR RENT IL | P51: TRANSPORTATION | Q51: TRAVEL EXPENSES | S51: 778.31 | T51: 778.31 | U51: 0 | V51: 45399 | W51: 45399 | X51: 778.31 | Y51: 0 | Z51: CASH | AA51: RABONA | AB51: COMPLETED | AE51: 0 | AG51: 778.31 | AH51: 0 | AI51: EXPENSES PAID CASH YK
C52: 24/5/ | D52: 101 | E52: CASH PAYMENTS | F52: OUT | G52: RABONA | H52: T5/38 | L52: 45416 | M52: 45416 | N52: UBER | O52: TAXI JAPAN | P52: TRANSPORTATION | Q52: TRAVEL EXPENSES | R52: 8701 | S52: 52.206 | T52: 52.206 | U52: 0 | V52: 45416 | W52: 45416 | X52: 52.206 | Y52: 0 | Z52: CASH | AA52: RABONA | AB52: COMPLETED | AE52: 0 | AG52: 52.206 | AH52: 0 | AI52: EXPENSES PAID CASH YK
C53: 24/5/ | D53: 102 | E53: CASH PAYMENTS | F53: OUT | G53: RABONA | H53: T5/39 | L53: 45416 | M53: 45416 | N53: UBER | O53: TAXI JAPAN | P53: TRANSPORTATION | Q53: TRAVEL EXPENSES | R53: 4314 | S53: 25.884 | T53: 25.884 | U53: 0 | V53: 45416 | W53: 45416 | X53: 25.884 | Y53: 0 | Z53: CASH | AA53: RABONA | AB53: COMPLETED | AE53: 0 | AG53: 25.884 | AH53: 0 | AI53: EXPENSES PAID CASH YK
C54: 24/5/ | D54: 103 | E54: CASH PAYMENTS | F54: OUT | G54: RABONA | H54: T5/40 | L54: 45416 | M54: 45416 | N54: UBER | O54: TAXI JAPAN | P54: TRANSPORTATION | Q54: TRAVEL EXPENSES | R54: 2415 | S54: 14.49 | T54: 14.49 | U54: 0 | V54: 45416 | W54: 45416 | X54: 14.49 | Y54: 0 | Z54: CASH | AA54: RABONA | AB54: COMPLETED | AE54: 0 | AG54: 14.49 | AH54: 0 | AI54: EXPENSES PAID CASH YK
C55: 24/5/ | D55: 104 | E55: CASH PAYMENTS | F55: OUT | G55: RABONA | H55: T5/41 | L55: 45416 | M55: 45416 | N55: UBER | O55: TAXI JAPAN | P55: TRANSPORTATION | Q55: TRAVEL EXPENSES | R55: 2636 | S55: 15.816 | T55: 15.816 | U55: 0 | V55: 45416 | W55: 45416 | X55: 15.816 | Y55: 0 | Z55: CASH | AA55: RABONA | AB55: COMPLETED | AE55: 0 | AG55: 15.816 | AH55: 0 | AI55: EXPENSES PAID CASH YK
C56: 24/5/ | D56: 105 | E56: CASH PAYMENTS | F56: OUT | G56: RABONA | H56: T5/42 | L56: 45423 | M56: 45423 | N56: UBER | O56: TAXI JAPAN | P56: TRANSPORTATION | Q56: TRAVEL EXPENSES | R56: 9860 | S56: 59.16 | T56: 59.16 | U56: 0 | V56: 45423 | W56: 45423 | X56: 59.16 | Y56: 0 | Z56: CASH | AA56: RABONA | AB56: COMPLETED | AE56: 0 | AG56: 59.16 | AH56: 0 | AI56: EXPENSES PAID CASH YK
C57: 24/5/ | D57: 106 | E57: CASH PAYMENTS | F57: OUT | G57: RABONA | H57: T5/43 | L57: 45414 | M57: 45414 | N57: INDIGO HOTEL | O57: ACCOMODATION | P57: ACCOMMODATION | Q57: TRAVEL EXPENSES | R57: 618180 | S57: 3770.898 | T57: 3770.898 | U57: 0 | V57: 45414 | W57: 45414 | X57: 3770.898 | Y57: 0 | Z57: CASH | AA57: RABONA | AB57: COMPLETED | AE57: 0 | AG57: 3770.898 | AH57: 0 | AI57: EXPENSES PAID CASH YK
C58: 24/5/ | D58: 107 | E58: CASH PAYMENTS | F58: OUT | G58: RABONA | H58: T5/44 | L58: 45414 | M58: 45414 | N58: INDIGO HOTEL | O58: ACCOMODATION | P58: ACCOMMODATION | Q58: TRAVEL EXPENSES | R58: 10030 | S58: 61.183 | T58: 61.183 | U58: 0 | V58: 45414 | W58: 45414 | X58: 61.183 | Y58: 0 | Z58: CASH | AA58: RABONA | AB58: COMPLETED | AE58: 0 | AG58: 61.183 | AH58: 0 | AI58: EXPENSES PAID CASH YK
C59: 24/5/ | D59: 108 | E59: CASH PAYMENTS | F59: OUT | G59: RABONA | H59: T5/45 | L59: 45422 | M59: 45422 | N59: W OSAKA | O59: ACCOMODATION | P59: ACCOMMODATION | Q59: TRAVEL EXPENSES | R59: 53940 | S59: 318.246 | T59: 318.246 | U59: 0 | V59: 45422 | W59: 45422 | X59: 318.246 | Y59: 0 | Z59: CASH | AA59: RABONA | AB59: COMPLETED | AE59: 0 | AG59: 318.246 | AH59: 0 | AI59: EXPENSES PAID CASH YK
C60: 24/5/ | D60: 109 | E60: CASH PAYMENTS | F60: OUT | G60: RABONA | H60: T5/46 | L60: 45415 | M60: 45415 | N60: SHIMIZU YUZEN | O60: ALLOWANCES | P60: ALLOWANCES | Q60: TRAVEL EXPENSES | R60: 8800 | S60: 53.68 | T60: 53.68 | U60: 0 | V60: 45415 | W60: 45415 | X60: 53.68 | Y60: 0 | Z60: CASH | AA60: RABONA | AB60: COMPLETED | AE60: 0 | AG60: 53.68 | AH60: 0 | AI60: EXPENSES PAID CASH YK
C61: 24/5/ | D61: 111 | E61: CASH PAYMENTS | F61: OUT | G61: RABONA | L61: 45360 | M61: 45360 | N61: BOLT TGI FRIDAYS | O61: MARKETING PURPOSES | P61: ENTERTAINMENT | Q61: OFFICE / GENERAL ADMINISTRATIVE | S61: 75.1 | T61: 75.1 | U61: 0 | V61: 45360 | W61: 45360 | X61: 75.1 | Y61: 0 | Z61: CASH | AA61: RABONA | AB61: COMPLETED | AE61: 0 | AG61: 75.1 | AH61: 0 | AI61: EXPENSES PAID CASH YK
C62: 24/5/ | D62: 112 | E62: CASH PAYMENTS | F62: OUT | G62: RABONA | L62: 45429 | M62: 45429 | N62: ESSO | O62: FUEL | P62: FUEL | Q62: TRANSPORTATION EXPENSES | S62: 106.51 | T62: 106.51 | U62: 0 | V62: 45429 | W62: 45429 | X62: 106.51 | Y62: 0 | Z62: CASH | AA62: RABONA | AB62: COMPLETED | AE62: 0 | AG62: 106.51 | AH62: 0 | AI62: EXPENSES PAID CASH YK
C63: 24/5/ | D63: 113 | E63: CASH PAYMENTS | F63: OUT | G63: RABONA | L63: 45433 | M63: 45433 | N63: BOLT MCDONALDS | O63: MARKETING PURPOSES | P63: ENTERTAINMENT | Q63: OFFICE / GENERAL ADMINISTRATIVE | S63: 50 | T63: 50 | U63: 0 | V63: 45428 | W63: 45428 | X63: 50 | Y63: 0 | Z63: CASH | AA63: RABONA | AB63: COMPLETED | AE63: 0 | AG63: 50 | AH63: 0 | AI63: EXPENSES PAID CASH YK
C64: 24/5/ | D64: 114 | E64: CASH PAYMENTS | F64: OUT | G64: RABONA | H64: T5/48 | L64: 45372 | M64: 45372 | N64: GR WOLT MAILO'S | O64: ALLOWANCES | P64: ALLOWANCES | Q64: TRAVEL EXPENSES | S64: 29.4 | T64: 29.4 | U64: 0 | V64: 45372 | W64: 45372 | X64: 29.4 | Y64: 0 | Z64: CASH | AA64: RABONA | AB64: COMPLETED | AE64: 0 | AG64: 29.4 | AH64: 0 | AI64: EXPENSES PAID CASH YK
C65: 24/5/ | D65: 133 | E65: CASH PAYMENTS | F65: OUT | G65: RABONA | L65: 45439 | M65: 45439 | N65: DERMADINO LTD | O65: CAR PARKING | P65: CAR PARK | Q65: TRANSPORTATION EXPENSES | S65: 3 | T65: 3 | U65: 0 | V65: 45439 | W65: 45439 | X65: 3 | Y65: 0 | Z65: CASH | AA65: RABONA | AB65: COMPLETED | AE65: 0 | AG65: 3 | AH65: 0 | AI65: EXPENSES PAID CASH YK
C66: TOTAL amount paid by Share Holder (Yoram Kedem) | S66: =SUM(S28:S65) -> 8501.8813
C67: 24/5/ | D67: 7 | E67: CURRENT A/C | F67: IN | G67: RABONA | K67: D | L67: 45365 | M67: 45365 | N67: INWARDS TRANSFER FROM SHA (YORAM KEDEM) | O67: INVESTMENT FROM SHARE HOLDER | P67: BANK TRANSFERS/CASH DEPOSITS (YK) | Q67: INVESTMENT (SHARE HOLDER'S ACCOUNT) | S67: 500 | T67: 0 | U67: 500 | V67: 45425 | W67: 45425 | X67: 500 | Y67: 0 | Z67: CASH | AA67: RABONA | AB67: COMPLETED | AC67: INWARDS TRANSFER | AE67: 0 | AG67: 500 | AH67: 0 | AI67: EXPENSES PAID CASH YK
C68: 24/5/ | D68: 9 | E68: CURRENT A/C | F68: IN | G68: RABONA | K68: F | L68: 45324 | M68: =L68 -> 45324 | N68: EL AL | O68: REFUND RECEIVED IN RELATION TO REF NO: 24/2/23 SHA | P68: BANK TRANSFERS/CASH DEPOSITS (YK) | Q68: INVESTMENT (SHARE HOLDER'S ACCOUNT) | S68: 24.92 | T68: 0 | U68: =S68 -> 24.92 | V68: 45435 | W68: =V68 -> 45435 | X68: =T68+U68 -> 24.92 | Y68: =S68-X68 -> 0 | Z68: CASH | AA68: =G68 -> RABONA | AB68: =IF(Y68>0,"PENDING EXECUTION","COMPLETED") -> COMPLETED | AC68: INWARDS TRANSFER | AE68: =IF(AA68=$AD$5,S68,0) -> 0 | AG68: =IF(Z68=$AG$5,X68,0) -> 0 | AH68: =IF(AA68=$AH$5,X68,0) -> 0 | AI68: EXPENSES PAID CASH YK
C69: 24/5/ | D69: 10 | E69: CURRENT A/C | F69: IN | G69: RABONA | K69: G | L69: 45324 | M69: =L69 -> 45324 | N69: EL AL | O69: REFUND RECEIVED IN RELATION TO REF NO: 24/2/23 SHA | P69: BANK TRANSFERS/CASH DEPOSITS (YK) | Q69: INVESTMENT (SHARE HOLDER'S ACCOUNT) | S69: 194.76 | T69: 0 | U69: =S69 -> 194.76 | V69: 45435 | W69: =V69 -> 45435 | X69: =T69+U69 -> 194.76 | Y69: =S69-X69 -> 0 | Z69: CASH | AA69: =G69 -> RABONA | AB69: =IF(Y69>0,"PENDING EXECUTION","COMPLETED") -> COMPLETED | AC69: INWARDS TRANSFER | AE69: =IF(AA69=$AD$5,S69,0) -> 0 | AG69: =IF(Z69=$AG$5,X69,0) -> 0 | AH69: =IF(AA69=$AH$5,X69,0) -> 0 | AI69: EXPENSES PAID CASH YK
C70: 24/5/ | D70: 11 | E70: CURRENT A/C | F70: IN | G70: RABONA | K70: H | L70: 45324 | M70: =L70 -> 45324 | N70: EL AL | O70: REFUND RECEIVED IN RELATION TO REF NO: 24/2/23 SHA | P70: BANK TRANSFERS/CASH DEPOSITS (YK) | Q70: INVESTMENT (SHARE HOLDER'S ACCOUNT) | S70: 24.92 | T70: 0 | U70: =S70 -> 24.92 | V70: 45435 | W70: =V70 -> 45435 | X70: =T70+U70 -> 24.92 | Y70: =S70-X70 -> 0 | Z70: CASH | AA70: =G70 -> RABONA | AB70: =IF(Y70>0,"PENDING EXECUTION","COMPLETED") -> COMPLETED | AC70: INWARDS TRANSFER | AE70: =IF(AA70=$AD$5,S70,0) -> 0 | AG70: =IF(Z70=$AG$5,X70,0) -> 0 | AH70: =IF(AA70=$AH$5,X70,0) -> 0 | AI70: EXPENSES PAID CASH YK
C71: 24/5/ | D71: 18 | E71: CURRENT A/C | F71: IN | G71: RABONA | K71: O | L71: 45434 | M71: 45434 | N71: INWARDS TRANSFER FROM SHA (YORAM KEDEM) | O71: INVESTMENT FROM SHARE HOLDER | P71: BANK TRANSFERS/CASH DEPOSITS (YK) | Q71: INVESTMENT (SHARE HOLDER'S ACCOUNT) | S71: 50 | T71: 0 | U71: 50 | V71: 45434 | W71: 45434 | X71: 50 | Y71: 0 | Z71: CASH | AA71: RABONA | AB71: COMPLETED | AC71: INWARDS TRANSFER | AE71: 0 | AG71: 50 | AH71: 0 | AI71: EXPENSES PAID CASH YK
C72: 24/5/ | D72: 21 | E72: MASTER CARD A/C | F72: IN | G72: RABONA | K72: R | L72: 45419 | M72: 45419 | N72: INWARDS TRANSFER FROM SHA (YORAM KEDEM) | O72: INVESTMENT FROM SHARE HOLDER | P72: BANK TRANSFERS/CASH DEPOSITS (YK) | Q72: INVESTMENT (SHARE HOLDER'S ACCOUNT) | S72: 20 | T72: 0 | U72: =S72 -> 20 | V72: 45419 | W72: 45419 | X72: 20 | Y72: 0 | Z72: CASH | AA72: RABONA | AB72: COMPLETED | AC72: INWARDS TRANSFER | AE72: 0 | AG72: 20 | AH72: 0 | AI72: EXPENSES PAID CASH YK
C73: 24/5/ | D73: 22 | E73: MASTER CARD A/C | F73: IN | G73: RABONA | K73: S | L73: 45421 | M73: 45421 | N73: INWARDS TRANSFER FROM SHA (YORAM KEDEM) | O73: INVESTMENT FROM SHARE HOLDER | P73: BANK TRANSFERS/CASH DEPOSITS (YK) | Q73: INVESTMENT (SHARE HOLDER'S ACCOUNT) | S73: 500 | T73: 0 | U73: =S73 -> 500 | V73: 45421 | W73: 45421 | X73: 500 | Y73: 0 | Z73: CASH | AA73: RABONA | AB73: COMPLETED | AC73: INWARDS TRANSFER | AE73: 0 | AG73: 500 | AH73: 0 | AI73: EXPENSES PAID CASH YK
C74: 24/5/ | D74: 25 | E74: MASTER CARD A/C | F74: IN | G74: RABONA | K74: V | L74: 45432 | M74: 45432 | N74: INWARDS TRANSFER FROM SHA (YORAM KEDEM) | O74: INVESTMENT FROM SHARE HOLDER | P74: BANK TRANSFERS/CASH DEPOSITS (YK) | Q74: INVESTMENT (SHARE HOLDER'S ACCOUNT) | S74: 500 | T74: 0 | U74: =S74 -> 500 | V74: 45432 | W74: 45432 | X74: 500 | Y74: 0 | Z74: CASH | AA74: RABONA | AB74: COMPLETED | AC74: INWARDS TRANSFER | AE74: 0 | AG74: 500 | AH74: 0 | AI74: EXPENSES PAID CASH YK
C75: 24/5/ | D75: 26 | E75: MASTER CARD A/C | F75: IN | G75: RABONA | K75: W | L75: 45440 | M75: 45440 | N75: INWARDS TRANSFER FROM SHA (YORAM KEDEM) | O75: INVESTMENT FROM SHARE HOLDER | P75: BANK TRANSFERS/CASH DEPOSITS (YK) | Q75: INVESTMENT (SHARE HOLDER'S ACCOUNT) | S75: 200 | T75: 0 | U75: =S75 -> 200 | V75: 45440 | W75: 45440 | X75: 200 | Y75: 0 | Z75: CASH | AA75: RABONA | AB75: COMPLETED | AC75: INWARDS TRANSFER | AE75: 0 | AG75: 200 | AH75: 0 | AI75: EXPENSES PAID CASH YK
V76: 0 | X76: 119.5 | Y76: 0 | Z76: EXPENSES PAID CASH YK
V77: 0 | X77: 74.4 | Y77: 0 | Z77: EXPENSES PAID CASH YK
V78: 0 | X78: 51 | Y78: 0 | Z78: EXPENSES PAID CASH YK
V79: 0 | X79: 98 | Y79: 0 | Z79: EXPENSES PAID CASH YK
C80: TOTAL amount INWARDS TRANSFERS from Share Holder (Yoram Kedem) | S80: =SUM(S67:S75) -> 2014.6
C81: TOTAL EXPENSE REIMBURSMENT TO SHAREHOLDER (YORAM KEDEM) | R81: 45443 | S81: =S27-S66-S80 -> 1161.0387
B84: EXPENSE REPORT MAY 31ST, 2024
B86: REF. NO: MONTH RECEIVED | C86: REF. NO: | E86: ACCOUNT PAID FROM | F86: INWARDS/ OUTWARDS | G86: EXPENSE OF | H86: Ref.No: Travel exp. | I86: Ref.No: Expense reimb. | J86: REF. NO: Salaries …. | K86: Ref.No: Inwards Transf. | L86: Document / Transfer date | M86: MONTH ISSUED | N86: COMPANY | O86: ITEM | P86: SUBCATEGORY | Q86: CATEGORY | R86: TOTAL AMOUNT (foreign curancy) Incl.VAT | S86: TOTAL AMOUNT (EURO) Incl.VAT | T86: AMOUNT PAID | U86: AMOUNT RECEIVED | V86: DATE PAID / DATE RECEIVED …. | W86: MONTH PAYED | X86: TOTAL PAID (EURO) | Y86: BALANCE (EURO) | Z86: PAYMENT TYPE …. | AA86: EXPENSE OF …. | AB86: STATUS | AC86: COMMENTS | AD86: REIMBURSE FROM/ PRORATE TO | AE86: TOTAL AMOUNT (EURO) | AF86: INVOICE NUMBER | AG86: TOTAL AMOUNT Incl. VAT (EURO) | AH86: AMOUNT | AI86: EXPENSES PAID IN CASH BY
B101: 23/3/66 | C101: TOTAL paid on behalf of Share Holder / transferred to Share Holders a/c (Betija Kedem) | S101: =SUM(S87:S100) -> 0
C102: 24/5/ | D102: 74 | E102: CASH PAYMENTS | F102: OUT | G102: RABONA | L102: 45437 | M102: =L102 -> 45437 | N102: A.Y.K. CO LTD | O102: DRINKING WATER FIX | P102: OFFICE SUPPLIES AND SUNDRIES | Q102: OFFICE / GENERAL ADMINISTRATIVE | S102: 71.4 | T102: =S102 -> 71.4 | U102: 0 | V102: 45442 | W102: =V102 -> 45442 | X102: =T102+U102 -> 71.4 | Y102: =S102-X102 -> 0 | Z102: CASH | AA102: =G102 -> RABONA | AB102: =IF(Y102>0,"PENDING EXECUTION","COMPLETED") -> COMPLETED | AE102: =IF(AA102=$AD$5,S102,0) -> 0 | AG102: =IF(Z102=$AG$5,X102,0) -> 0 | AH102: =IF(AA102=$AH$5,X102,0) -> 0 | AI102: EXPENSES PAID CASH BK
C103: 24/5/ | D103: 75 | E103: CASH PAYMENTS | F103: OUT | G103: RABONA | L103: 45436 | M103: =L103 -> 45436 | N103: DERMADINO LTD | O103: CAR PARKING | P103: CAR PARK | Q103: TRANSPORTATION EXPENSES | S103: 3 | T103: =S103 -> 3 | U103: 0 | V103: =L103 -> 45436 | W103: =V103 -> 45436 | X103: =T103+U103 -> 3 | Y103: =S103-X103 -> 0 | Z103: CASH | AA103: =G103 -> RABONA | AB103: =IF(Y103>0,"PENDING EXECUTION","COMPLETED") -> COMPLETED | AE103: =IF(AA103=$AD$5,S103,0) -> 0 | AG103: =IF(Z103=$AG$5,X103,0) -> 0 | AH103: =IF(AA103=$AH$5,X103,0) -> 0 | AI103: EXPENSES PAID CASH BK
C104: 24/5/ | D104: 76 | E104: CASH PAYMENTS | F104: OUT | G104: RABONA | L104: 45434 | M104: =L104 -> 45434 | N104: MIELE | O104: COFFEE MASHINE FILTERS | P104: OFFICE SUPPLIES AND SUNDRIES | Q104: OFFICE / GENERAL ADMINISTRATIVE | S104: 130 | T104: =S104 -> 130 | U104: 0 | V104: 45434 | W104: =V104 -> 45434 | X104: =T104+U104 -> 130 | Y104: =S104-X104 -> 0 | Z104: CASH | AA104: =G104 -> RABONA | AB104: =IF(Y104>0,"PENDING EXECUTION","COMPLETED") -> COMPLETED | AE104: =IF(AA104=$AD$5,S104,0) -> 0 | AG104: =IF(Z104=$AG$5,X104,0) -> 0 | AH104: =IF(AA104=$AH$5,X104,0) -> 0 | AI104: EXPENSES PAID CASH BK
C105: TOTAL amount paid by Share Holder (Betija Kedem) | S105: =SUM(S102:S104) -> 204.4
S106: 0
C116: TOTAL amount INWARDS TRANSFERS from Share Holder (Betija Kedem) | S116: ='EXPENSES Mothly Totals'!D16 -> 0
C117: TOTAL EXPENSE REIMBURSMENT TO SHAREHOLDER (BETIJA KEDEM) | R117: 45443 | S117: =S105-S101 -> 204.4
M120: =M111+#REF! -> #REF! | AA120: ='RABONA PAYMENTS'!AG206 -> 10602.627
