Workbook

Sheet Agreement Tracker
D2: RABONA HOLDINGS LTD
D3: Service Agreement & Monthly Invoicing Tracker
D4: Service Provider: Rabona Holdings Ltd (HE 402420, Limassol, Cyprus) · Confidential · Rev 01 · Prepared 23 Jul 2026
B6: Project Name | C6: Country | D6: City | E6: Agreement Signing Date | F6: Client (Legal Entity) | G6: Primary Contact Person | H6: Contact Position | I6: Contact Email (Monthly Invoice Issuance) | J6: Contact Telephone | K6: Monthly Invoice Date | L6: Monthly Fee | M6: Currency | N6: VAT Applicable | O6: VAT Rate | P6: Agreement Start Date | Q6: Agreement End Date | R6: Invoice Ref / PO | S6: Status | T6: Notes
A7: 1 | B7: Urban City 44 | C7: Greece | D7: Athens | E7: 45320 | F7: Evimer Ltd (HE 439329, Nicosia, Cyprus) | G7: Gal Amar, Yota Spioliti | H7: Finance | I7: finance@astrea-properties.com; controller@astrea-properties.com | J7: +972 52 466 6892 | K7: On/before 25th | L7: 10000 | M7: EUR | N7: Yes | O7: 0.19 | P7: 45292 | Q7: 46387 | S7: Active | T7: Urban City 44, Athens. €10,000/mo + VAT from 1 Jan 2024. Client Evimer Ltd (Cyprus). Invoice recipients: Gal Amar (finance@) and Yota Spilioti — Controller (controller@astrea-properties.com). VAT: Cyprus-domestic 19% tentatively shown — CONFIRM (immovable-property rules may point to Greek VAT).
A8: 2 | B8: Kipseli | C8: Greece | D8: Athens (Kypseli) | E8: 45748 | F8: Sunday Lifestyle, S.L. (Barcelona, Spain) | G8: Amir Yagil, Guy Gelboiz | I8: amir@bcapital.com (cc: guyg@bcapital.com) | J8: +357 97 795 555 | K8: On/before 25th | L8: 6000 | M8: EUR | N8: No | O8: 0 | P8: 45748 | Q8: 46538 | S8: Active | T8: Kipseli project. €6,000/mo advances; total €160,000; plus 10% cost-saving bonus. Client Sunday Lifestyle S.L. (Spain). Invoice settled on/before the 25th of the month issued. To: Amir Yagil; cc: Guy Galboiz (bcapital). Confirm project city; telephone shown is Guy Galboiz. VAT: EU B2B reverse charge assumed — CONFIRM.
A9: 3 | B9: Blue Lagoon | C9: Greece | D9: Loutraki | E9: 45320 | F9: BTS Real Estate SM SA (Athens, Greece) | G9: Gal Amar, Yota Spioliti | H9: Finance | I9: finance@astrea-properties.com; controller@astrea-properties.com | J9: +972 52 466 6892 | K9: On/before 25th | L9: 5000 | M9: EUR | N9: No | O9: 0 | P9: 45139 | Q9: 46387 | S9: Active | T9: Blue Lagoon, Loutraki. €3,000/mo + VAT (Aug–Dec 2023) then €5,000/mo + VAT from 1 Jan 2024. Client BTS Real Estate SM SA (Greece). Invoice recipients: Gal Amar & Yota Spilioti (Controller), Astrea. VAT: EU B2B reverse charge assumed — CONFIRM.
A10: 4 | B10: Evia Mare | C10: Greece | D10: Eretria (Evia) | E10: 46044 | F10: Diamond Star Real Estate Single Member (Athens, Greece) | G10: Gal Amar, Yota Spioliti | H10: Finance | I10: finance@astrea-properties.com; controller@astrea-properties.com | J10: +972 52 466 6892 | K10: On/before 25th | L10: 3750 | M10: EUR | N10: No | O10: 0 | P10: 46023 | Q10: 46752 | S10: Active | T10: Evia Mare residential, Leof. Archeou Theatrou, Eretria. €3,750/mo non-refundable advances (~50% of total); balance on handover; total €180,000; plus 10% cost-saving bonus. Client Diamond Star Real Estate SM (Greece). Invoice recipients: Gal Amar & Yota Spilioti (Controller), Astrea. VAT: EU B2B reverse charge assumed — CONFIRM.
A11: 5 | B11: Hotel Echo | C11: Greece | D11: Athens | E11: 45566 | F11: Oz Shlomi Single Member S.A. (Athens, Greece) | G11: Shlomi Oz | I11: shlomi@oz-ceramica.co.il (cc: e.roditi@progressinc.gr) | K11: On/before 25th | L11: 3500 | M11: EUR | N11: No | O11: 0 | P11: 45566 | Q11: 47118 | S11: Active | T11: Hotel Echo, Athens. Milestone fees: Design €3,500/mo (from Oct 2024) to Milestone A; Execution €6,500/mo to handover (+ one-time €24,000 bonus); Post-handover €3,000/mo. Client Oz Shlomi Single Member S.A. (Greece). To: Shlomi Oz; cc: Eva Roditi (Progress Inc). CURRENT MILESTONE/FEE (shown €6,500) TO CONFIRM. VAT: reverse charge assumed — CONFIRM.
A12: 6 | B12: Thermalpark Spa Hotel (Obermain Therme) | C12: Germany | D12: Bad Staffelstein | E12: 46021 | F12: 613 Investment Group GmbH (HRB 4249, Coburg, Germany) | G12: Joseph Moran | H12: Managing Director | I12: joseph@613hotels.com | J12: +1 (310) 346 2660 | K12: On/before 25th | L12: 2500 | M12: EUR | N12: No | O12: 0 | P12: 46023 | Q12: 47483 | S12: Active | T12: Spa hotel, ~120 keys. Stage fees: Design/Permit/Tender €2,500/mo; Execution €5,250/mo (~24 mo); Handover/Snagging €2,250/mo. Total €180,000. 4-month trial period from start. Agreement dated 30 Dec 2025. CURRENT STAGE/FEE TO CONFIRM. VAT: EU B2B reverse charge assumed — CONFIRM.
A13: 7 | B13: City Hall Hotel (Bären Areal) | C13: Germany | D13: Bad Staffelstein | E13: 46021 | F13: 613 Investment Group GmbH (HRB 4249, Coburg, Germany) | G13: Joseph Moran | H13: Managing Director | I13: joseph@613hotels.com | J13: +1 (310) 346 2660 | K13: 15th of the Month | L13: 2500 | M13: EUR | N13: No | O13: 0 | P13: 46023 | Q13: 47483 | S13: Active | T13: Bad Staffelstein Urban City Hall Hotel (Bären Areal), heritage-integrated, ~85 keys. Stage fees: Design/Permit/Tender €2,500/mo (from 1 Jan 2026); Execution €5,250/mo (~24 mo); Handover/Snagging €2,250/mo. Total €180,000. Agreement dated 30 Dec 2025. CURRENT STAGE/FEE TO CONFIRM. VAT: EU B2B reverse charge assumed — CONFIRM.
A14: 8 | B14: Boutique Hotels Portfolio Retainer (5 hotels) | C14: Germany | D14: Various (Bavaria) | E14: 46220 | F14: 613 Investment Group GmbH (HRB 4249, Coburg, Germany) | G14: Joseph Moran | H14: Managing Director | I14: joseph@613hotels.com | J14: +1 (310) 346 2660 | K14: On/before 25th | L14: 2000 | M14: EUR | N14: No | O14: 0 | P14: 46235 | Q14: 46783 | S14: Active | T14: Single portfolio retainer covering 5 boutique hotels: Adam Riese (Bad Staffelstein); Hotel 57 / Steinweg 57 (Coburg); Hotel The Post (Pfarrweisach); Hahnmühle 1323 (Coburg); The Square (Coburg). Combined fee — Phase 1 €2,000/mo (Aug 2026–Mar 2027), Phase 2 €3,400/mo (Apr 2027–Jan 2028); extension €7,500/mo. Completion fees at practical completion: Adam Riese €16,500, Hotel 57 €16,500, The Post €11,000, Hahnmühle €3,000, The Square €3,000. Invoiced monthly IN ADVANCE, due 14 days. Dated 12 Jul 2026, executed 17 Jul 2026. Contract notice contact: Shani Moran. VAT: EU B2B reverse charge assumed — CONFIRM.
A15: 9 | B15: Thermalpark Residenz (Residence 58) | C15: Germany | D15: Bad Staffelstein | E15: 46220 | F15: 613 Investment Group GmbH (HRB 4249, Coburg, Germany) | G15: Joseph Moran | H15: Managing Director | I15: joseph@613investmentgroup.com | J15: +1 (310) 346 2660 | K15: On/before 25th | L15: 2000 | M15: EUR | N15: No | O15: 0 | P15: 46174 | Q15: 47269 | S15: Active | T15: Wellness-led residential — 58 apartments, Am Kurpark, Bad Staffelstein. Phase 1 €2,000/mo (Jun–Dec 2026), Phase 2 €4,100/mo (Jan 2027–May 2029); Completion payment €30,100 at end of term. Total €163,000. Invoiced monthly IN ARREARS, due 30 days. Dated 12 Jul 2026, executed 17 Jul 2026. VAT: EU B2B reverse charge assumed — CONFIRM.

Sheet Fee Schedule
A1: RABONA HOLDINGS — FEE SCHEDULE (phased monthly fees per project & agreement)
A2: One row per fee phase/stage. Yellow = confirm/complete (mainly milestone-based stage change-over dates and VAT). 'IN EFFECT' shows the monthly amount billable as of the date in C3. One-off items (bonuses / completion / caps) are listed as separate lines.
B3: As-of date: | C3: 46266 | E3: Total monthly fees in effect (as-of): | I3: =SUM(K6:K200) -> 37250
A5: # | B5: PROJECT | C5: CLIENT (LEGAL ENTITY) | D5: COUNTRY | E5: FEE LINE / STAGE | F5: BASIS | G5: EFFECTIVE FROM | H5: EFFECTIVE TO | I5: MONTHLY AMOUNT (€) | J5: ONE-OFF (€) | K5: IN EFFECT (as-of) | L5: INVOICE DAY | M5: VAT | N5: AGREEMENT END | O5: STATUS | P5: CONFIRM / NOTES | Q5: projkey (helper)
A6: 1 | B6: Urban City 44 | C6: Evimer Ltd (HE 439329, Nicosia, Cyprus) | D6: Greece | E6: Monthly consultancy fee | F6: Monthly advance | G6: 45292 | H6: 46387 | I6: 10000 | K6: =IF(AND($G6<>"",$C$3>=$G6,OR($H6="",$C$3<=$H6)),$I6,"") -> 10000 | L6: On/before 25th | M6: 19% (confirm) | N6: 46387 | O6: Active | P6: €10,000/mo + VAT. VAT 19% tentative — confirm immovable-property rules. | Q6: Urban City 44
A7: 2 | B7: Kipseli | C7: Sunday Lifestyle, S.L. (Barcelona, Spain) | D7: Greece | E7: Monthly advance | F7: Monthly advance | G7: 45748 | H7: 46538 | I7: 6000 | K7: =IF(AND($G7<>"",$C$3>=$G7,OR($H7="",$C$3<=$H7)),$I7,"") -> 6000 | L7: On/before 25th | M7: No (reverse charge) | N7: 46538 | O7: Active | P7: Advances; total cap €160,000. | Q7: Kipseli
E8: 10% cost-saving bonus | F8: One-off (end) | M8: No | P8: 10% of cost savings — amount TBC. | Q8: Kipseli
A9: 3 | B9: Blue Lagoon | C9: BTS Real Estate SM SA (Athens, Greece) | D9: Greece | E9: Monthly fee — Phase 1 | F9: Monthly advance | G9: 45139 | H9: 45291 | I9: 3000 | K9: =IF(AND($G9<>"",$C$3>=$G9,OR($H9="",$C$3<=$H9)),$I9,"") | L9: On/before 25th | M9: No (reverse charge) | N9: 46387 | O9: Active | P9: Aug–Dec 2023. | Q9: Blue Lagoon
E10: Monthly fee — Phase 2 | F10: Monthly advance | G10: 45292 | H10: 46387 | I10: 5000 | K10: =IF(AND($G10<>"",$C$3>=$G10,OR($H10="",$C$3<=$H10)),$I10,"") -> 5000 | M10: No (reverse charge) | P10: From 1 Jan 2024. | Q10: Blue Lagoon
A11: 4 | B11: Evia Mare | C11: Diamond Star Real Estate SM (Athens, Greece) | D11: Greece | E11: Monthly advance (~50% of total) | F11: Monthly advance | G11: 46023 | H11: 46752 | I11: 3750 | K11: =IF(AND($G11<>"",$C$3>=$G11,OR($H11="",$C$3<=$H11)),$I11,"") -> 3750 | L11: On/before 25th | M11: No (reverse charge) | N11: 46752 | O11: Active | P11: Non-refundable advances; total €180,000. | Q11: Evia Mare
E12: Balance on handover | F12: One-off (handover) | M12: No | P12: Balance to total €180,000 — amount/date TBC. | Q12: Evia Mare
E13: 10% cost-saving bonus | F13: One-off (end) | M13: No | P13: 10% of savings — amount TBC. | Q13: Evia Mare
A14: 5 | B14: Hotel Echo | C14: Oz Shlomi Single Member S.A. (Athens, Greece) | D14: Greece | E14: Stage 1 — Design | F14: Monthly (stage) | G14: 45566 | I14: 3500 | K14: =IF(AND($G14<>"",$C$3>=$G14,OR($H14="",$C$3<=$H14)),$I14,"") -> 3500 | L14: On/before 25th | M14: No (reverse charge) | N14: 47118 | O14: Active | P14: To Milestone A — change-over date TBC. | Q14: Hotel Echo
E15: Stage 2 — Execution | F15: Monthly (stage) | I15: 6500 | K15: =IF(AND($G15<>"",$C$3>=$G15,OR($H15="",$C$3<=$H15)),$I15,"") | M15: No | P15: From Milestone A to handover — dates TBC. Confirm current stage. | Q15: Hotel Echo
E16: Stage 3 — Post-handover | F16: Monthly (stage) | H16: 47118 | I16: 3000 | K16: =IF(AND($G16<>"",$C$3>=$G16,OR($H16="",$C$3<=$H16)),$I16,"") | M16: No | P16: From handover — start date TBC. | Q16: Hotel Echo
E17: Execution completion bonus | F17: One-off | J17: 24000 | M17: No | P17: One-time €24,000 at execution completion. | Q17: Hotel Echo
A18: 6 | B18: Thermalpark Spa Hotel (Obermain Therme) | C18: 613 Investment Group GmbH (HRB 4249, Coburg, Germany) | D18: Germany | E18: Stage 1 — Design/Permit/Tender | F18: Monthly (stage) | G18: 46023 | I18: 2500 | K18: =IF(AND($G18<>"",$C$3>=$G18,OR($H18="",$C$3<=$H18)),$I18,"") -> 2500 | L18: On/before 25th | M18: No (reverse charge) | N18: 47483 | O18: Active | P18: 4-month trial from start. Change-over date TBC. | Q18: Thermalpark Spa Hotel (Obermain Therme)
E19: Stage 2 — Execution (~24 mo) | F19: Monthly (stage) | I19: 5250 | K19: =IF(AND($G19<>"",$C$3>=$G19,OR($H19="",$C$3<=$H19)),$I19,"") | M19: No | P19: ~24 months — dates TBC. Confirm current stage. | Q19: Thermalpark Spa Hotel (Obermain Therme)
E20: Stage 3 — Handover/Snagging | F20: Monthly (stage) | H20: 47483 | I20: 2250 | K20: =IF(AND($G20<>"",$C$3>=$G20,OR($H20="",$C$3<=$H20)),$I20,"") | M20: No | P20: Start date TBC. Total €180,000. | Q20: Thermalpark Spa Hotel (Obermain Therme)
A21: 7 | B21: City Hall Hotel (Bären Areal) | C21: 613 Investment Group GmbH (HRB 4249, Coburg, Germany) | D21: Germany | E21: Stage 1 — Design/Permit/Tender | F21: Monthly (stage) | G21: 46023 | I21: 2500 | K21: =IF(AND($G21<>"",$C$3>=$G21,OR($H21="",$C$3<=$H21)),$I21,"") -> 2500 | L21: 15th of the month | M21: No (reverse charge) | N21: 47483 | O21: Active | P21: 4-month trial from start. Change-over date TBC. | Q21: City Hall Hotel (Bären Areal)
E22: Stage 2 — Execution (~24 mo) | F22: Monthly (stage) | I22: 5250 | K22: =IF(AND($G22<>"",$C$3>=$G22,OR($H22="",$C$3<=$H22)),$I22,"") | M22: No | P22: ~24 months — dates TBC. Confirm current stage. | Q22: City Hall Hotel (Bären Areal)
E23: Stage 3 — Handover/Snagging | F23: Monthly (stage) | H23: 47483 | I23: 2250 | K23: =IF(AND($G23<>"",$C$3>=$G23,OR($H23="",$C$3<=$H23)),$I23,"") | M23: No | P23: Start date TBC. Total €180,000. | Q23: City Hall Hotel (Bären Areal)
A24: 8 | B24: Boutique Hotels Portfolio Retainer (5 hotels) | C24: 613 Investment Group GmbH (HRB 4249, Coburg, Germany) | D24: Germany | E24: Phase 1 | F24: Monthly advance | G24: 46235 | H24: 46477 | I24: 2000 | K24: =IF(AND($G24<>"",$C$3>=$G24,OR($H24="",$C$3<=$H24)),$I24,"") -> 2000 | L24: On/before 25th | M24: No (reverse charge) | N24: 46783 | O24: Active | P24: Aug 2026–Mar 2027. Due 14 days. | Q24: Boutique Hotels Portfolio Retainer (5 hotels)
E25: Phase 2 | F25: Monthly advance | G25: 46478 | H25: 46783 | I25: 3400 | K25: =IF(AND($G25<>"",$C$3>=$G25,OR($H25="",$C$3<=$H25)),$I25,"") | M25: No | P25: Apr 2027–Jan 2028. | Q25: Boutique Hotels Portfolio Retainer (5 hotels)
E26: Extension (if extended) | F26: Monthly (optional) | I26: 7500 | M26: No | P26: €7,500/mo if extended. | Q26: Boutique Hotels Portfolio Retainer (5 hotels)
E27: Completion fees (per hotel) | F27: One-off | J27: 50000 | M27: No | P27: At practical completion: Adam Riese 16,500 + Hotel 57 16,500 + The Post 11,000 + Hahnmühle 3,000 + The Square 3,000 = 50,000. | Q27: Boutique Hotels Portfolio Retainer (5 hotels)
A28: 9 | B28: Thermalpark Residenz (Residence 58) | C28: 613 Investment Group GmbH (HRB 4249, Coburg, Germany) | D28: Germany | E28: Phase 1 | F28: Monthly arrears | G28: 46174 | H28: 46387 | I28: 2000 | K28: =IF(AND($G28<>"",$C$3>=$G28,OR($H28="",$C$3<=$H28)),$I28,"") -> 2000 | L28: On/before 25th | M28: No (reverse charge) | N28: 47269 | O28: Active | P28: Jun–Dec 2026. Due 30 days. | Q28: Thermalpark Residenz (Residence 58)
E29: Phase 2 | F29: Monthly arrears | G29: 46388 | H29: 47269 | I29: 4100 | K29: =IF(AND($G29<>"",$C$3>=$G29,OR($H29="",$C$3<=$H29)),$I29,"") | M29: No | P29: Jan 2027–May 2029. | Q29: Thermalpark Residenz (Residence 58)
E30: Completion payment | F30: One-off (end) | J30: 30100 | M30: No | P30: At end of term. Total €163,000. | Q30: Thermalpark Residenz (Residence 58)

Sheet Current Month Invoicing
A1: RABONA HOLDINGS — CURRENT MONTH INVOICING
A2: Pick the invoicing month in C3. GREEN cells pull automatically (monthly fee from the Fee Schedule tab; client & VAT% from the Agreement Tracker). YELLOW cells you fill: fixed reimbursement, one-off invoices, credit notes (enter as negative), invoice number, and issued/paid dates. 'Accumulated Expenses' will later come from the system per project.
B3: Invoicing month: | C3: 46266
A5: # | B5: PROJECT | C5: CLIENT | D5: MONTHLY FEE (6.1) | E5: FIXED REIMB. (6.2) | F5: ACCUM. EXPENSES | G5: ONE-OFF INVOICE | H5: CREDIT NOTES | I5: NET TOTAL | J5: VAT % | K5: VAT € | L5: GRAND TOTAL | M5: INVOICE No | N5: DATE ISSUED | O5: DATE PAID | P5: STATUS | Q5: NOTES
A6: 1 | B6: Urban City 44 | C6: =IFERROR(INDEX('Agreement Tracker'!$F$7:$F$15,MATCH($B6,'Agreement Tracker'!$B$7:$B$15,0)),"") -> Evimer Ltd (HE 439329, Nicosia, Cyprus) | D6: =SUMPRODUCT(('Fee Schedule'!$Q$6:$Q$30=$B6)*('Fee Schedule'!$G$6:$G$30<>"")*($C$3>='Fee Schedule'!$G$6:$G$30)*(('Fee Schedule'!$H$6:$H$30="")+($C$3<='Fee Schedule'!$H$6:$H$30))*('Fee Schedule'!$I$6:$I$30)) -> 10000 | I6: =SUM(D6:H6) -> 10000 | J6: =IFERROR(INDEX('Agreement Tracker'!$O$7:$O$15,MATCH($B6,'Agreement Tracker'!$B$7:$B$15,0)),0) -> 0.19 | K6: =I6*J6 -> 1900 | L6: =I6+K6 -> 11900 | P6: =IF($O6<>"","Paid",IF($N6<>"","Issued","Draft")) -> Draft
A7: 2 | B7: Kipseli | C7: =IFERROR(INDEX('Agreement Tracker'!$F$7:$F$15,MATCH($B7,'Agreement Tracker'!$B$7:$B$15,0)),"") -> Sunday Lifestyle, S.L. (Barcelona, Spain) | D7: =SUMPRODUCT(('Fee Schedule'!$Q$6:$Q$30=$B7)*('Fee Schedule'!$G$6:$G$30<>"")*($C$3>='Fee Schedule'!$G$6:$G$30)*(('Fee Schedule'!$H$6:$H$30="")+($C$3<='Fee Schedule'!$H$6:$H$30))*('Fee Schedule'!$I$6:$I$30)) -> 6000 | I7: =SUM(D7:H7) -> 6000 | J7: =IFERROR(INDEX('Agreement Tracker'!$O$7:$O$15,MATCH($B7,'Agreement Tracker'!$B$7:$B$15,0)),0) -> 0 | K7: =I7*J7 -> 0 | L7: =I7+K7 -> 6000 | P7: =IF($O7<>"","Paid",IF($N7<>"","Issued","Draft")) -> Draft
A8: 3 | B8: Blue Lagoon | C8: =IFERROR(INDEX('Agreement Tracker'!$F$7:$F$15,MATCH($B8,'Agreement Tracker'!$B$7:$B$15,0)),"") -> BTS Real Estate SM SA (Athens, Greece) | D8: =SUMPRODUCT(('Fee Schedule'!$Q$6:$Q$30=$B8)*('Fee Schedule'!$G$6:$G$30<>"")*($C$3>='Fee Schedule'!$G$6:$G$30)*(('Fee Schedule'!$H$6:$H$30="")+($C$3<='Fee Schedule'!$H$6:$H$30))*('Fee Schedule'!$I$6:$I$30)) -> 5000 | I8: =SUM(D8:H8) -> 5000 | J8: =IFERROR(INDEX('Agreement Tracker'!$O$7:$O$15,MATCH($B8,'Agreement Tracker'!$B$7:$B$15,0)),0) -> 0 | K8: =I8*J8 -> 0 | L8: =I8+K8 -> 5000 | P8: =IF($O8<>"","Paid",IF($N8<>"","Issued","Draft")) -> Draft
A9: 4 | B9: Evia Mare | C9: =IFERROR(INDEX('Agreement Tracker'!$F$7:$F$15,MATCH($B9,'Agreement Tracker'!$B$7:$B$15,0)),"") -> Diamond Star Real Estate Single Member (Athens, Greece) | D9: =SUMPRODUCT(('Fee Schedule'!$Q$6:$Q$30=$B9)*('Fee Schedule'!$G$6:$G$30<>"")*($C$3>='Fee Schedule'!$G$6:$G$30)*(('Fee Schedule'!$H$6:$H$30="")+($C$3<='Fee Schedule'!$H$6:$H$30))*('Fee Schedule'!$I$6:$I$30)) -> 3750 | I9: =SUM(D9:H9) -> 3750 | J9: =IFERROR(INDEX('Agreement Tracker'!$O$7:$O$15,MATCH($B9,'Agreement Tracker'!$B$7:$B$15,0)),0) -> 0 | K9: =I9*J9 -> 0 | L9: =I9+K9 -> 3750 | P9: =IF($O9<>"","Paid",IF($N9<>"","Issued","Draft")) -> Draft
A10: 5 | B10: Hotel Echo | C10: =IFERROR(INDEX('Agreement Tracker'!$F$7:$F$15,MATCH($B10,'Agreement Tracker'!$B$7:$B$15,0)),"") -> Oz Shlomi Single Member S.A. (Athens, Greece) | D10: =SUMPRODUCT(('Fee Schedule'!$Q$6:$Q$30=$B10)*('Fee Schedule'!$G$6:$G$30<>"")*($C$3>='Fee Schedule'!$G$6:$G$30)*(('Fee Schedule'!$H$6:$H$30="")+($C$3<='Fee Schedule'!$H$6:$H$30))*('Fee Schedule'!$I$6:$I$30)) -> 3500 | I10: =SUM(D10:H10) -> 3500 | J10: =IFERROR(INDEX('Agreement Tracker'!$O$7:$O$15,MATCH($B10,'Agreement Tracker'!$B$7:$B$15,0)),0) -> 0 | K10: =I10*J10 -> 0 | L10: =I10+K10 -> 3500 | P10: =IF($O10<>"","Paid",IF($N10<>"","Issued","Draft")) -> Draft
A11: 6 | B11: Thermalpark Spa Hotel (Obermain Therme) | C11: =IFERROR(INDEX('Agreement Tracker'!$F$7:$F$15,MATCH($B11,'Agreement Tracker'!$B$7:$B$15,0)),"") -> 613 Investment Group GmbH (HRB 4249, Coburg, Germany) | D11: =SUMPRODUCT(('Fee Schedule'!$Q$6:$Q$30=$B11)*('Fee Schedule'!$G$6:$G$30<>"")*($C$3>='Fee Schedule'!$G$6:$G$30)*(('Fee Schedule'!$H$6:$H$30="")+($C$3<='Fee Schedule'!$H$6:$H$30))*('Fee Schedule'!$I$6:$I$30)) -> 2500 | I11: =SUM(D11:H11) -> 2500 | J11: =IFERROR(INDEX('Agreement Tracker'!$O$7:$O$15,MATCH($B11,'Agreement Tracker'!$B$7:$B$15,0)),0) -> 0 | K11: =I11*J11 -> 0 | L11: =I11+K11 -> 2500 | P11: =IF($O11<>"","Paid",IF($N11<>"","Issued","Draft")) -> Draft
A12: 7 | B12: City Hall Hotel (Bären Areal) | C12: =IFERROR(INDEX('Agreement Tracker'!$F$7:$F$15,MATCH($B12,'Agreement Tracker'!$B$7:$B$15,0)),"") -> 613 Investment Group GmbH (HRB 4249, Coburg, Germany) | D12: =SUMPRODUCT(('Fee Schedule'!$Q$6:$Q$30=$B12)*('Fee Schedule'!$G$6:$G$30<>"")*($C$3>='Fee Schedule'!$G$6:$G$30)*(('Fee Schedule'!$H$6:$H$30="")+($C$3<='Fee Schedule'!$H$6:$H$30))*('Fee Schedule'!$I$6:$I$30)) -> 2500 | I12: =SUM(D12:H12) -> 2500 | J12: =IFERROR(INDEX('Agreement Tracker'!$O$7:$O$15,MATCH($B12,'Agreement Tracker'!$B$7:$B$15,0)),0) -> 0 | K12: =I12*J12 -> 0 | L12: =I12+K12 -> 2500 | P12: =IF($O12<>"","Paid",IF($N12<>"","Issued","Draft")) -> Draft
A13: 8 | B13: Boutique Hotels Portfolio Retainer (5 hotels) | C13: =IFERROR(INDEX('Agreement Tracker'!$F$7:$F$15,MATCH($B13,'Agreement Tracker'!$B$7:$B$15,0)),"") -> 613 Investment Group GmbH (HRB 4249, Coburg, Germany) | D13: =SUMPRODUCT(('Fee Schedule'!$Q$6:$Q$30=$B13)*('Fee Schedule'!$G$6:$G$30<>"")*($C$3>='Fee Schedule'!$G$6:$G$30)*(('Fee Schedule'!$H$6:$H$30="")+($C$3<='Fee Schedule'!$H$6:$H$30))*('Fee Schedule'!$I$6:$I$30)) -> 2000 | I13: =SUM(D13:H13) -> 2000 | J13: =IFERROR(INDEX('Agreement Tracker'!$O$7:$O$15,MATCH($B13,'Agreement Tracker'!$B$7:$B$15,0)),0) -> 0 | K13: =I13*J13 -> 0 | L13: =I13+K13 -> 2000 | P13: =IF($O13<>"","Paid",IF($N13<>"","Issued","Draft")) -> Draft
A14: 9 | B14: Thermalpark Residenz (Residence 58) | C14: =IFERROR(INDEX('Agreement Tracker'!$F$7:$F$15,MATCH($B14,'Agreement Tracker'!$B$7:$B$15,0)),"") -> 613 Investment Group GmbH (HRB 4249, Coburg, Germany) | D14: =SUMPRODUCT(('Fee Schedule'!$Q$6:$Q$30=$B14)*('Fee Schedule'!$G$6:$G$30<>"")*($C$3>='Fee Schedule'!$G$6:$G$30)*(('Fee Schedule'!$H$6:$H$30="")+($C$3<='Fee Schedule'!$H$6:$H$30))*('Fee Schedule'!$I$6:$I$30)) -> 2000 | I14: =SUM(D14:H14) -> 2000 | J14: =IFERROR(INDEX('Agreement Tracker'!$O$7:$O$15,MATCH($B14,'Agreement Tracker'!$B$7:$B$15,0)),0) -> 0 | K14: =I14*J14 -> 0 | L14: =I14+K14 -> 2000 | P14: =IF($O14<>"","Paid",IF($N14<>"","Issued","Draft")) -> Draft
B15: TOTAL ISSUED THIS MONTH | D15: =SUM(D6:D14) -> 37250 | E15: =SUM(E6:E14) -> 0 | F15: =SUM(F6:F14) -> 0 | G15: =SUM(G6:G14) -> 0 | H15: =SUM(H6:H14) -> 0 | I15: =SUM(I6:I14) -> 37250 | K15: =SUM(K6:K14) -> 1900 | L15: =SUM(L6:L14) -> 39150

Sheet Legend & Notes
A1: RABONA HOLDINGS — TRACKER LEGEND & GUIDANCE
A3: How to use this workbook
A4: • | B4: Each row = one Rabona Holdings service agreement, used as the master source for monthly invoicing.
A5: • | B5: Header row and the Project Name column are frozen; every column has a filter (drop-down arrow on the header).
A6: • | B6: Yellow cells = values to confirm (currently the VAT columns). Replace with the confirmed value.
A7: • | B7: To add a project: type into the first empty formatted row (rows are pre-formatted to row 40). Drop-downs and colour-coding apply automatically.
A8: • | B8: Status colour-codes automatically: Active (green), On Hold (amber), Completed (blue), Terminated (red).
A10: Column definitions
A11: Agreement Signing Date | B11: Date the agreement was executed/entered into (for the 613 retainer & Residenz: executed 17 Jul 2026, dated 12 Jul 2026).
A12: Client (Legal Entity) | B12: The contracting client entity and its registration/jurisdiction — the party invoiced.
A13: Contact Email | B13: Recipient(s) for monthly invoice issuance. Semicolons separate multiple 'To' addresses; 'cc:' shown where a copy is required.
A14: Monthly Invoice Date | B14: Timing/day the invoice is issued each month (advance vs arrears where the agreement specifies).
A15: Monthly Fee | B15: The fee currently in effect. Phased/stage schedules are given in full in Notes.
A16: VAT Applicable / VAT Rate | B16: Whether Rabona adds VAT and at what rate. Currently assumptions (yellow) — see VAT note below.
A17: Status | B17: Active / On Hold / Completed / Terminated.
A18: Notes | B18: Full fee schedule, completion/bonus terms, payment terms, secondary contacts and any items to confirm.
A20: Open items to confirm
A21: VAT treatment | B21: Rabona is Cyprus-registered. Cross-border EU B2B services are shown as reverse charge (VAT = No). Urban City 44 (client Evimer Ltd, Cyprus) is tentatively shown as Cyprus-domestic 19%. Services connected to immovable property may instead be taxed where each property is located — please confirm the correct treatment per project with your tax advisor.
A22: Monthly invoice day | B22: Only Kipseli specifies a calendar day (on/before the 25th). For the others the agreement states advance/arrears but not a day — set your standard issue day.
A23: Current stage / fee | B23: Spa Hotel, City Hall and Hotel Echo use stage/milestone-based fees. The 'Monthly Fee' shows the assumed current stage — confirm which stage each is in today.
A24: Contact positions / phones | B24: Some contact positions and a couple of phone numbers were not stated in the agreements — please complete.
A25: Statuses | B25: All set to Active. Adjust any that are On Hold, Completed or Terminated.
